[
  {
    "id": "_EHmnmGVSDI",
    "title": "Python Crash Course (Hebrew) - קורס מקיף בפייתון",
    "score": 110
  },
  {
    "id": "jwmU-L8ihwg",
    "title": "מדריך פייתון - 31 - טאפלים",
    "score": 110
  },
  {
    "id": "ZZCnfRmxq6s",
    "title": "מדריך פייתון - 18- String Formats",
    "score": 110
  },
  {
    "id": "WzbyPDDN6v0",
    "title": "מדריך פייתון - 22 - פונקציית range",
    "score": 110
  },
  {
    "id": "o0wyYsNbJeY",
    "title": "קורס פייתון מלא למתחילים",
    "score": 110
  },
  {
    "id": "oXzPqxrynzY",
    "title": "שיפוץ רהיטים ויצירת אדנית הולנדית",
    "score": 60
  },
  {
    "id": "uCATRNZY7TM",
    "title": "סדנת שיפוץ רהיטים בדנדש - תכנית חיסכון",
    "score": 60
  },
  {
    "id": "hyt5EPbrNeI",
    "title": "איך מחדשים רהיט עץ מלא",
    "score": 60
  },
  {
    "id": "GGZocUaWTwc",
    "title": "חידוש רהיטים - שיפוץ רהיטים",
    "score": 60
  },
  {
    "id": "IZxyO3zm0dY",
    "title": "שחזור כיור רחצה מעץ אלם (נחשף גימור עץ מדהים)",
    "score": 60
  },
  {
    "id": "B-CoK1bYpv8",
    "title": "שיקום \\\"אשפה לאוצר\\\" | שיקום רהיטים",
    "score": 60
  },
  {
    "id": "fNX8tKnozF0",
    "title": "פייתון למתחילים - ללמוד פייתון בשעה וחצי",
    "score": 60
  },
  {
    "id": "byLFiFawEuY",
    "title": "סביבת עבודה",
    "score": 60
  },
  {
    "id": "gjLP9A19L_I",
    "title": "מבוא",
    "score": 60
  },
  {
    "id": "SDQEaJY291A",
    "title": "How to sketch anything intro",
    "score": 50
  },
  {
    "id": "1OLI4qiHh9Q",
    "title": "how to draw hand for beginners ✋",
    "score": 50
  },
  {
    "id": "ug-d9uzr8v8",
    "title": "Multi-million-dollar river restoration project underway",
    "score": 50
  },
  {
    "id": "xAansOUEmmk",
    "title": "This might be my favourite restoration project of this year!",
    "score": 50
  },
  {
    "id": "Cg5qqai54_A",
    "title": "Couple Turns Abandoned Shed Into Cozy Home | Full Renovation by @project.restoration",
    "score": 50
  },
  {
    "id": "E2XjTQf_sMg",
    "title": "1920's Vintage Scale Restoration - A Scale That Every American Once Knew",
    "score": 50
  },
  {
    "id": "BZmoJh-iyZE",
    "title": "KAWASAKI Ninja Full Restoration | Restored KAWASAKI Four-stroke Sport Motorcycle",
    "score": 50
  },
  {
    "id": "xvexIbE5WCg",
    "title": "Absolute disaster turns satisfying restoration project.",
    "score": 50
  },
  {
    "id": "54mpymkZruc",
    "title": "Restore a truck they said, it’ll be fun they said | 359 Peterbilt Restoration (Pocket Change) ",
    "score": 50
  },
  {
    "id": "Jiqkmg8jl1M",
    "title": "From Completely Destroyed to Perfectly Functional – The Ultimate Steel Gear Restoration Project",
    "score": 50
  },
  {
    "id": "v9C2YnZqyIQ",
    "title": "Restoration the Miter Saw I bought for $10",
    "score": 50
  },
  {
    "id": "mqCP82rubho",
    "title": "Wrecked Mazda RX-7 Restoration | Full JDM Transformation Project",
    "score": 50
  },
  {
    "id": "guhgcnqstck",
    "title": "Saving A Massive Historic Ship  - The Aurora Restoration Project",
    "score": 50
  },
  {
    "id": "rkG_dZ_YT0I",
    "title": "IZH-49 from 1952 | Full Rusted Shotgun Restoration",
    "score": 50
  },
  {
    "id": "zQwDRRnuqTY",
    "title": "Unbelievable Restoration 💎 Restoring a $1.5 Million 1988 Mercedes-Benz 300SL #restoration",
    "score": 50
  },
  {
    "id": "oU2UuAFsi80",
    "title": "Medieval Manor Restoration - The Restoration Man - S02 EP6 - Home Renovation",
    "score": 50
  },
  {
    "id": "ZioqHNFv6Ag",
    "title": "Full Build: From Rusted Out 1961 Chevy Impala to Revved Up Red Sled",
    "score": 50
  },
  {
    "id": "MdBI_0OmNW4",
    "title": "Trash to TREASURE Restoration | Furniture Restoration",
    "score": 50
  },
  {
    "id": "PKtuu8XZZ9k",
    "title": "Finesse2tymes explains how he makes hundreds of thousands from music + meeting King ",
    "score": 50
  },
  {
    "id": "JRv-gA_3jPk",
    "title": "The Abyss | Deep Sea Documentary for Sleep (4K)",
    "score": 50
  },
  {
    "id": "6gLqIYJiz1w",
    "title": "Finesse 2x previews lil king diss song \"},{\"text\":\"#rap\",\"navigationEndpoint\":{\"clickTrackingParams\":\"CMsCENbKAxgJIhMItvvfgpizkgMVGhtoCB23PAsrygEEVPHr1A==\",\"commandMetadata\":{\"webCommandMetadata\":{\"url\":\"/hashtag/rap\",\"webPageType\":\"WEB_PAGE_TYPE_BROWSE\",\"rootVe\":6827,\"apiUrl\":\"/youtubei/v1/browse\"}},\"browseEndpoint\":{\"browseId\":\"FEhashtag\",\"params\":\"6gUHCgNyYXAYAQ%3D%3D\"}},\"loggingDirectives\":{\"trackingParams\":\"CMsCENbKAxgJIhMItvvfgpizkgMVGhtoCB23PAsr\",\"visibility\":{\"types\":\"12\"}}},{\"text\":\" \"},{\"text\":\"#viralvideo\",\"navigationEndpoint\":{\"clickTrackingParams\":\"CMoCENbKAxgLIhMItvvfgpizkgMVGhtoCB23PAsrygEEVPHr1A==\",\"commandMetadata\":{\"webCommandMetadata\":{\"url\":\"/hashtag/viralvideo\",\"webPageType\":\"WEB_PAGE_TYPE_BROWSE\",\"rootVe\":6827,\"apiUrl\":\"/youtubei/v1/browse\"}},\"browseEndpoint\":{\"browseId\":\"FEhashtag\",\"params\":\"6gUOCgp2aXJhbHZpZGVvGAE%3D\"}},\"loggingDirectives\":{\"trackingParams\":\"CMoCENbKAxgLIhMItvvfgpizkgMVGhtoCB23PAsr\",\"visibility\":{\"types\":\"12\"}}},{\"text\":\" \"},{\"text\":\"#hiphop\",\"navigationEndpoint\":{\"clickTrackingParams\":\"CMkCENbKAxgNIhMItvvfgpizkgMVGhtoCB23PAsrygEEVPHr1A==\",\"commandMetadata\":{\"webCommandMetadata\":{\"url\":\"/hashtag/hiphop\",\"webPageType\":\"WEB_PAGE_TYPE_BROWSE\",\"rootVe\":6827,\"apiUrl\":\"/youtubei/v1/browse\"}},\"browseEndpoint\":{\"browseId\":\"FEhashtag\",\"params\":\"6gUKCgZoaXBob3AYAQ%3D%3D\"}},\"loggingDirectives\":{\"trackingParams\":\"CMkCENbKAxgNIhMItvvfgpizkgMVGhtoCB23PAsr\",\"visibility\":{\"types\":\"12\"}}},{\"text\":\" \"},{\"text\":\"#fng\",\"navigationEndpoint\":{\"clickTrackingParams\":\"CMgCENbKAxgPIhMItvvfgpizkgMVGhtoCB23PAsrygEEVPHr1A==\",\"commandMetadata\":{\"webCommandMetadata\":{\"url\":\"/hashtag/fng\",\"webPageType\":\"WEB_PAGE_TYPE_BROWSE\",\"rootVe\":6827,\"apiUrl\":\"/youtubei/v1/browse\"}},\"browseEndpoint\":{\"browseId\":\"FEhashtag\",\"params\":\"6gUHCgNmbmcYAQ%3D%3D\"}},\"loggingDirectives\":{\"trackingParams\":\"CMgCENbKAxgPIhMItvvfgpizkgMVGhtoCB23PAsr\",\"visibility\":{\"types\":\"12\"}}},{\"text\":\" \"},{\"text\":\"#hiphopartist\",\"navigationEndpoint\":{\"clickTrackingParams\":\"CMcCENbKAxgRIhMItvvfgpizkgMVGhtoCB23PAsrygEEVPHr1A==\",\"commandMetadata\":{\"webCommandMetadata\":{\"url\":\"/hashtag/hiphopartist\",\"webPageType\":\"WEB_PAGE_TYPE_BROWSE\",\"rootVe\":6827,\"apiUrl\":\"/youtubei/v1/browse\"}},\"browseEndpoint\":{\"browseId\":\"FEhashtag\",\"params\":\"6gUQCgxoaXBob3BhcnRpc3QYAQ%3D%3D\"}},\"loggingDirectives\":{\"trackingParams\":\"CMcCENbKAxgRIhMItvvfgpizkgMVGhtoCB23PAsr\",\"visibility\":{\"types\":\"12\"}}},{\"text\":\" \"},{\"text\":\"#finesse\",\"navigationEndpoint\":{\"clickTrackingParams\":\"CMYCENbKAxgTIhMItvvfgpizkgMVGhtoCB23PAsrygEEVPHr1A==\",\"commandMetadata\":{\"webCommandMetadata\":{\"url\":\"/hashtag/finesse\",\"webPageType\":\"WEB_PAGE_TYPE_BROWSE\",\"rootVe\":6827,\"apiUrl\":\"/youtubei/v1/browse\"}},\"browseEndpoint\":{\"browseId\":\"FEhashtag\",\"params\":\"6gULCgdmaW5lc3NlGAE%3D\"}},\"loggingDirectives\":{\"trackingParams\":\"CMYCENbKAxgTIhMItvvfgpizkgMVGhtoCB23PAsr\",\"visibility\":{\"types\":\"12\"}}},{\"text\":\" \"},{\"text\":\"#memphis\",\"navigationEndpoint\":{\"clickTrackingParams\":\"CMUCENbKAxgVIhMItvvfgpizkgMVGhtoCB23PAsrygEEVPHr1A==\",\"commandMetadata\":{\"webCommandMetadata\":{\"url\":\"/hashtag/memphis\",\"webPageType\":\"WEB_PAGE_TYPE_BROWSE\",\"rootVe\":6827,\"apiUrl\":\"/youtubei/v1/browse\"}},\"browseEndpoint\":{\"browseId\":\"FEhashtag\",\"params\":\"6gULCgdtZW1waGlzGAE%3D\"}},\"loggingDirectives\":{\"trackingParams\":\"CMUCENbKAxgVIhMItvvfgpizkgMVGhtoCB23PAsr\",\"visibility\":{\"types\":\"12\"}}}]},\"viewCount\":{\"videoViewCountRenderer\":{\"viewCount\":{\"simpleText\":\"452,297 views\"},\"shortViewCount\":{\"simpleText\":\"452K views\"},\"originalViewCount\":\"0\"}},\"videoActions\":{\"menuRenderer\":{\"items\":[{\"menuServiceItemRenderer\":{\"text\":{\"runs\":[{\"text\":\"Report",
    "score": 50
  },
  {
    "id": "jE8C0FHWuks",
    "title": "20 Future Technologies That Will Change The World",
    "score": 50
  },
  {
    "id": "RM717Aj_VKQ",
    "title": "15 CRAZY FUTURE TECHNOLOGY IDEAS YOU'LL SEE SOON",
    "score": 50
  },
  {
    "id": "Hb5sRAzY6Jc",
    "title": "The World In 2060: Top 15 Future Technologies",
    "score": 50
  },
  {
    "id": "YqBl2h_1vWI",
    "title": "The Year 3000 \\u0026 Beyond: 300 Future Technologies",
    "score": 50
  },
  {
    "id": "b0HfmY64eSE",
    "title": "$1 vs $1,000,000,000 Futuristic Tech!",
    "score": 50
  },
  {
    "id": "q6Fh07zQ2KU",
    "title": "What Makes Good Brush Work? - Oil Painting Instruction",
    "score": 50
  },
  {
    "id": "bZ-iV7aAouA",
    "title": "Introduction: What Makes a Good Glaze?",
    "score": 50
  },
  {
    "id": "25EVQncFaf4",
    "title": "Color Theory Lesson",
    "score": 50
  },
  {
    "id": "By5ryf3wbAw",
    "title": "Oil Painting Techniques for Beginners, RISD Art Professor Demo, Part 1 of 2",
    "score": 50
  },
  {
    "id": "JRd6htjbd6Q",
    "title": "How Elon Musk will Build Moon Base Alpha: Inside SpaceX's Ultimate Survival Plan",
    "score": 50
  },
  {
    "id": "7XCFc6JfJIg",
    "title": "Python Tutorial For Beginners in Hindi | Complete Python Course 🔥",
    "score": 50
  },
  {
    "id": "XKHEtdqhLK8",
    "title": "1.Python tutorial for beginners",
    "score": 50
  },
  {
    "id": "nLRL_NcnK-4",
    "title": "Python for AI - Full Beginner Course",
    "score": 50
  },
  {
    "id": "ygXn5nV5qFc",
    "title": "Introduction: Learn Python for AI",
    "score": 50
  },
  {
    "id": "pqCCn72LXP0",
    "title": "Python Tutorial: Starting a New Project | Lesson 1",
    "score": 50
  },
  {
    "id": "qANjueE_EkE",
    "title": "Python Guide: Why You Should Learn Python in 2025?",
    "score": 50
  },
  {
    "id": "uIiy30Cxb_w",
    "title": "Python Full Course for Beginners",
    "score": 50
  },
  {
    "id": "c0ZW0GIRp7Q",
    "title": "Python Guide: Installing Python and a Workspace on Your Computer",
    "score": 50
  },
  {
    "id": "pIBZHGbI5jQ",
    "title": "Haymaker we apologize to nobody",
    "score": 50
  },
  {
    "id": "KZLYHdZOMvc",
    "title": "How To Use Search Filters In WhatsApp (Updated)",
    "score": 50
  },
  {
    "id": "ppHZTjKZomI",
    "title": "Designing UX for search filters #figma #prototype #tutorial #beginners #uidesign #ux #filter",
    "score": 50
  },
  {
    "id": "MN6Fmdz5uLk",
    "title": "How to Use Search Filters on Netflix app 🔎 (step-by-step for beginners)",
    "score": 50
  },
  {
    "id": "XjCjhAN-Pcc",
    "title": "How to Use Search Filters",
    "score": 50
  },
  {
    "id": "xAqCEBFGdYk",
    "title": "YouTube Search Filter Missing? Fix it now | How to fix missing search filter",
    "score": 50
  },
  {
    "id": "cplkrqJT8r4",
    "title": "how to mold a sleek ponytail",
    "score": 50
  },
  {
    "id": "i2gVzZRT6O4",
    "title": "How to Attach Braiding Hair to a Ponytail | Easy Braid Tutorial #braidtutorial #protectivestyles",
    "score": 50
  },
  {
    "id": "cq5zMXlcxHc",
    "title": "🔥How to do a High Sleek Fluffy Natural Ponytail on Short 4C Natural Hair | #ponytail",
    "score": 50
  },
  {
    "id": "0oi-XOHeYAc",
    "title": "How To Make A Ponytail ⭐️",
    "score": 50
  },
  {
    "id": "uDT5gCwItC0",
    "title": "💘How About Red Color Slick Back Ponytail? Tutorial For Hair Extensions~ High Pony Look #Elfinhair",
    "score": 50
  },
  {
    "id": "vVmwuuOgnxU",
    "title": "🍀Barbie Ponytail Sleeking + Swoop Tutorial | ELFIN HAIR #transformation #extension #viral",
    "score": 50
  },
  {
    "id": "n5FRon9CONU",
    "title": "How to do a Basic Ponytail",
    "score": 50
  },
  {
    "id": "g8SMElzGJxo",
    "title": "Ambika- The Mango, The Myth, The Legend |A Milestone To Remember Among Hybrids| Complete Review",
    "score": 50
  },
  {
    "id": "8JAcNoZZ8vY",
    "title": "How to Wear a Claw Clip | Easy Hairstyles",
    "score": 50
  },
  {
    "id": "VClvCzZ5G9Y",
    "title": "How To Make a Smash Burger",
    "score": 50
  },
  {
    "id": "19X0o_X8qnk",
    "title": "JUMBO BRAID PONYTAIL✨HEATLESS EXTENDED TWO BRAID PONYTAIL TUTORIAL ON NATURAL HAIR FT.#ULAHAIR",
    "score": 50
  },
  {
    "id": "KrIOEV6QOI0",
    "title": "MY TECHNIQUES! SLEEK MID BACK BRAIDED PONYTAIL!| NATURAL HAIR TO SLEEK| iamroxybennett Ponytails",
    "score": 50
  },
  {
    "id": "dbrmp3FSuuc",
    "title": "HOW TO DO A PONYTAIL WITH BRAID HAIR 🤫",
    "score": 50
  },
  {
    "id": "2l8OnlNiAEc",
    "title": "How to braided ponytail for short hair",
    "score": 50
  },
  {
    "id": "bLcYQnrssYA",
    "title": "JUMBO BRAID PONYTAIL USING BRAIDING HAIR | how to",
    "score": 50
  },
  {
    "id": "ZiDt5fQep88",
    "title": "HOW TO: SLEEK BRAIDED PONYTAIL 😍 #sleekponytail  #natural #ponytail",
    "score": 50
  },
  {
    "id": "0WzWP1ygSwA",
    "title": "Butterfly Ponytail #ponytailstyles #hair #hairtutorial #natrualhair #braidedponytail",
    "score": 50
  },
  {
    "id": "Wrn9pIxzTbI",
    "title": "Prison bully bullied rural girl, but girl killed her with one move,make them recognize new boss！",
    "score": 50
  },
  {
    "id": "4HrWCMMQ0wI",
    "title": "Monkeys are more than Just Funny! | 4K Nature Documentary",
    "score": 50
  },
  {
    "id": "eFj0byHLx4A",
    "title": "$220 Billion Bank Scandal: How Nordics Bank Committed the Largest Money Laundering Scheme in History",
    "score": 50
  },
  {
    "id": "YTq-E3YIICY",
    "title": "How to Make the PERFECT Press Joint",
    "score": 50
  },
  {
    "id": "-CAUZC705y4",
    "title": "Binance Tutorial 2026 Start Binance Step by Step (Payback, Welcome Bonus) #BinanceTutorial #Binance",
    "score": 50
  },
  {
    "id": "7CEPV1b_qZA",
    "title": "CUET PG 2026 Step by Step Correction Window | How to use correction window of CUET PG Form 2026",
    "score": 50
  },
  {
    "id": "Gz2KcNwNpuk",
    "title": "How To Draw Rumi From KPop Demon Hunters",
    "score": 50
  },
  {
    "id": "x95D8umOU8Q",
    "title": "Tomake | তোমাকে | Parineeta | Arko | Shreya Ghoshal | Subhashree | Ritwick | Raj Chakraborty",
    "score": 50
  },
  {
    "id": "ao2IP7f23-8",
    "title": "drawing a curve right here in the middle of our paper",
    "score": 10
  },
  {
    "id": "7SWvlUd2at8",
    "title": "hooplakidz Doodle",
    "score": 10
  },
  {
    "id": "8O35tkIqtfU",
    "title": "5 BEGINNER Drawing Exercises to IMPROVE Fast (Do these First!)",
    "score": 10
  },
  {
    "id": "YlddL1A9rgk",
    "title": "Secret Treasure Inside - Restoring a French Cash Register with Hidden Money",
    "score": 10
  },
  {
    "id": "F30RCJQ2tsY",
    "title": "I Bought a $1,900 Swamp Boat Wreck and Rebuilt It Back to Sea Trial Ready",
    "score": 10
  },
  {
    "id": "2sU-2SHK9qU",
    "title": "Search filters",
    "score": 10
  },
  {
    "id": "zGg7tDu9vXM",
    "title": "Extreme Constructions | Complete Series | All Episodes | FD Engineering",
    "score": 10
  },
  {
    "id": "GJIxBKOwa-E",
    "title": "Inside the Sub That Reached Earth's Deepest Point | Bathyscaphe Trieste",
    "score": 10
  },
  {
    "id": "FmR14Yng9kI",
    "title": "Introduction to Deep Sea Gigantism",
    "score": 10
  },
  {
    "id": "t_S_cN2re4g",
    "title": "20 New Deep Sea Creature Encounters Caught on Camera in Hawaii 2025 | Mega ROV Countdown № 2",
    "score": 10
  },
  {
    "id": "Jc7ogKSFs_4",
    "title": "The Bridge at Dusk - Alternate Version by Jim Gifford [from Waterwick: Prologue Short Film Soundtrack]",
    "score": 10
  },
  {
    "id": "PSBwp63FUhc",
    "title": "The Anunnaki and Human Origins",
    "score": 10
  },
  {
    "id": "LnHD1OJclYw",
    "title": "Finesse King | Lor Liq | Big Bag",
    "score": 10
  },
  {
    "id": "yB0dkfqjr0E",
    "title": "Transcript",
    "score": 10
  },
  {
    "id": "kE-IJLXd4ZI",
    "title": "Intro",
    "score": 10
  },
  {
    "id": "5VuW76Bc5Mw",
    "title": "2030",
    "score": 10
  },
  {
    "id": "L2pMSsfLoSM",
    "title": "Conscious AI",
    "score": 10
  },
  {
    "id": "wrJsExM8D-o",
    "title": "Intro",
    "score": 10
  },
  {
    "id": "SwkGVPh8jYs",
    "title": "20 Space Megastructures That Will Transform Our Future",
    "score": 10
  },
  {
    "id": "o41gYSHXMKo",
    "title": "Kardashev Scale Explained: Type 1 to Type 7 Civilizations",
    "score": 10
  },
  {
    "id": "8hJuF8EZmuM",
    "title": "The Kardashev Scale: Type 1 to Type 7 Civilizations",
    "score": 10
  },
  {
    "id": "SzMiJFOa6w8",
    "title": "Artificial General Intelligence",
    "score": 10
  },
  {
    "id": "pAnGwRiQ4-4",
    "title": "The Future of AI: 130 Predictions",
    "score": 10
  },
  {
    "id": "gSBGNv9f8vU",
    "title": "AI In The Next 5 Years (2026 to 2030)",
    "score": 10
  },
  {
    "id": "5fTNGvuPTMU",
    "title": "Type 1 Civilization (Planetary)",
    "score": 10
  },
  {
    "id": "wD6hyGXRcgk",
    "title": "Universal Translator",
    "score": 10
  },
  {
    "id": "T-F-vVNVQ50",
    "title": "Intro",
    "score": 10
  },
  {
    "id": "Oa9aWdcCC4o",
    "title": "Introduction",
    "score": 10
  },
  {
    "id": "zAmZ7tS2Cdk",
    "title": "Intro",
    "score": 10
  },
  {
    "id": "9He9hoo3agk",
    "title": "AI In The Next 5 Years (2026 to 2030)",
    "score": 10
  },
  {
    "id": "m-Wbn1htwdY",
    "title": "20 Space Megastructures That Could Transform Our Future",
    "score": 10
  },
  {
    "id": "0sGd38Hy4ng",
    "title": "1. Colony Starships",
    "score": 10
  },
  {
    "id": "KFpFcPtzXSA",
    "title": "Finesse2Tymes Speaks Out \\u0026 Responds To Lil King's Apology.",
    "score": 10
  },
  {
    "id": "hOfn1ff8ZDw",
    "title": "Finesse2tymes GOES OFF On Lil King For His Daughter",
    "score": 10
  },
  {
    "id": "Zv_OkJfgheM",
    "title": "USE AN UNDERPAINTING",
    "score": 10
  },
  {
    "id": "m2kU8JXL0JU",
    "title": "Introduction",
    "score": 10
  },
  {
    "id": "DGGy6DvbXu8",
    "title": "Intro Graphics and Music",
    "score": 10
  },
  {
    "id": "2QP8uJCSD2g",
    "title": "Intro",
    "score": 10
  },
  {
    "id": "8L66Zlc8T24",
    "title": "Photographic References",
    "score": 10
  },
  {
    "id": "XzYRCOGDa88",
    "title": "Intro",
    "score": 10
  },
  {
    "id": "A2gsfar6RaM",
    "title": "Intro",
    "score": 10
  },
  {
    "id": "ZdfAR6oeylM",
    "title": "Intro",
    "score": 10
  },
  {
    "id": "jYtwUPi6Rsw",
    "title": "Negative Space",
    "score": 10
  },
  {
    "id": "0H9OiRWAMMw",
    "title": "Intro",
    "score": 10
  },
  {
    "id": "gp-lY7WcqkQ",
    "title": "Intro",
    "score": 10
  },
  {
    "id": "7nnR69HiSTU",
    "title": "Ultraglazing",
    "score": 10
  },
  {
    "id": "zYQd41u1niw",
    "title": "Surface is fundamental",
    "score": 10
  },
  {
    "id": "F7qS1lvjGAs",
    "title": "Intro",
    "score": 10
  },
  {
    "id": "dPw8J2G7cqI",
    "title": "Oil Painting Basics",
    "score": 10
  },
  {
    "id": "ucdrgul9T2g",
    "title": "FNG King Goes OFF On Finesse 2 Tymes For Snitch Rumors \"},{\"text\":\"#drill\",\"navigationEndpoint\":{\"clickTrackingParams\":\"CL0CENbKAxgJIhMI2NTcgpizkgMVyC5oCB0tEzsvygEEeKhGQQ==\",\"commandMetadata\":{\"webCommandMetadata\":{\"url\":\"/hashtag/drill\",\"webPageType\":\"WEB_PAGE_TYPE_BROWSE\",\"rootVe\":6827,\"apiUrl\":\"/youtubei/v1/browse\"}},\"browseEndpoint\":{\"browseId\":\"FEhashtag\",\"params\":\"6gUJCgVkcmlsbBgB\"}},\"loggingDirectives\":{\"trackingParams\":\"CL0CENbKAxgJIhMI2NTcgpizkgMVyC5oCB0tEzsv\",\"visibility\":{\"types\":\"12\"}}},{\"text\":\" \"},{\"text\":\"#chiraq\",\"navigationEndpoint\":{\"clickTrackingParams\":\"CLwCENbKAxgLIhMI2NTcgpizkgMVyC5oCB0tEzsvygEEeKhGQQ==\",\"commandMetadata\":{\"webCommandMetadata\":{\"url\":\"/hashtag/chiraq\",\"webPageType\":\"WEB_PAGE_TYPE_BROWSE\",\"rootVe\":6827,\"apiUrl\":\"/youtubei/v1/browse\"}},\"browseEndpoint\":{\"browseId\":\"FEhashtag\",\"params\":\"6gUKCgZjaGlyYXEYAQ%3D%3D\"}},\"loggingDirectives\":{\"trackingParams\":\"CLwCENbKAxgLIhMI2NTcgpizkgMVyC5oCB0tEzsv\",\"visibility\":{\"types\":\"12\"}}}]},\"viewCount\":{\"videoViewCountRenderer\":{\"viewCount\":{\"simpleText\":\"339,688 views\"},\"shortViewCount\":{\"simpleText\":\"339K views\"},\"originalViewCount\":\"0\"}},\"videoActions\":{\"menuRenderer\":{\"items\":[{\"menuServiceItemRenderer\":{\"text\":{\"runs\":[{\"text\":\"Report",
    "score": 10
  },
  {
    "id": "C3iHAgwIYtI",
    "title": "Starship | Second Flight Test",
    "score": 10
  },
  {
    "id": "gWMYYu8ijoI",
    "title": "See SpaceX Starship's 10th launch in epic 4K slow motion",
    "score": 10
  },
  {
    "id": "PaPm0a8SIUM",
    "title": "NASA's SpaceX Crew-7 Launch (Official NASA Broadcast in 4K)",
    "score": 10
  },
  {
    "id": "QD2XDoeT8SI",
    "title": "Artemis-1 Launch Cinematic 4K (FULL VOLUME) No Music (NASA's SLS Rocket)",
    "score": 10
  },
  {
    "id": "zctTKdQcmVA",
    "title": "Starship | Tenth Flight Test",
    "score": 10
  },
  {
    "id": "rcd_SQZDlnk",
    "title": "SPLASHDOWN! SpaceX Starship 11th Flight Test [4K]",
    "score": 10
  },
  {
    "id": "vf_WTkIExgY",
    "title": "Blastoff! SpaceX Starship launches on 5th flight, nails 'chopsticks' booster catch!",
    "score": 10
  },
  {
    "id": "b28zbsnk-48",
    "title": "Time lapse of the SpaceX Falcon 9 rocket launch from Huntington Beach, CA - 4K version",
    "score": 10
  },
  {
    "id": "-x7ruR5Vygc",
    "title": "Starship | Seventh Flight Test",
    "score": 10
  },
  {
    "id": "Pn6e1O5bEyA",
    "title": "[4K] SpaceX Starship Flight 9 Launch | Drone Cam",
    "score": 10
  },
  {
    "id": "mhJRzQsLZGg",
    "title": "Everything About First SpaceX Starship V3 Launch You Should Know",
    "score": 10
  },
  {
    "id": "tnp5zB01m1s",
    "title": "Flight 12 preparations",
    "score": 10
  },
  {
    "id": "Jm8wRjD3xVA",
    "title": "SpaceX Starship Pad 2 just Fully TESTED X100 than ever. New Starship V3 Launch Date...",
    "score": 10
  },
  {
    "id": "Fayc9nxu9lI",
    "title": "What SpaceX JUST Announced RAPTOR Production Is INSANE! And NO Company Comes Close",
    "score": 10
  },
  {
    "id": "KYjdRIMkM3c",
    "title": "Elon Musk Reveals Next Step before Starship Flight 12 Launch. NASA’s Artemis 2 Sooner...REPLAY#69",
    "score": 10
  },
  {
    "id": "dmRkwLfHSK0",
    "title": "The Most Beautiful Earth Scenes Captured in 4K HDR (60FPS) |",
    "score": 10
  },
  {
    "id": "CShz8rvng20",
    "title": "What SpaceX Just Confirmed About Moon Mission — And Why It Changes the Moon Race",
    "score": 10
  },
  {
    "id": "KwuZoAZo0PQ",
    "title": "Intro",
    "score": 10
  },
  {
    "id": "hI9HQfCAw64",
    "title": "SpaceX Starship 11th Flight Test [4K]",
    "score": 10
  },
  {
    "id": "MgMNo7q5P0U",
    "title": "SPLASHDOWN! SpaceX Starship 11th Flight Test [4K]",
    "score": 10
  },
  {
    "id": "lchtXWn8SOw",
    "title": "4K Footage | SpaceX Launches",
    "score": 10
  },
  {
    "id": "gmJgW-yMAIg",
    "title": "FULL LAUNCH! SpaceX Starship 11th Flight Test",
    "score": 10
  },
  {
    "id": "K0NOSJF1RrA",
    "title": "SpaceX Starship's 5th Flight Booster Catch Landing from Isla Blanca October 13 2024",
    "score": 10
  },
  {
    "id": "ntmssdzp_qY",
    "title": "WOW! Watch SpaceX Land Starship In The Ocean [4K]",
    "score": 10
  },
  {
    "id": "-4qlPXOuDaI",
    "title": "Whoa! See SpaceX Starship lift off from beneath in launch mount view",
    "score": 10
  },
  {
    "id": "wS_8WOQJUu8",
    "title": "WOW! Watch SpaceX Land Starship In The Ocean [4K]",
    "score": 10
  },
  {
    "id": "ROlEtlldxqk",
    "title": "Search filters",
    "score": 10
  },
  {
    "id": "oC_Fc2NtrnI",
    "title": "آموزش برنامه نویسی پایتون از مقدماتی تا پیشرفته ( صفر تا صد python )",
    "score": 10
  },
  {
    "id": "MAdr67RNrMg",
    "title": "INTRO",
    "score": 10
  },
  {
    "id": "UrsmFxEIp5k",
    "title": "Introduction",
    "score": 10
  },
  {
    "id": "_uQrJ0TkZlc",
    "title": "Introduction",
    "score": 10
  },
  {
    "id": "kqtD5dpn9C8",
    "title": "Introduction",
    "score": 10
  },
  {
    "id": "9mmVa6O-hzQ",
    "title": "Einleitung",
    "score": 10
  },
  {
    "id": "6DMeU4S-Ibw",
    "title": "Bizzy \\u0026 Flesh N Bone Speak On Finesse 2tymes Disrespect‼️8ight Ball Defends Layzie⁉️",
    "score": 10
  },
  {
    "id": "pgIMZnH6ubY",
    "title": "HoneyKomb Brazy Tells Fng Lil King Finesse 2Tymes Tryna P.Diddy Him After Finesse Made 🍤 Comment ",
    "score": 10
  },
  {
    "id": "S7vwh3he0Yw",
    "title": "Shakur Stevenson RIPS Teofimo's dad for being on DRUGS - SOUNDS OFF after press conference!",
    "score": 10
  },
  {
    "id": "YvekMtG7FbY",
    "title": "SCAM LIKELY VS YK OSIRIS Full Fight - BRAND RISK \"},{\"text\":\"#012\",\"navigationEndpoint\":{\"clickTrackingParams\":\"CMACENbKAxgHIhMItKP5gpizkgMV-gloCB0jIy4yygEEnNYvtw==\",\"commandMetadata\":{\"webCommandMetadata\":{\"url\":\"/hashtag/012\",\"webPageType\":\"WEB_PAGE_TYPE_BROWSE\",\"rootVe\":6827,\"apiUrl\":\"/youtubei/v1/browse\"}},\"browseEndpoint\":{\"browseId\":\"FEhashtag\",\"params\":\"6gUHCgMwMTIYAQ%3D%3D\"}},\"loggingDirectives\":{\"trackingParams\":\"CMACENbKAxgHIhMItKP5gpizkgMV-gloCB0jIy4y\",\"visibility\":{\"types\":\"12\"}}}]},\"viewCount\":{\"videoViewCountRenderer\":{\"viewCount\":{\"simpleText\":\"244,216 views\"},\"shortViewCount\":{\"simpleText\":\"244K views\"},\"originalViewCount\":\"0\"}},\"videoActions\":{\"menuRenderer\":{\"items\":[{\"menuServiceItemRenderer\":{\"text\":{\"runs\":[{\"text\":\"Report",
    "score": 10
  },
  {
    "id": "8PBj0HPVV3I",
    "title": "Transcript",
    "score": 10
  },
  {
    "id": "xMFF4NFpWrg",
    "title": "Charleston White FIRST Interview of 2026!!! ADDRESS Lil Woody, Tekashi 69, MLK Day \\u0026 U.S. Politics",
    "score": 10
  },
  {
    "id": "gqSAIJZp2cY",
    "title": "Wrekonize - SORRY TO NOBODY (Official Visualizer)",
    "score": 10
  },
  {
    "id": "TS4GBWpvU34",
    "title": "🔥\\\"I Want to Apologize to ABSOLUTELY NOBODY\\\" - Conor McGregor🔥",
    "score": 10
  },
  {
    "id": "tJ6JaN0vLi8",
    "title": "Nobody showed up to Natalie Reynolds meet and greet #nataliereynolds",
    "score": 10
  },
  {
    "id": "ztROkFCJSeE",
    "title": "Apologies To Nobody",
    "score": 10
  },
  {
    "id": "97zg4kboDDE",
    "title": "“I apologize......to NOBODY!!!”",
    "score": 10
  },
  {
    "id": "aIJVOxra8z4",
    "title": "Connor McGregor apologize to absolutely nobody",
    "score": 10
  },
  {
    "id": "BGx_hxI9dmY",
    "title": "We Apologies To Nobody",
    "score": 10
  },
  {
    "id": "7Ao9lFp4w0E",
    "title": "Apologize To Nobody (JudaX Remix)",
    "score": 10
  },
  {
    "id": "jL34It8JMuo",
    "title": "Mike Perry hit Conor McGregor’s famous “apologizing to absolutely nobody” line in front of him. 😂",
    "score": 10
  },
  {
    "id": "LLvxMqEsLPQ",
    "title": "Conor Mcgregor apologizing..To absolutely NOBODY🔥👀",
    "score": 10
  },
  {
    "id": "4diMz5hRP-A",
    "title": "Sorry Nobody - Babylon",
    "score": 10
  },
  {
    "id": "adF6MY2to1w",
    "title": "Search filters",
    "score": 10
  },
  {
    "id": "zf4aMlFgd6I",
    "title": "Known issue 🚨 Greyed out search filters issue yt studio Greyed out search filters issue",
    "score": 10
  },
  {
    "id": "dneR1fSiS2Q",
    "title": "Known issue: Search Filter Button Missing on YouTube Kya Hai | Yt Studio New Notifications Kya Hai",
    "score": 10
  },
  {
    "id": "-IUMoXUmrRY",
    "title": "Known issue 🚨 Greyed out search filters issue | Greyed out search filters issue yt Studio Update",
    "score": 10
  },
  {
    "id": "i4Uy050xsEM",
    "title": "Known Issue 🚨Greyed out search filters issue | YouTube notice Known Issue🚨",
    "score": 10
  },
  {
    "id": "nf48TRJCrvk",
    "title": "Known issue 🚨 Greyed out search filters issue | Greyed out search filters issue yt studio ",
    "score": 10
  },
  {
    "id": "UW2Ra50WHTw",
    "title": "Known issue Greyed out search filters issue kya hai Yt Studio | Greyed out search filters issue",
    "score": 10
  },
  {
    "id": "lhhFDISgobg",
    "title": "Episode #219 - Using the Search Filters Web Part of PnP Modern Search",
    "score": 10
  },
  {
    "id": "z8JzYvXjXNg",
    "title": "Google Search Tricks - Google Advanced Search Filters -  Google Search Filters",
    "score": 10
  },
  {
    "id": "1HEHAAyaF7E",
    "title": "Introduction",
    "score": 10
  },
  {
    "id": "PG5mBrM1QBA",
    "title": "Introduction and overview",
    "score": 10
  },
  {
    "id": "HEujaFBgrXI",
    "title": "Search filters",
    "score": 10
  },
  {
    "id": "KL7XOODvwvs",
    "title": "[Hard] Screwly G Type Beat 2026 - 'Rumors' | Chicago Drill Type Beat",
    "score": 10
  },
  {
    "id": "b6K31DVoIaw",
    "title": "(FREE) Yus Gz NY Drill Sample Type Beat “Rumors” (prod . n0luvjahh)",
    "score": 10
  },
  {
    "id": "3gma5L0LmnA",
    "title": "Giannis trade rumors, Eli's HOF forecast + Yankee predictions | DiPietro \\u0026 Rothenberg | 1/30/26",
    "score": 10
  },
  {
    "id": "C95QmCCda6Q",
    "title": "[FREE] Nemzzz x Knucks x Hoodtrap Type Beat - \\\"Rumors\\\"",
    "score": 10
  },
  {
    "id": "yFVX3Hl8cAg",
    "title": "Intro",
    "score": 10
  },
  {
    "id": "0OR2tKO1utI",
    "title": "Big Mike Reacts to Pooh Shiesty Robbing Gucci Mane Rumors “That 1017 Story Ain’t Random”!!",
    "score": 10
  },
  {
    "id": "WDhuLwfbhaE",
    "title": "[FREE] Fredo x Clavish x Slim Type Beat 2025 – \\\"Rumors\\\" | UK Rap x Drill (prod. CDS x RQ x IJD)",
    "score": 10
  },
  {
    "id": "J4ZURrNocu0",
    "title": "Dallas Drill Rumors DEBUNKED",
    "score": 10
  },
  {
    "id": "BtsbLusq574",
    "title": "STL YN’s Respond To Rumors Of BH Q50 Taking $60k From Them😳 #drill #chicago #chiraq #v2drillnews",
    "score": 10
  },
  {
    "id": "_7i1WSOy_7o",
    "title": "Lil Durk - Rumors (PHILLY DRILL REMIX 👹)",
    "score": 10
  },
  {
    "id": "H9QSKKVw_p8",
    "title": "Rumours Drill",
    "score": 10
  },
  {
    "id": "q8-UaOraQAg",
    "title": "Gucci Mane - Rumors (Drill Remix)",
    "score": 10
  },
  {
    "id": "LTyhynlMzHQ",
    "title": "[FREE] FullyChop Type Beat - \\\"RUMORS\\\" | Chicago Drill Type Beat 2025",
    "score": 10
  },
  {
    "id": "2HgZN-f0ijY",
    "title": "Intro",
    "score": 10
  },
  {
    "id": "VONXJ_dE__M",
    "title": "Finesse 2tymes Banned From Atlanta‼️Rocko And TI Defend Atl While Jody Breeze Stamps Finesse⁉️",
    "score": 10
  },
  {
    "id": "9to611_sAQY",
    "title": "INVISIBLE  PONYTAIL WITH BRAIDS!🗣Natural Long Hair Ponytail Feedin Braids #Elfin Hair",
    "score": 10
  },
  {
    "id": "gRigtpjEerM",
    "title": "High Genie Ponytail Slayer!🎀Slick Back Natural Hair With Hair Weave Ft. #ULAHAIR",
    "score": 10
  },
  {
    "id": "ooQpBnU8cf4",
    "title": "👌🏾High Drawstring Ponytail Sleeking | NO HEAT | QUICK \\u0026 EASY Ft.#elfinhair #protectivestyles",
    "score": 10
  },
  {
    "id": "FHk8Q9qSuuc",
    "title": "Easy Braided Ponytail with braiding hair #braidedhairstyles #sleekponytail",
    "score": 10
  },
  {
    "id": "HI865HtRPCY",
    "title": "😦Using Clip \\u0026 Bundles For High Ponytail Install? Natural Hair Extension #Elfinhair",
    "score": 10
  },
  {
    "id": "_-cGBYAt2Fw",
    "title": "5 Minute Natural Ponytail with Clip-In Hair Extensions | Clip In #Ponytailhack | Go Sleek Hair",
    "score": 10
  },
  {
    "id": "sh9lKyzZpIw",
    "title": "Search filters",
    "score": 10
  },
  {
    "id": "gNP2X_R23M8",
    "title": "Part 25 | Claw Jack Track Jack with Claw | Heavy Lifting Power Tool 🔧",
    "score": 10
  },
  {
    "id": "1sgSF7wUyC0",
    "title": "White Claw | Grab Life By The Claw | Come Along",
    "score": 10
  },
  {
    "id": "8KVsaoveTbw",
    "title": "(No Talking, VRChat ASMR) relaxing with claw",
    "score": 10
  },
  {
    "id": "OT0b3gyJHdM",
    "title": "SCOTTIE SCHEFFLER WINS WITH CLAW GRIP!",
    "score": 10
  },
  {
    "id": "yvTv8NHYbtQ",
    "title": "Season 3 Episode 5 Cooking with Claw / Catnipped in the Bud ",
    "score": 10
  },
  {
    "id": "AQryDdQXJ2c",
    "title": "Can You Beat BLOODBORNE With Only The Beast Claw?",
    "score": 10
  },
  {
    "id": "Q6G65m8BIC0",
    "title": "The Intro",
    "score": 10
  },
  {
    "id": "U8kXfk8enrY",
    "title": "Intro",
    "score": 10
  },
  {
    "id": "NGnX_99HQ2o",
    "title": "EASY TWISTED CLAW CLIP HAIRSTYLE",
    "score": 10
  },
  {
    "id": "2LELDPqOc9Q",
    "title": "mic scratching with the gloves",
    "score": 10
  },
  {
    "id": "G7zHkReUaTM",
    "title": "Are CLAW MACHINES A Scam?! 🫣",
    "score": 10
  },
  {
    "id": "R6qofJcc2bs",
    "title": "Throwing In Boots With Claw Spiral! #wrestling",
    "score": 10
  },
  {
    "id": "eTD8wKvuQjA",
    "title": "Yellow Claw - Both Of Us ft. STORi [Official Lyric Video]",
    "score": 10
  },
  {
    "id": "NqWGQZm2rHc",
    "title": "Search filters",
    "score": 10
  },
  {
    "id": "-eq81PVVsX4",
    "title": "Kadambari Telugu Full Movie | Vinay Krishna | Hashika Dutt |Telugu Horror Movie | Mango Indian Films",
    "score": 10
  },
  {
    "id": "KMLr-dw4BV8",
    "title": "I Tried SIX Different Mango Species  (Kasturi, Kuini, Wani, Bambagan, Paho... and a regular one)",
    "score": 10
  },
  {
    "id": "5ekTtcejwmY",
    "title": "Other mango species",
    "score": 10
  },
  {
    "id": "qEVfs5epB5A",
    "title": "Mangos 🥭🥭",
    "score": 10
  },
  {
    "id": "Nj_Ygj9voF0",
    "title": "Raw mango pachadi with all six tastes| Tamil | Kadambari Murugan",
    "score": 10
  },
  {
    "id": "2RFafE58Qqs",
    "title": "Chilli powder",
    "score": 10
  },
  {
    "id": "D3U9x9MEetw",
    "title": "Mango Masters: Dr Richard Campbell on The World of Mangos",
    "score": 10
  },
  {
    "id": "NzMiEWb6G6w",
    "title": "Natyam Latest Full Movie 4K | Sandhya Raju | Aditya Menon | Hindi Dubbed | Mango Indian Films",
    "score": 10
  },
  {
    "id": "cMPWr9JyU7s",
    "title": "Actress Kadambari Jethwani Talks About Andhra Pradesh Government | AP News | NDA | Mango News",
    "score": 10
  },
  {
    "id": "qMV-wJPRIaE",
    "title": "Mango 🥭",
    "score": 10
  },
  {
    "id": "zZUou87Gb4A",
    "title": "Jackfruit seeds, drumstick, and raw mango sidedish for rice| Tastes like home❤️",
    "score": 10
  },
  {
    "id": "kqr8-vOj7sM",
    "title": "मँगो विथ क्रिम|mango with cream dessert recipe @Kadambari's kitchen",
    "score": 10
  },
  {
    "id": "5VpQIW6Sf-8",
    "title": "🥭⚠️ Mango Seed Benefits You Never Knew! Use Before It's Too Late! ⏳💊 #healthyfood #health #watchnow",
    "score": 10
  },
  {
    "id": "xBUumqnmVxs",
    "title": "Search filters",
    "score": 10
  },
  {
    "id": "tlNBB0jdL3w",
    "title": "king of Apology",
    "score": 10
  },
  {
    "id": "D_83nTqcxrc",
    "title": "He Apologized",
    "score": 10
  },
  {
    "id": "EYNK6MB_Oko",
    "title": "Civilization #21:  The Apology of King David of Israel",
    "score": 10
  },
  {
    "id": "RkpGrRUgjnk",
    "title": "King - Apology (Lyric Video)",
    "score": 10
  },
  {
    "id": "Odm95GeXHFk",
    "title": "Finesse2Tymes Speaks Out \\u0026 Responds To Lil King's Apology.",
    "score": 10
  },
  {
    "id": "Tp84-New5aA",
    "title": "King Chollo - Can’t Accept Yo Apology (Prod. Elii Beatz)",
    "score": 10
  },
  {
    "id": "p33InAaq21A",
    "title": "Too Late to Apologize: A Declaration",
    "score": 10
  },
  {
    "id": "TRzDyZWcack",
    "title": "Snoop Says Mom Urged Gayle King Apology | The View",
    "score": 10
  },
  {
    "id": "0uR3qR0BLqs",
    "title": "Lucifers Apology",
    "score": 10
  },
  {
    "id": "cMXHIMQ2iAY",
    "title": "My Apology to Eliop14",
    "score": 10
  },
  {
    "id": "11FWm3DqFcA",
    "title": "Intro",
    "score": 10
  },
  {
    "id": "juEaJmZ_loI",
    "title": "Arthur's Heartfelt Apology | The King of Queens",
    "score": 10
  },
  {
    "id": "vPRPg5UsUTY",
    "title": "Jana Kramer King of Apology WYCD Downtown Hoedown 2012",
    "score": 10
  },
  {
    "id": "TZS4Fn0eNEU",
    "title": "Finesse 2Tymes Addresses Fng Lil King Apology Video \\u0026 Speaks More On Offset × Kevin Gates \\u0026 CW",
    "score": 10
  },
  {
    "id": "7lgTytiRAUE",
    "title": "Lil King  APOLOGIZE To Finesse2Tymes \\u0026 said HE GOT NOBODY TO HOLD HIM, Kodak Black on NBA Youngboy",
    "score": 10
  },
  {
    "id": "t0yQlO4wFKE",
    "title": "Search filters",
    "score": 10
  },
  {
    "id": "HNrCi1Ztfog",
    "title": "FORGIVENESS 🎬 Full Exclusive Thriller Horror Movie 🎬 English HD 2025",
    "score": 10
  },
  {
    "id": "ovCSePsD8h0",
    "title": "LAKE ARTIFACT 🎬 Full Exclusive Thriller Horror Movie Premiere 🎬 English HD 2024",
    "score": 10
  },
  {
    "id": "J77B_HANMIM",
    "title": "Claw clips for thick hair you would not believe!",
    "score": 10
  },
  {
    "id": "FnokEOv3dCY",
    "title": "Which size claw clip do you need? Sizes XS-3XL 🤍 #hairtok #hairstyle #hairstyle #clawclip",
    "score": 10
  },
  {
    "id": "imNnwW9wR34",
    "title": "King El - #FinesseGang (Prod. CashMoneyAp)",
    "score": 10
  },
  {
    "id": "pm4H0Mvw77A",
    "title": "Finesse Gang L X Taziz Mainey - \\\"Last Call\\\" | Dir. Playa Play \\u0026 SM Visuals",
    "score": 10
  },
  {
    "id": "_aGou2mK-eI",
    "title": "King Ace - Finesse Gang",
    "score": 10
  },
  {
    "id": "qlE_nXJtNI4",
    "title": "FinesseGang Mooka - \\\"Times Up\\\" | Shot By A1Visuals",
    "score": 10
  },
  {
    "id": "oHBnnzuIjos",
    "title": "XXXTENTACION- King of the dead",
    "score": 10
  },
  {
    "id": "XIj-RBIVXj4",
    "title": "20 KIDS VS 1 RAPPER :LIL RT \\u0026 HIS GF",
    "score": 10
  },
  {
    "id": "DrfFBj8-QEk",
    "title": "Living With Lil RT \\u0026 KKingCee For 24 hours!",
    "score": 10
  },
  {
    "id": "dkaAnA2mgEI",
    "title": "ABKNino takes us to the most DANGEROUS hood in North Las Vegas | The Rose Gardens",
    "score": 10
  },
  {
    "id": "yMtACsyFbf8",
    "title": "Finesse2tymes said lilking dad don’t want him nomo 😱must watch 😱",
    "score": 10
  },
  {
    "id": "DlGCQnKnDwM",
    "title": "Finesse Gang - Can't See Me |Prod: Detrakz| |Dir: KeroFilms|",
    "score": 10
  },
  {
    "id": "bgN-nfFgnR8",
    "title": "Pacman Shawty \\\"Finesse King\\\"",
    "score": 10
  },
  {
    "id": "C5jAugbfwfk",
    "title": "Finesse \\\"Shootin Fast'' Shot By | CAMERAGAWDZ",
    "score": 10
  },
  {
    "id": "fRDTEU9y4us",
    "title": "Fng King ''Respect the struggle FREESTYLE''",
    "score": 10
  },
  {
    "id": "qE78D_ulLRI",
    "title": "FINESSE GANG - Like Water (40oz OF FINE$$E MIXTAPE)",
    "score": 10
  },
  {
    "id": "RtzBw8zULhM",
    "title": "FGW Drip - Finesse King",
    "score": 10
  },
  {
    "id": "OoE1faPGO2U",
    "title": "Understood (feat. Finesse Gang Kliff)",
    "score": 10
  },
  {
    "id": "D61ki9JGw0o",
    "title": "Finesse Gang - Grind | Shot By: @RealWoosie",
    "score": 10
  },
  {
    "id": "85URa9qDLPU",
    "title": "Search filters",
    "score": 10
  },
  {
    "id": "TBRCZLzn5pM",
    "title": "Classic Cadburys smash 1970's t.v advert",
    "score": 10
  },
  {
    "id": "eD3QkNyORIo",
    "title": "19-Year-Old Just Smashed A WORLD RECORD! || 2026 Clemson Invite",
    "score": 10
  },
  {
    "id": "rIpYoAZM6pg",
    "title": "Smash Mouth - All Star",
    "score": 10
  },
  {
    "id": "L_jWHffIx5E",
    "title": "Entitled Ex-Cop's Daughter Resists Arrest, Calls Dad \\u0026 Gets Window Smashed!",
    "score": 10
  },
  {
    "id": "WL1WH6AsqgA",
    "title": "Gold and Silver Smashed: What's Driving It?",
    "score": 10
  },
  {
    "id": "rXG9DkOMN60",
    "title": "Coco Gauff smashes racket in frustration after Australian Open loss to Elina Svitolina",
    "score": 10
  },
  {
    "id": "B8gyW3N3eGY",
    "title": "Cousin’s Ex Smashed BMW Windows? | Part 1",
    "score": 10
  },
  {
    "id": "yHLxPnswbIQ",
    "title": "Woman Admits She Smashed Friend's Car Windows! | Part 2",
    "score": 10
  },
  {
    "id": "19jG2X-KSQM",
    "title": "The Damned - Smash it Up Old Grey Whistle Test, Stage wrecked!",
    "score": 10
  },
  {
    "id": "YZ76LC_l8yk",
    "title": "Better Than Fast Food! Classic Smash Burger Recipe",
    "score": 10
  },
  {
    "id": "foD42-73wdI",
    "title": "Intro",
    "score": 10
  },
  {
    "id": "owQcIBVjEcs",
    "title": "A Proper Smash Burger",
    "score": 10
  },
  {
    "id": "XuYIqSpKQUM",
    "title": "My Own Parents Smashed My Six-Year-Old Daughter's Face While She Slept So......",
    "score": 10
  },
  {
    "id": "1bYAl2btRUE",
    "title": "Racket SMASHED! Kotov Shocks Quimper Crowd With Meltdown 😳",
    "score": 10
  },
  {
    "id": "0mJL4OSl2VM",
    "title": "My Dad Smashed My 4-Year-Old Daughter's Jaw For 'Talking Back.' She Came Crying To Me Saying.....",
    "score": 10
  },
  {
    "id": "0huMUONFgZA",
    "title": "Rewatching My Old Tourney Sets From Ultimate \\u0026 Smash 4!",
    "score": 10
  },
  {
    "id": "l_5MCZcqJjU",
    "title": "[SSBU] How Min Min Went From a Joke to Smash Ultimate’s Best",
    "score": 10
  },
  {
    "id": "IBJ5QEyUnco",
    "title": "Woman Admits She Smashed Friend's Car Windows! | Part 1",
    "score": 10
  },
  {
    "id": "zW-0FDVhzt4",
    "title": "Search filters",
    "score": 10
  },
  {
    "id": "V256nY6aFD4",
    "title": "Mozzy - Tryna Win [Thizzler.com]",
    "score": 10
  },
  {
    "id": "7BfnH233ACc",
    "title": "Female rapper MOCKS her opps from the hospital after surviving 😳",
    "score": 10
  },
  {
    "id": "bxdJSCV_Oyw",
    "title": "Gigi Moss - Do Your Worst (Lyric Video)",
    "score": 10
  },
  {
    "id": "BwVgaf6iY8Y",
    "title": "The IMMEDIATE Regret After Trying To Claim My Dogs Were His Was Real.",
    "score": 10
  },
  {
    "id": "ZjS9LOv7u4s",
    "title": "Tryna get back into R6 after 2-3 years (Mic is broke)",
    "score": 10
  },
  {
    "id": "raIJdyRQKH8",
    "title": "Tryna put on socks after a shower be like 😂",
    "score": 10
  },
  {
    "id": "kitYgw8qAzc",
    "title": "BACK FOR THE FIRST TIME LIKE LUDACRIS",
    "score": 10
  },
  {
    "id": "kqXs_TpNUx0",
    "title": "Mase \\u0026 Cam’ron LOST IT Over Jim Jones’ FREEZING Facility \\u0026 Power OUTAGE!",
    "score": 10
  },
  {
    "id": "SjAVyzc--fE",
    "title": "Prime \\u0026 Dre Solidifies the Crush at 2 am",
    "score": 10
  },
  {
    "id": "6E6zTCFCrS0",
    "title": "♌LEO UHHMMM... SOMEONE TRYNA TRAUMA DUMP ON🫵 😮😱🙄 AFTER COMING AGAINST🫵LOOKIN4 SYMPATHY🥺; SETUP⚠🙅‍♀️",
    "score": 10
  },
  {
    "id": "U9FFROz2bYs",
    "title": "I Watched The Full Chris Unbias Story And... | NoMercyTV",
    "score": 10
  },
  {
    "id": "BU7qgeK1Tkc",
    "title": "[AFTERMATH] Aftons stuck in a room for 24 hours || MY AU ⚠️ || Afton Family Reunion || PART 3 / 3",
    "score": 10
  },
  {
    "id": "jt_0aZnpMLw",
    "title": "Dogs Tested to See Whether They’d Defend Owner During Home Invasion",
    "score": 10
  },
  {
    "id": "NZ74oFctP_g",
    "title": "Perry",
    "score": 10
  },
  {
    "id": "_EYjyrNKCkk",
    "title": "Young MA Fans Are WORRIED After She Post This DISTURBING VIDEO!",
    "score": 10
  },
  {
    "id": "Baw9RGcOojE",
    "title": "Boosie Estates: $200K 6 Acre Fishing Lake, $150K Pool Slide, New House for His Mom (Full Interview)",
    "score": 10
  },
  {
    "id": "zjXwJAz5Btk",
    "title": "The After Show: R U Not Entertained",
    "score": 10
  },
  {
    "id": "HNRofzemcPU",
    "title": "Boosie Breaks Down After New FED Charges – ‘They Tryna Put More On Me’",
    "score": 10
  },
  {
    "id": "BxCniLfDaqg",
    "title": "Bhad Bhabie has meltdown after tryna stop acting black",
    "score": 10
  },
  {
    "id": "Jbv7hS8_Yz8",
    "title": "How dudes be after tryna talk to a random girl :",
    "score": 10
  },
  {
    "id": "g4oc1UJ9X5g",
    "title": "Cassidy Female Man Club Put To Shame After Tryna Come Up Off Me.",
    "score": 10
  },
  {
    "id": "2eOMIrdEg5Y",
    "title": "how loid tryna be entering the desmond household after the friendship scheme fails 💀",
    "score": 10
  },
  {
    "id": "QYMNtymhbAA",
    "title": "Girl Almost Break Spine After Tryna Grind😂😂",
    "score": 10
  },
  {
    "id": "gwIwKs9velE",
    "title": "SAGITTARIUS - THEY OWE U THEIR LIFE AFTER TRYNA SET U UP SMH STUPID ASF ",
    "score": 10
  },
  {
    "id": "-FA3GAAG2VU",
    "title": "CHRISEANROCK DUBS DOUGIE B IN NEW YORK CITY AFTER TRYNA PUT HIS ARM AROUND HER WHILE PREGNANT",
    "score": 10
  },
  {
    "id": "-KKeDwQOVkw",
    "title": "They Stopped Tryna Play With Young M.A Quick After That 🤣 (via @breakbeatmedia)",
    "score": 10
  },
  {
    "id": "OXofT16TVic",
    "title": "Static in My Head — Dark Pop | Night Drive | After Hours Vibes",
    "score": 10
  },
  {
    "id": "5IpfG1rw-9U",
    "title": "Search filters",
    "score": 10
  },
  {
    "id": "hs1aKdh1VLA",
    "title": "FNG king telling it all #finesse2Tymes",
    "score": 10
  },
  {
    "id": "1mmeYR4fPO0",
    "title": "No look pass ⚡️ #king68 #kingenergy",
    "score": 10
  },
  {
    "id": "zwvWB58hFYQ",
    "title": "King von telling his sister ( Kayla b) ‘’you off 63rd gang “",
    "score": 10
  },
  {
    "id": "Fn9QQ9jv6fo",
    "title": "King von telling cops he has a body \\u0026 2 attempts 😭 #kingvon #lildurk #oblock",
    "score": 10
  },
  {
    "id": "ODsp_8ucr5g",
    "title": "Telling People Ridiculous Fortunes",
    "score": 10
  },
  {
    "id": "sopWBfIPw4I",
    "title": "'The King of Kindergarten' read by Terry Crews",
    "score": 10
  },
  {
    "id": "mz6o8b2bFd0",
    "title": "Shuler King - Grandma Is Telling The Truth",
    "score": 10
  },
  {
    "id": "sK-xVWV5_yo",
    "title": "SML Movie: The Talent SHOW !!! ( Funniest Jeffy Videos ) 4 HOURS !!! Movie content 2026",
    "score": 10
  },
  {
    "id": "4sjSMoUXQ9A",
    "title": "Telling my Son i'm PREGNANT! *Emotional*",
    "score": 10
  },
  {
    "id": "GnvVur8mv10",
    "title": "SML Movie: The McDonalds RAP !!! ( Funniest Jeffy Videos ) 4 HOURS !!! Movie content 2026",
    "score": 10
  },
  {
    "id": "M3a-X7wo5PU",
    "title": "Tyrone Davis Jr. | Lulu’s Car IMPOUNDED as Evidence, Police Confirm No Accident, Open Investigation",
    "score": 10
  },
  {
    "id": "uucZsbL7T_0",
    "title": "THIS WEIRD OLD LADY HIRED ME TO FIX HER TV BUT SOMETHING SEEMS A LITTLE OFF..",
    "score": 10
  },
  {
    "id": "313KfrBd7O8",
    "title": "Tyrone Davis Jr. | Lulu Old Messages CONFESS She K!lled Him, Witnesses Expose Cabin Fight \\u0026 Cheating",
    "score": 10
  },
  {
    "id": "wgfGmyvIzb8",
    "title": "Ivori Chooses Her friend over GirlFriend‼️Donyae Busts Out Ivori’s Car Window‼️",
    "score": 10
  },
  {
    "id": "8_qbBeKmtBs",
    "title": "⚠️ 2026 Layoffs Everywhere — Here’s What They’re Not Telling You",
    "score": 10
  },
  {
    "id": "i2bnp8prjGc",
    "title": "Morning Prayer for Strength | Gratitude Prayer — Start Your Day With Peace and Trust in God",
    "score": 10
  },
  {
    "id": "Olq0e4jDTJQ",
    "title": "Shuler King - Is This Appropriate For A Funeral",
    "score": 10
  },
  {
    "id": "SgSxSbDmfFc",
    "title": "Finesse2tymes REACTS To His PROBATION VIOLATION \\u0026 King TELLING Police On Him In Case “I AM",
    "score": 10
  },
  {
    "id": "fBL1V48AXAA",
    "title": "Story Telling Competition 2022 “King Midas \\u0026 The Golden Touch” by Kenzie Morgan Abelardo",
    "score": 10
  },
  {
    "id": "bBz_XHlqoSc",
    "title": "Telling People Ridiculous Fortunes Again",
    "score": 10
  },
  {
    "id": "ZjXmwrCTgKk",
    "title": "TEDxCincy - Brad King - Telling Stories on the World",
    "score": 10
  },
  {
    "id": "uajiGYo6qLk",
    "title": "everything matters",
    "score": 10
  },
  {
    "id": "7IoF9IrZnXU",
    "title": "What did Midas wish for?",
    "score": 10
  },
  {
    "id": "3Ki3mK0KmWg",
    "title": "KING KALE - AIN'T NO TELLING",
    "score": 10
  },
  {
    "id": "5bJtRAnD8sE",
    "title": "The Evolution of King Kong (Animated)",
    "score": 10
  },
  {
    "id": "kmTELp7hfN4",
    "title": "Stinger",
    "score": 10
  },
  {
    "id": "PYhwlKHoEBw",
    "title": "Telling King",
    "score": 10
  },
  {
    "id": "ER5Tuf4cYt8",
    "title": "Search filters",
    "score": 10
  },
  {
    "id": "P6LcsdquAZU",
    "title": "South Released New LITTLE HEARTS BlockBuster Romantic Black Comedy Thriller Hindi Dubbed Full Movie",
    "score": 10
  },
  {
    "id": "k7Qb4nF8bbs",
    "title": "ASTHRAM New 2026 Release SOUTH BLOCKBUSTER Latest Hindi Dubbed Moveis | Shaam, Niranjani, Jeeva",
    "score": 10
  },
  {
    "id": "2zzxyCLjcHo",
    "title": "Peddi || Ramcharan || New Released Full Hindi Dubbed Action Movie 2026 #south #latestmovies",
    "score": 10
  },
  {
    "id": "NpBjDT2ZSg4",
    "title": "🎥【FULL DUBBED】Reborn to Revenge My Evil Foster Daughter#chinesedrama #drama",
    "score": 10
  },
  {
    "id": "CvnGOiYLplU",
    "title": "THE TIME WE HAVE LEFT [FULL MOVIE TAGALOG DUBBED] - Pag-ibig na Umabot Hanggang Huling Saglit.",
    "score": 10
  },
  {
    "id": "CYzC336Iccg",
    "title": "Flu Full Movie Tagalog Dubbed | Jang Hyuk, Soo Ae, Ma Dong-seok",
    "score": 10
  },
  {
    "id": "qU--pv5M6GY",
    "title": "FIRE YODHA SURYA - Hindi Dubbed Full Movie | Vikram, Nikki Galrani, Bindhu | Romantic Action Movie",
    "score": 10
  },
  {
    "id": "DmSq3vq-wjI",
    "title": "TOXIC TIGER Mahesh Hindi Dubbed Full Movie | Intense Action Thriller | South Blockbuster | HD",
    "score": 10
  },
  {
    "id": "TxJ6uBRqrn4",
    "title": "Recreate Our Life! Episodes 1-12 English Dubbed Full Screen Eng Dub New Anime 2026",
    "score": 10
  },
  {
    "id": "1RbGZUKqjY0",
    "title": "Anime in English ✨All Episodes ✨Anime Full Screen English Dub2026✨ New Anime Series #138 ",
    "score": 10
  },
  {
    "id": "wBLqPcBFJfI",
    "title": "Anime Full Screen English Dub2026 ⚡️All Episodes ⚡️ Anime in English Series ⚡️Anime in English #134 ",
    "score": 10
  },
  {
    "id": "g5H0y8J2FdM",
    "title": "Anime Full Screen English Dub2026 ⚡️All Episodes ⚡️ Anime in English Series ⚡️Anime in English #133 ",
    "score": 10
  },
  {
    "id": "QoHdJ-MHo24",
    "title": "Limang taon matapos ang diborsyo, CEO na siya; unang araw ko, tinawag siya ng anak kong ‘Tatay’!",
    "score": 10
  },
  {
    "id": "4aZUjcubxJ8",
    "title": "Sa burol, sinabi niyang buhay pa ang patay — at ginamit ang dugo para ibalik ang kaluluwa.",
    "score": 10
  },
  {
    "id": "BlMteZNN59E",
    "title": "Tinulungan ng rich CEO ang kawawang tindera, anak pala niya! Agad siyang dinala pauwi!#kdrama",
    "score": 10
  },
  {
    "id": "i1IURZ3M5qc",
    "title": "They Blocked My Driveway Every Day. I Had Their Cars Towed 47 Times.",
    "score": 10
  },
  {
    "id": "JkR7JsOWYuY",
    "title": "ஸ்டாலின் வழக்கில் அதிரடி வெற்றி! உச்சநீதிமன்றம் பரபரப்பு தீர்ப்பு! நெருக்கடியில் தேர்தல் ஆணையம்!",
    "score": 10
  },
  {
    "id": "KWvs8NAChmo",
    "title": "Masamang Ugat FULL MOVIE |  Eddie Garcia, Mikey Arroyo, Ace Vergel",
    "score": 10
  },
  {
    "id": "GmfM2_n29Ao",
    "title": "Tagalog Horror Movie | Sobrang Ganda, Pramis!",
    "score": 10
  },
  {
    "id": "0olWCXCdieI",
    "title": "Spirit Full Hindi Dubbed Movie 2026 | Rebal Star Prabhas | Sandeep Reddy Vanga | Latest Action Movie",
    "score": 10
  },
  {
    "id": "FPtmWZQdG-U",
    "title": "Decent Lover New (2026) Released Full Hindi Dubbed Action Movie | Allu Arjun,Samantha New Movie 2026",
    "score": 10
  },
  {
    "id": "mbmS2fcsskg",
    "title": "Benz Full Movie Hindi Dubbed 2025 | Raghava Lawrence New Hindi Movie 2025 | Latest South Movie 2025",
    "score": 10
  },
  {
    "id": "tetzvmmngOQ",
    "title": "RED DIARY (2026) | Dhanush, Nithya Menon Hindi Dubbed Action Drama Thriller | Full HD Movie",
    "score": 10
  },
  {
    "id": "Oe65KJWuM2c",
    "title": "Best Impression of a Dubbed Kung Fu Movie. Arvin Mitchell - Full Special",
    "score": 10
  },
  {
    "id": "bdLXT__mecU",
    "title": "Border 2 Full Movie Hindi Dubbed 2026 | Sunny Deol New Movie | Sonam B | Latest Movie 2026 Bollywood",
    "score": 10
  },
  {
    "id": "BwLQSq6FwNY",
    "title": "ENGAGED TO A LIE [FULL MOVIE TAGALOG DUBBED] - Pekeng Tagapagmana, Tunay na Puso.",
    "score": 10
  },
  {
    "id": "2huJV9j2bsA",
    "title": "FALLING FOR THE FORBIDDEN [FULL MOVIE TAGALOG DUBBED] - Pag-ibig na Walang Pangalan.",
    "score": 10
  },
  {
    "id": "g3Epp0Ie3cQ",
    "title": "MAXX (2026) | Allu Arjun, Priyanka Chopra | Hindi Dubbed Action Thriller Movie | Full HD Movie",
    "score": 10
  },
  {
    "id": "iRwlu6aEx50",
    "title": "Mass Rajni (2026) | Rajinikanth Hindi Dubbed Action Thriller Movie | Full HD Movie",
    "score": 10
  },
  {
    "id": "EDuVf1R2vaE",
    "title": "Search filters",
    "score": 10
  },
  {
    "id": "I-_Vka8WIb4",
    "title": "Ultra Sleek Braided Ponytail on Natural Hair (NO HEAT!)",
    "score": 10
  },
  {
    "id": "Csw4qD71CTA",
    "title": "Intro",
    "score": 10
  },
  {
    "id": "mAEkAzjViU0",
    "title": "Intro",
    "score": 10
  },
  {
    "id": "uQAKo1UeRW0",
    "title": "Intro",
    "score": 10
  },
  {
    "id": "06S1Pv0bqxQ",
    "title": "Braided ponytail 🔥🔥#viralvideo #foryou #braids",
    "score": 10
  },
  {
    "id": "qRweZnRhirE",
    "title": "Stitch Braided Ponytail W/ Boho 👏🏽 #viralvideo",
    "score": 10
  },
  {
    "id": "EMVdOcsiWf0",
    "title": "Search filters",
    "score": 10
  },
  {
    "id": "vD9VgoRx71E",
    "title": "NIMROD THE KING WHO CLAIMED TO BE GOD AGAINST ALLAH",
    "score": 10
  },
  {
    "id": "uWx_xo8yqlE",
    "title": "The Lion King King of Pride Rock HD",
    "score": 10
  },
  {
    "id": "i-gzUVVpezU",
    "title": "She Saved A DYING Wolf… Now The Most Powerful Alpha King CLAIMS her",
    "score": 10
  },
  {
    "id": "8i-cDaN7tSA",
    "title": "She Saved A Dying Wolf… Now The Most POWERFUL Alpha King CLAIMS HER | (PART 2)",
    "score": 10
  },
  {
    "id": "jOM2nFhyVz0",
    "title": "[ASMR] Monstrous King Claims You as His",
    "score": 10
  },
  {
    "id": "aULsLRfls6I",
    "title": "OG COREY KING CLAIMS FAT JOE HAS 48 HOURS TO APOLOGIZE “YOU A RAC!ST GERMAN”.",
    "score": 10
  },
  {
    "id": "r6Er8qJ5qBY",
    "title": "'LOOPHOLE!' Can Andrew STILL use Duke of York title? | Palace Confidential",
    "score": 10
  },
  {
    "id": "Nh5se01cFu8",
    "title": "Intro",
    "score": 10
  },
  {
    "id": "4YmORRFz3Vw",
    "title": "What Trump Aides Whisper About His Cabinet: Wolff | Inside Trump's Head",
    "score": 10
  },
  {
    "id": "TlDA3gUjd2I",
    "title": "Melania Returns: Movie Promotion, Money, and Power",
    "score": 10
  },
  {
    "id": "FSBDYffIDv4",
    "title": "Intro - BTC falling lower",
    "score": 10
  },
  {
    "id": "k7FQ7dHg9uI",
    "title": "Ghislaine Maxwell Drops BOMBSHELL",
    "score": 10
  },
  {
    "id": "73SjxAgiueM",
    "title": "Breaking News: New York in Winter Chaos – 106 Dead and 400,000 Without Power in US",
    "score": 10
  },
  {
    "id": "9Hh9RBc2YII",
    "title": "Why And When I Will Long Bitcoin (Lower First, Targets Explained)",
    "score": 10
  },
  {
    "id": "Eztv-FHw108",
    "title": "Trump Celebrates Melania’s Movie Premiere, Has New BFF Nicki Minaj \\u0026 Government Shutdown Looms",
    "score": 10
  },
  {
    "id": "sr0hHyj7W94",
    "title": "Pnp conference!Mark Golding tell us what happens to the donation money #jamaica #jlp #pnp #politics ",
    "score": 10
  },
  {
    "id": "1fm1Tvv-JpE",
    "title": "Rep. Steve King Claims Undocumented Immigrants Mostly '130-Pound' Drug Runners",
    "score": 10
  },
  {
    "id": "devaYmPTrIc",
    "title": "Man Who Claims To Be King Charles \\u0026 Camilla's Son Drops DNA Bombshell!",
    "score": 10
  },
  {
    "id": "IjTxSFv7dVw",
    "title": "SHE SAVED A DYING WOLF EVERYONE FEARED... Now The Alpha King Claims Her As His...",
    "score": 10
  },
  {
    "id": "TbvWIbAJvtU",
    "title": "King’s Solomon’s secret to life #motivation #love #money #god #success #happy #life #business #power",
    "score": 10
  },
  {
    "id": "ubUlKLBtpE4",
    "title": "Bobby Hill Claims Hardbone! Meat Judging Team",
    "score": 10
  },
  {
    "id": "k4EmMlC_HoA",
    "title": "Man Who Claims He Is King Charles’ Son Launches Defamation Case Against News Publication | 10 News",
    "score": 10
  },
  {
    "id": "STGB-EU_Ezs",
    "title": "𝗡𝗶𝗴𝗵𝘁 𝗞𝗶𝗻𝗴 𝗱𝗲𝗳𝗲𝗻𝗱𝘀 𝗧𝗵𝗲 𝗰𝗵𝗶𝗹𝗱𝗿𝗲𝗻 𝗼𝗳 𝘁𝗵𝗲 𝗙𝗼𝗿𝗲𝘀𝘁🥹💀 | 𝗚𝗮𝗺𝗲 𝗼𝗳 𝗧𝗵𝗿𝗼𝗻𝗲𝘀🐉| 𝗛𝗗 @MOODBEATZ1",
    "score": 10
  },
  {
    "id": "kbRiGqrPMfU",
    "title": "From Love to Murder: The King Von x KI Tragedy",
    "score": 10
  },
  {
    "id": "SAZsnvfgJXM",
    "title": "They Locked Her In A Shed For Years—Now The Alpha King Claims Her",
    "score": 10
  },
  {
    "id": "uifkZxyrglc",
    "title": "Search filters",
    "score": 10
  },
  {
    "id": "USe_niebR3I",
    "title": "YBG Lo - Struggle (Official Audio) ft. King Von",
    "score": 10
  },
  {
    "id": "zjP02GIKFsk",
    "title": "Struggle - Isaiah King x Lokk G x Scotty Drippin Prod by: Shinoxmker",
    "score": 10
  },
  {
    "id": "i-XYaX4eKws",
    "title": "Fng King ''Respect the struggle FREESTYLE''",
    "score": 10
  },
  {
    "id": "mwwTTPTJ_u4",
    "title": "Struggle ft. YBG Lo",
    "score": 10
  },
  {
    "id": "iUwSePR5P5I",
    "title": "Wish you would - Ray Gotti Feat. Struggle Jennings and Alexander King",
    "score": 10
  },
  {
    "id": "B1vqTezaAY8",
    "title": "Bryann T - Struggle Ft. YD Kev, Brandon Trejo, \\u0026 Ryann T",
    "score": 10
  },
  {
    "id": "WKB8NFjN3eE",
    "title": "Cappadonna - Struggle With This feat. King Just - The Struggle",
    "score": 10
  },
  {
    "id": "vCgVg-kvg7Y",
    "title": "The Houndmaster of Georgia — The Slave Who Trained Dogs to Attack Only White Plantation Men",
    "score": 10
  },
  {
    "id": "-pCguynp7N4",
    "title": "Ex Warlock Reveals Why God's Chosen Secretly Struggle with Lust (James Kawalya)",
    "score": 10
  },
  {
    "id": "3hVImKP4SqI",
    "title": "Jungle War King Cobra vs Porcupine   Unbelievable",
    "score": 10
  },
  {
    "id": "D9TcCAWePxQ",
    "title": "Intro",
    "score": 10
  },
  {
    "id": "3-sc7fzWHPE",
    "title": "Loading Timbers With The Loader For Firewood Jan 29 2026",
    "score": 10
  },
  {
    "id": "7Y7QPxX0hhI",
    "title": "A Card Game Gone Wrong | King of New York Iconic Scene",
    "score": 10
  },
  {
    "id": "FgGYqonkP8A",
    "title": "Primate Party starts here!",
    "score": 10
  },
  {
    "id": "347V7p50Hcc",
    "title": "Beggar Slays Snake King with One Sword to Save War Goddess, Revealed as Reborn Immortal Emperor",
    "score": 10
  },
  {
    "id": "28fEkDzIHSg",
    "title": "MLK Talks 'New Phase' Of Civil Rights Struggle, 11 Months Before His Assassination | NBC News",
    "score": 10
  },
  {
    "id": "2xsbt3a7K-8",
    "title": "Shambhu // Anantay  // R.D.Jaan // king Beats //",
    "score": 10
  },
  {
    "id": "9Yc9fWsui-I",
    "title": "Struggle meals? #kingj2x #funny #food",
    "score": 10
  },
  {
    "id": "_uj4qSPcGUw",
    "title": "More Than The Struggle",
    "score": 10
  },
  {
    "id": "jC0Qb_3udNo",
    "title": "Lil Cash King - Struggle ft AUDIE",
    "score": 10
  },
  {
    "id": "IddKN8NF73U",
    "title": "BOHEMIA STRUGGLE 🔥",
    "score": 10
  },
  {
    "id": "RnlBEyi-0hQ",
    "title": "2024 Thanksgiving Struggle Plates",
    "score": 10
  },
  {
    "id": "PgkAWk9590U",
    "title": "Young Scooter - Made It Threw The Struggle ft. Mase \\u0026 Verse Simmonds [Street Lottery Mixtape]",
    "score": 10
  },
  {
    "id": "WI_2wP8l2nU",
    "title": "Search filters",
    "score": 10
  },
  {
    "id": "oXYFnE_fT_o",
    "title": "The Untold Story of Chand Usmani | Bollywood Stories | Tabassum Talkies",
    "score": 10
  },
  {
    "id": "CC88C3jNxdw",
    "title": "दो चोटियों वाली इस हसीन अभिनेत्री का ज़माना था Actress Chand Usmani Biography In Hindi EP 137",
    "score": 10
  },
  {
    "id": "JOiWHlqrzrY",
    "title": "Chhal Chhal Paani Hamari (HD) - Amaanat (1955) - Chand Usmani - Bharat Bhushan - Manna Dey",
    "score": 10
  },
  {
    "id": "38-lBE-PHd8",
    "title": "Tum Na Aaye | Chand Usmani | Video Song | Asha Bhosle | Baap Re Baap | Old Hit Video Songs",
    "score": 10
  },
  {
    "id": "NWxGrfHak-E",
    "title": "CHAND USMANI Movies List | चाँद उस्मानी मूवीज लिस्ट",
    "score": 10
  },
  {
    "id": "a8y4QQSbqQc",
    "title": "Intro",
    "score": 10
  },
  {
    "id": "XPJgrxW569U",
    "title": "Amaanat (1955) Full Movie | अमानत | Bharat Bhushan, Chand Usmani",
    "score": 10
  },
  {
    "id": "ET_eAZz1A6U",
    "title": "Piya Piya Mora Jiya Pukare | Baap Re Baap (1955) Kishore Kumar | Chand Usmani Hit Songs",
    "score": 10
  },
  {
    "id": "JpYfxqsKVYk",
    "title": "Chand   usmani",
    "score": 10
  },
  {
    "id": "PPovWInCQZg",
    "title": "Zindagi Aur Hum (1962) Full Movie | Nalini Jaywant, Chand Usmani | Old Hindi Superhit Movie",
    "score": 10
  },
  {
    "id": "9fWYu5wbWuQ",
    "title": "Miss World 1978 - Kalpana Iyer",
    "score": 10
  },
  {
    "id": "YEuytZtRTRc",
    "title": "The Unforgettable Comedian - Pyarelal (Ram Sethi)",
    "score": 10
  },
  {
    "id": "0iBmLg6Yja4",
    "title": "Daisy Irani: Farhan Akhtar's Maternal Aunt | Tabassum Talkies",
    "score": 10
  },
  {
    "id": "4OgzDedAkac",
    "title": "Aaja O Belwa - Lata Mangeshkar - BARATI - Shyam Kumar, Chand Usmani, Johnny Walker, Om Prakash, Agha",
    "score": 10
  },
  {
    "id": "Ry6XCghfKhk",
    "title": "बाराती - Barati - Super Hit Movie - Shyam Kumar, Chand Usmani, Johnny Walker",
    "score": 10
  },
  {
    "id": "IVoY1dHyP0g",
    "title": "Tum Na Aaye (HD) - Baap Re Baap Song -  Chand Usmani - Old Hindi Song - Filmigaane",
    "score": 10
  },
  {
    "id": "l8BvkqGP8RY",
    "title": "Baanki Adaayen Dekhanaa Ji (HD) - Amaanat (1955) - Chand Usmani - Bharat Bhushan - Asha Mathur",
    "score": 10
  },
  {
    "id": "k13IIvsTK80",
    "title": "Kahe Dil Yeh Deewana (HD) - Baap Re Baap Song - Chand Usmani",
    "score": 10
  },
  {
    "id": "5TPMRs3C0jU",
    "title": "Jab Tumne Mohabbat (HD) - Amaanat (1955) - Chand Usmani - Bharat Bhushan - Asha Bhosle",
    "score": 10
  },
  {
    "id": "Y412-Wb7ALU",
    "title": "Search filters",
    "score": 10
  },
  {
    "id": "AuYPo1qtZiU",
    "title": "The Scandal That Nearly Destroyed the Vatican Bank",
    "score": 10
  },
  {
    "id": "7yBsBrLWm_w",
    "title": "Tangled Web: BCCI Bank Scandal (1991)",
    "score": 10
  },
  {
    "id": "g-pE3eAMwT8",
    "title": "Danske Bank's €200 Billion Blunder: How One Scandal Sparked Europe's AML Overhaul",
    "score": 10
  },
  {
    "id": "u0cnyxr3Z1o",
    "title": "How Silicon Valley Bank Collapsed in 36 Hours | WSJ What Went Wrong",
    "score": 10
  },
  {
    "id": "QACGoKb48_0",
    "title": "SVB’s collapse forced bank closures, rattled global markets and threatened startups",
    "score": 10
  },
  {
    "id": "l9LVMP7UmGM",
    "title": "The great bank heist: Malema, Shivambu, Matodzi, and the VBS scandal",
    "score": 10
  },
  {
    "id": "geMQgBnaHC0",
    "title": "Inside America’s Biggest Banking Fraud | The Wells Fargo Scandal",
    "score": 10
  },
  {
    "id": "2JZEhv0HWU0",
    "title": "When a Bank Scam Reveals a Secret in the Relationship",
    "score": 10
  },
  {
    "id": "hunhSI4r9JM",
    "title": "Initial Contact with Suspects Outside",
    "score": 10
  },
  {
    "id": "k2APYPjTWZ8",
    "title": "Why Wealthy Americans Love UBS, The Secretive Swiss Banking Giant",
    "score": 10
  },
  {
    "id": "YXTXNzyOMCk",
    "title": "Introduction",
    "score": 10
  },
  {
    "id": "3IyIc5TcHPc",
    "title": "Introduction",
    "score": 10
  },
  {
    "id": "0I0cdP021bg",
    "title": "The Danske Bank Scandal Explainer",
    "score": 10
  },
  {
    "id": "ZAnMUMDiO7U",
    "title": "The Fall of a Speaker: Jim Wright's 1989 House Banking Scandal Explained",
    "score": 10
  },
  {
    "id": "jRiEG6a6uKI",
    "title": "Riad Salameh: Lebanon’s $300M Banking Scandal EXPOSED",
    "score": 10
  },
  {
    "id": "0OHmoLaz5Kc",
    "title": "The Crazy Crane Bank Scandal",
    "score": 10
  },
  {
    "id": "WY9F5G57bjU",
    "title": "The Secret Bank That Was Too Corrupt to Fail: The BCCI Scandal",
    "score": 10
  },
  {
    "id": "sdo3zJY5bMs",
    "title": "Introduction",
    "score": 10
  },
  {
    "id": "H0wmUqpMcEg",
    "title": "Introduction to Money Laundering",
    "score": 10
  },
  {
    "id": "fbSSSIU_KGM",
    "title": "Corruption in Andorra | Scandal | Bank Systems",
    "score": 10
  },
  {
    "id": "I7H3rwNElbU",
    "title": "€200 BILLION Danske Bank Fraud!! Money Laundering Machine 💶",
    "score": 10
  },
  {
    "id": "f8iPIV9cBAs",
    "title": "Intro",
    "score": 10
  },
  {
    "id": "b3BgBFNzqcQ",
    "title": "Search filters",
    "score": 10
  },
  {
    "id": "ZBuEJ7bymzY",
    "title": "Kadambari Devi's Suicide Note || Voiced by: Varsha Pramanik || 🖤",
    "score": 10
  },
  {
    "id": "Mtd1ABQYv2A",
    "title": "কাদম্বরীদেবীর, সুইসাইড-নোটে ঠিক কি লেখা  ছিল? | Antara Das",
    "score": 10
  },
  {
    "id": "vWNzVttBWt8",
    "title": "Notun Bouthan | Sruti Natok | Jagannath Basu - Urmimala Basu | Written by Soumitra Basu |",
    "score": 10
  },
  {
    "id": "DF8HG_qRgzU",
    "title": "Srikanta O Indranath By Sarat Chandra Chattopadhyay | Mir | Kanchan | #GoppoMirerThek Full Episode",
    "score": 10
  },
  {
    "id": "aF20OmIBt68",
    "title": "রবীন্দ্রনাথ কাদম্বরী দেবী কতটা প্রেম? আর কতটা সত্যি? মুখরোচক গল্প ছেড়ে সত্যিটা জানুন",
    "score": 10
  },
  {
    "id": "DDEjyczaf-Q",
    "title": "Hathat Dekha | হঠাৎ দেখা - Bengali Full Movie | Debashree Roy | Shankar Chakraborty",
    "score": 10
  },
  {
    "id": "eWxKrRSxi0Y",
    "title": "কাদম্বরী দেবী KadambariDebir Suicide Note by Ranjan Bandyopadhyay",
    "score": 10
  },
  {
    "id": "efCUZPXssMk",
    "title": "মনে খুব আঘাত দিলে না কেঁদে ৪টি কাজ করুন 😊 Sayed Mokarram Bari || Best Islamic Motivation ||",
    "score": 10
  },
  {
    "id": "YIGuFUpTJ6A",
    "title": "আমি রবিঠাকুরের বউ | Epi. 09 | Ami Robi Thakurer Bou | Sahityer Sera Somoy | Aakash Aath |",
    "score": 10
  },
  {
    "id": "gJlTW49LoIk",
    "title": "Kacher Sure | Kadambori | KonkonaSen Sharma | Srabani Sen | Bickram Ghosh",
    "score": 10
  },
  {
    "id": "xXliSJv2dO4",
    "title": "Tribute to Kadambari Devi | Rabindra Sangeet |  Kadambari Devi | Bengali Songs",
    "score": 10
  },
  {
    "id": "mmUyV8_dIqA",
    "title": "Gyanadanandini Devi | Gyandanandini Devi | Mejo Bouthan of Rabindranath Tagore | Antara Das",
    "score": 10
  },
  {
    "id": "qbW9Gd_3PqQ",
    "title": "রবীন্দ্রনাথ ঠাকুরের জন্য প্রাণ দিয়েছিলেন যে নারী | Rabindranath Love Story |  Kadambari Devi | Rtv",
    "score": 10
  },
  {
    "id": "y00mBPPJQpU",
    "title": "বিদায়, নতুন বৌঠান | Biday, Notun Bouthan | Ditipriya",
    "score": 10
  },
  {
    "id": "dUtEjQuzBqs",
    "title": "রবীন্দ্রনাথ ঠাকুরের নিজ জীবনের গল্প কাদম্বরী. Kadambari movie explain in bangla.",
    "score": 10
  },
  {
    "id": "bVbcEv5hLss",
    "title": "কাদম্বরী দেবীর সুইসাইড নোট | রবীন্দ্রনাথের নতুন বৌঠানের শেষ চিঠি |",
    "score": 10
  },
  {
    "id": "98v2jU7kR0Q",
    "title": "BOUTHAN ER SESH CHITHI, 1941।।  BAISHE SRABON ।। RABINDRANATH TAGORE ।। AMARTYA ।। MAYURIKA",
    "score": 10
  },
  {
    "id": "DBRitssW-Vk",
    "title": "Search filters",
    "score": 10
  },
  {
    "id": "Vcwhe0pY4Bg",
    "title": "BossMan Dlow - Finesse ft. GloRilla",
    "score": 10
  },
  {
    "id": "NwfVDKGkZfo",
    "title": "Finesse",
    "score": 10
  },
  {
    "id": "WPuP-qkhkuI",
    "title": "Finesse",
    "score": 10
  },
  {
    "id": "Vzkr-G1QEh8",
    "title": "Bryson Tiller - Finesse (Drake Cover) lyrics",
    "score": 10
  },
  {
    "id": "uHiM3SLiVjI",
    "title": "Finesse (feat. Koncept P, willnosleep \\u0026 avonosleep)",
    "score": 10
  },
  {
    "id": "Gz_HEtzYT1o",
    "title": "FOOD STAMPS FINESSE... SNAP Benefits are GOING UP 30% and how you're incentivized to stay poor",
    "score": 10
  },
  {
    "id": "hyAq8UhJzt0",
    "title": "Finesse2Tymes - Finesse Duh P [Official Audio]",
    "score": 10
  },
  {
    "id": "Tb6pM4Gqhn4",
    "title": "Finesse TwoTymes Dissing ASAP | \\\"Food Stamps\\\" Freestyle",
    "score": 10
  },
  {
    "id": "7XJsJzbuQVE",
    "title": "Bruno Mars - Finesse (Official Audio)",
    "score": 10
  },
  {
    "id": "MRSaiAREnwI",
    "title": "TRUMP cracking down on FOOD STAMPS #trumpnews",
    "score": 10
  },
  {
    "id": "Mxd_lYdo0Gk",
    "title": "Search filters",
    "score": 10
  },
  {
    "id": "LZ_BG6xGyQk",
    "title": "NATE DIAZ SLAPS \\\"FULL SEND\\\" REPORTER AT UFC 276",
    "score": 10
  },
  {
    "id": "q8YoVROsDBY",
    "title": "Man Slaps Friend's Belly to Motivate Him as He Struggles While Lifting Weights - 1113182-1",
    "score": 10
  },
  {
    "id": "k_tgU3nmArA",
    "title": "KSI SLAPS Dillon Danis with PANCAKE as BRAWL breaks out during face off at presser",
    "score": 10
  },
  {
    "id": "u9S8EYah6p0",
    "title": "HEATED! Canelo Alvarez \\u0026 Caleb Plant trade punches at pre-fight press conference 😡",
    "score": 10
  },
  {
    "id": "eTN9xDspQqw",
    "title": "Power Slap 16: Post-Match Press Conference",
    "score": 10
  },
  {
    "id": "OiHY-8OSuro",
    "title": "Power Slap 15: Post-Match Press Conference",
    "score": 10
  },
  {
    "id": "srXkV1Xzm0A",
    "title": "Pre-Fight Press Conference | Power Slap 1 Finale",
    "score": 10
  },
  {
    "id": "ZhKuaSe1d6I",
    "title": "Power Slap 12: Post-Match Press Conference",
    "score": 10
  },
  {
    "id": "cAzc4tdEPF0",
    "title": "Mike Tyson slaps Jake Paul during ceremonial weigh-ins | ESPN Ringside",
    "score": 10
  },
  {
    "id": "PyI7vGy-Fos",
    "title": "Power Slap 12: Post-Match Press Conference",
    "score": 10
  },
  {
    "id": "beD4HmWHpmQ",
    "title": "Power Slap 2 Press Conference Highlights",
    "score": 10
  },
  {
    "id": "eV5wptDimZo",
    "title": "The Day President's Wife Stormed Kenyan Newspaper and Slapped Cameraman",
    "score": 10
  },
  {
    "id": "nmOCylyhSQc",
    "title": "Conor McGregor Smacks Floyd Mayweather's Head: \\\"Do Something Slap-Head\\\"",
    "score": 10
  },
  {
    "id": "ukUBrbLMZDc",
    "title": "Power Slap 11: Post-Match Press Conference",
    "score": 10
  },
  {
    "id": "G75nnol4ei4",
    "title": "Power Slap Press Conference with Dana White",
    "score": 10
  },
  {
    "id": "CSDeGysOOPo",
    "title": "\\\"OUTSIDE RING CHAOS\\\" Teofimo Lopez SLAPS Shakur Stevenson at Heated Presser!",
    "score": 10
  },
  {
    "id": "j-ALV0uISQA",
    "title": "Dana White vs. Reporter on Power Slap: “You know who’s laughing? This guy!”",
    "score": 10
  },
  {
    "id": "_VsMdwh5Y7c",
    "title": "AARON THE PLUMBER FIGHT AFTER GETTING SLAPPED👀#viral #trending #20vs1 #aarontheplumber #fight #slap",
    "score": 10
  },
  {
    "id": "V_DoHo1R1k4",
    "title": "Power Slap 13: Post-Match Press Conference",
    "score": 10
  },
  {
    "id": "SDAnYfgUD5A",
    "title": "Playing Slap \\u0026 Press on African Drums",
    "score": 10
  },
  {
    "id": "9wNpKiu_xKg",
    "title": "Intro",
    "score": 10
  },
  {
    "id": "SUQex68L6SQ",
    "title": "Search filters",
    "score": 10
  },
  {
    "id": "wvvnKJzxONQ",
    "title": "Shane Gillis vs The View.. Comedian Responds After Talk Show Remarks Go Viral",
    "score": 10
  },
  {
    "id": "uHRK4_czzmg",
    "title": "CERN's 2026 Run Just Detected a Particle That Reacts to Human Presence",
    "score": 10
  },
  {
    "id": "sgnyQcbz7c8",
    "title": "The Anomaly CERN Won't Talk About",
    "score": 10
  },
  {
    "id": "S8JF-n4Ixks",
    "title": "Intro",
    "score": 10
  },
  {
    "id": "pXvzjslK7lc",
    "title": "Prince Harry REACTS To Trump’s NATO Comments w/ Bold Statement",
    "score": 10
  },
  {
    "id": "bncY3mrnMt8",
    "title": "Introduction and Welcome",
    "score": 10
  },
  {
    "id": "G-71LzlEPcg",
    "title": "Carney responds to Trump's 100% tariff threat, says China deal consistent with CUSMA",
    "score": 10
  },
  {
    "id": "Vrrn3h4ghEg",
    "title": "I Analyzed 50 TOEFL Speaking Answers – Here’s What Gets a 26+",
    "score": 10
  },
  {
    "id": "t1VK-SPlQhY",
    "title": "#IlhanOmar was attacked while speaking in #minneapolis. Her response speaks volumes. #trump",
    "score": 10
  },
  {
    "id": "ZeHhsa6L0UA",
    "title": "Donald Trump speaks as world reacts in horror to Bondi Beach mass shooting",
    "score": 10
  },
  {
    "id": "sGiNAauowEs",
    "title": "Smith responds to B.C. premier's traitor claims over Alberta separatists seeking help from U.S.",
    "score": 10
  },
  {
    "id": "PheAhObsxVQ",
    "title": "IELTS Speaking Band 9.0 - Advanced Answers",
    "score": 10
  },
  {
    "id": "jYk0pvSiNhQ",
    "title": "Most Common IELTS Speaking Part 1 Questions and Answers",
    "score": 10
  },
  {
    "id": "FUNeZlSQhRY",
    "title": "Introduction",
    "score": 10
  },
  {
    "id": "jVWBU0gEX9M",
    "title": "Report on Rep. Ilhan Omar’s attack at a town hall in Minneapolis",
    "score": 10
  },
  {
    "id": "gX9M_kfuZg4",
    "title": "Rakai Responds To Kai Cenat’s Ex Gigi For Speaking On Him 👀🤔",
    "score": 10
  },
  {
    "id": "24TofRZuxFI",
    "title": "GD v BDs! Akademiks reacts to Fivio Foreign speaking on his encounter w Rooga in the Studio! ",
    "score": 10
  },
  {
    "id": "ROhYRmytUYc",
    "title": "Search filters",
    "score": 10
  },
  {
    "id": "MdpIjE1k4YI",
    "title": "Eddie Rabbitt- Step By Step",
    "score": 10
  },
  {
    "id": "94XfyjRo-DE",
    "title": "New Kids On The Block - Step By Step",
    "score": 10
  },
  {
    "id": "iCrargw1rrM",
    "title": "Whitney Houston - Step By Step (Official HD Video)",
    "score": 10
  },
  {
    "id": "sWa5vE4MUpU",
    "title": "step by step - fadinglight (pitched down + reverbed + looped)",
    "score": 10
  },
  {
    "id": "HTudDGPGmMQ",
    "title": "Step by Step",
    "score": 10
  },
  {
    "id": "rk2Btm15W58",
    "title": "Step by Step – Soulful Original Gospel Song | Inspirational Faith Music | Lyrics in Description",
    "score": 10
  },
  {
    "id": "4uufk4bdRGc",
    "title": "STEP BY STEP (1991 vs 2023) Cast: Then and Now [32 Years After]",
    "score": 10
  },
  {
    "id": "ILXgJyIMVcE",
    "title": "Intro",
    "score": 10
  },
  {
    "id": "htNphBVfl4w",
    "title": "Step by Step - Best of Cody",
    "score": 10
  },
  {
    "id": "SovQU4N5hj4",
    "title": "Man's Prayer Over President Donald Trump Goes Viral",
    "score": 10
  },
  {
    "id": "YpCJMR7wK9A",
    "title": "30TH JANUARY, FRIDAY 2026, MOST POWERFUL SPIRITUAL MORNING WARFARE PRAYER BY APOSTLE JOSHUA SELMAN",
    "score": 10
  },
  {
    "id": "-Ki1EmOnwGk",
    "title": "January 30th | Pray This to Win the Battle in Your Mind | Releasing Fear and Overthinking with God",
    "score": 10
  },
  {
    "id": "0ZMMKepkj68",
    "title": "💖His heart bleeds when it comes to you💖",
    "score": 10
  },
  {
    "id": "iZrgvKyGTFw",
    "title": "What Red Flags Should You Look For In a Company?",
    "score": 10
  },
  {
    "id": "rEBa0dm8zTA",
    "title": "A PRIMERA HORA | Gobierno niega crisis interna | 30/01/26",
    "score": 10
  },
  {
    "id": "o8o9Uq3nEuY",
    "title": "Merz stoppt schnellen EU-Beitritt der Ukraine: Jetzt kippt der US-Friedensplan!",
    "score": 10
  },
  {
    "id": "NBtL7B22F6A",
    "title": "\\\"The Williams Sisters\\\" Step By Step 1996",
    "score": 10
  },
  {
    "id": "gX8Pe5alcrg",
    "title": "Step By Step - \\\"Carol's Nasty Aunt (Doris Roberts) Visits for Christmas\\\" - 1994",
    "score": 10
  },
  {
    "id": "HZLdKRGMGRE",
    "title": "Hook Step Lyrical | Mana ShankaraVaraPrasad Garu | Chiranjeevi | Anil Ravipudi | Bheems |Baba Sehgal",
    "score": 10
  },
  {
    "id": "Bh-tOJ8UAXA",
    "title": "Gazza ft Jaliza - Step by step (Official Audio)",
    "score": 10
  },
  {
    "id": "00I-eIB15uo",
    "title": "Olivia Dean - Baby Steps (Lyric Video)",
    "score": 10
  },
  {
    "id": "6kLEQi0u5rA",
    "title": "\\\"Step By Step\\\" Sing-A-Long! 🧩🎵 | Rainbow High Music",
    "score": 10
  },
  {
    "id": "wS7ghKb6H9k",
    "title": "Step By Step",
    "score": 10
  },
  {
    "id": "uRtR1FU2Rko",
    "title": "Step by Step (Lyric Video)",
    "score": 10
  },
  {
    "id": "-b73Fg8TwG8",
    "title": "When Cody Saves Karen | Step By Step TV Series",
    "score": 10
  },
  {
    "id": "Spq-g2XyjOA",
    "title": "Dana vs. Karen | Step By Step TV Series",
    "score": 10
  },
  {
    "id": "bgQiIx-nkl4",
    "title": "𝒔𝒕𝒆𝒑 𝒃𝒚 𝒔𝒕𝒆𝒑 - 𝒇𝒂𝒅𝒊𝒏𝒈 𝒍𝒊𝒈𝒉𝒕 (𝒔𝒍𝒐𝒘𝒆𝒅)",
    "score": 10
  },
  {
    "id": "5bKvmrg8bPU",
    "title": "Step By Step Season One Theme Song- Sasha Mitchell Version",
    "score": 10
  },
  {
    "id": "9g94bPMtxtM",
    "title": "When Cody Saves Dana | Step By Step TV Series",
    "score": 10
  },
  {
    "id": "O12RqN0g5bM",
    "title": "Search filters",
    "score": 10
  },
  {
    "id": "BHIKbzD_KSs",
    "title": "গেমের জন্য তাদের ছেলেটি পালালো?  | Habji Gabji | Subhashree, Parambrata| Raj Chakraborty | hoichoi",
    "score": 10
  },
  {
    "id": "3q0xu27Kbko",
    "title": "তার ছেলে গেমের পাগল! | Habji Gabji | Subhashree, Parambrata| Raj Chakraborty | hoichoi",
    "score": 10
  },
  {
    "id": "ICNycs6gQKw",
    "title": "Dure | Habji Gabji | Papon | Iman | Srijato | Indraadip | Subhashree | Parambrata",
    "score": 10
  },
  {
    "id": "l2pwNKI_CGs",
    "title": "শুভশ্রীর কপি ক্যাট | Habji Gabji | Subhashree Ganguly | Samontak Dyuti Maitra | Parambrata | Raj",
    "score": 10
  },
  {
    "id": "16dIyByf_uQ",
    "title": "গেমের জন্য মিথ্যা বলল! | Habji Gabji | Subhashree, Parambrata| Raj Chakraborty | hoichoi",
    "score": 10
  },
  {
    "id": "IDNRtuodcgQ",
    "title": "গেম না পেয়ে মাকে অপমান! | Habji Gabji | Subhashree, Parambrata| Raj Chakraborty | hoichoi",
    "score": 10
  },
  {
    "id": "XJ2pyA5OLsg",
    "title": "বাবার বিরুদ্ধে যুদ্ধ! | Habji Gabji | Subhashree, Parambrata| Raj Chakraborty | hoichoi",
    "score": 10
  },
  {
    "id": "R6LUjktBiFc",
    "title": "নারীদের এখনো ভোগ্যপণ্য হিসেবে ভাবা হচ্ছে: শুভশ্রী | Subhashree Ganguly | Bijoy Entertainment",
    "score": 10
  },
  {
    "id": "vx3i1y-0Igo",
    "title": "Byomkesh Bakshi | কামলালসার রহস্যভেদ | Detective Audio Story | Bengali Audio Story | Sunday Suspense",
    "score": 10
  },
  {
    "id": "l8ewKJBrR8I",
    "title": "আমেরিকায় তুষার ঝড়ে কেমন আছি আমরা 😊snowstorm in America,how are we doing ",
    "score": 10
  },
  {
    "id": "IDDwDcECjs8",
    "title": "গেমের কারনে ছেলে এখন হাসপাতালে! | Habji Gabji | Subhashree, Parambrata| Raj Chakraborty | hoichoi",
    "score": 10
  },
  {
    "id": "Sz69YhvESzI",
    "title": "হাবজি গাবজি থেকে ইউভান-  আড্ডায় রাজ শুভশ্রী | Exclusive Interview | Habji Gabji | Raj | Subhashree",
    "score": 10
  },
  {
    "id": "HyJBH-81w8c",
    "title": "Mobile Games-এ addicted খুদেরা কি করলো শুভশ্রীকে দেখে? | Habji Gabji | Subhashree | Parambrata",
    "score": 10
  },
  {
    "id": "fTL6lEbQG3A",
    "title": "বাসার বাসন বেচে ফুটানি! | Indubala Bhaater Hotel|Subhashree | Parijat| Debaloy Bhattacharya |hoichoi",
    "score": 10
  },
  {
    "id": "bioOwXMn9CU",
    "title": "'বাংলা ছবির পাশে দাঁড়ান' নিয়ে কী বললেন শুভশ্রী | Subhashree Ganguly | Dr. Bakshi",
    "score": 10
  },
  {
    "id": "IC8lx6ynnWI",
    "title": "আমার মেয়েকে মোটা বলার তুই কে? শুভশ্রীকে ধুয়ে দিলেন কোয়েল ৷ Subhashree Ganguly",
    "score": 10
  },
  {
    "id": "4_Odb3G_ZeQ",
    "title": "সিপিএম, হুমায়ুন কবীর, আইএসএফ কংগ্রেস জোট ২০২৬ এর নির্বাচনে সম্ভব? হলে তার ফল কী হবে?",
    "score": 10
  },
  {
    "id": "EC0ZPmOksVc",
    "title": "চেনো কি আমায় | Subhashree Ganguly | Know The Star | Habji Gabji | Exclusive Interview | Siti Cinema",
    "score": 10
  },
  {
    "id": "TB3NQ65olSc",
    "title": "গেম যখন reel থেকে real -এ | Habji Gabji | Subhashree, Parambrata| Raj Chakraborty | hoichoi",
    "score": 10
  },
  {
    "id": "rnv5JCrTtII",
    "title": "Habji Gabji |Raj Chakraborty | Subhashree | Parambrata  || PREMIER HABJI GABJI",
    "score": 10
  },
  {
    "id": "ilCuPKdLHsI",
    "title": "Habji Gabji | Releasing On 3rd June | Raj Chakraborty | Subhashree | Parambrata | RCE",
    "score": 10
  },
  {
    "id": "Whr3M4P2RKE",
    "title": "Chaamp - Hindi Dubbed Full Movie | Dev | Rukmini Maitra | Raj Chakroborty | Jeet Gannguli",
    "score": 10
  },
  {
    "id": "0xEFF6FmdE8",
    "title": "মোবাইল না দিলে বিপদ! | Habji Gabji | Subhashree, Parambrata| Raj Chakraborty | hoichoi",
    "score": 10
  },
  {
    "id": "Xq9WuCAgN2E",
    "title": "হাসপাতালে ছেলে, তারা কোথায়?| Habji Gabji | Subhashree, Parambrata| Raj Chakraborty | hoichoi",
    "score": 10
  },
  {
    "id": "M44mCqgvOlU",
    "title": "Phone Addiction Se Mukti Pao🤪All The Best Subhashree Ganguly Raj Chakraborty  For Habji Gabji :)",
    "score": 10
  },
  {
    "id": "-vgmeKgjX_w",
    "title": "Search filters",
    "score": 10
  }
]