[
  {
    "id": "Wh7fM_VBrsk",
    "title": "5 ניסויים מדעיים בספיישל מיוחד של ניסויים מדעיים עם ילדים 🧪 | רפאל המטייל ויאנצ'יקס",
    "score": 60
  },
  {
    "id": "-scoD7XQ288",
    "title": "5 ניסויים מדעיים בספיישל מיוחד 2 ! ניסויים מדעיים עם ילדים 🧪 | רפאל המטייל ויאנצ'יקס",
    "score": 60
  },
  {
    "id": "2oDdsK1PCnc",
    "title": "קיסמי שיניים זזים מעצמם ויוצרים כוכב",
    "score": 60
  },
  {
    "id": "Ll3yKFl2zH4",
    "title": "ניסויים מדעיים לילדים - מטבע טובע",
    "score": 60
  },
  {
    "id": "gbCUwCykzko",
    "title": "ניסוי החץ המתהפך",
    "score": 60
  },
  {
    "id": "Vp-rcdwuxGc",
    "title": "ניסוי הר געש-מתאים לילדים ופשוט ביותר!",
    "score": 60
  },
  {
    "id": "Bjc5MCVLSYE",
    "title": "לגרום לדברים להיעלם! | אור | ניסויים מדעיים לילדים | RTÉjr",
    "score": 60
  },
  {
    "id": "s7XgfF6SVwY",
    "title": "4 ניסויי מדע מדהימים ליום אחד בפנים | אוסף | SciShow Kids",
    "score": 60
  },
  {
    "id": "SGUMC19IISY",
    "title": "The Entire History of Physics Explained — From Aristotle to Quantum Reality",
    "score": 50
  },
  {
    "id": "245RCAuFACg",
    "title": "Listen and learn Spanish with Subtitles",
    "score": 50
  },
  {
    "id": "GkqwWesdLhE",
    "title": "33 AMAZING SCIENCE EXPERIMENTS! Compilation | Best of the Year",
    "score": 50
  },
  {
    "id": "1JIF8GcWeKA",
    "title": "EASY SCIENCE EXPERIMENTS TO DO AT HOME",
    "score": 50
  },
  {
    "id": "n09iGowWdLY",
    "title": "40 Science Experiments - Experiments You Can Do at Home Compilation by Inventor 101",
    "score": 50
  },
  {
    "id": "_ZizKQqHNgI",
    "title": "29 SCIENCE TRICKS that look like real MAGIC",
    "score": 50
  },
  {
    "id": "hX8dTJXt9TY",
    "title": "SATISFYING EASY SCIENCE EXPERIMENTS to do at home BY 5-minute MAGIC",
    "score": 50
  },
  {
    "id": "UXQugQPSLmA",
    "title": "Megastructures: Building Wonders of Modern Mankind | FD Engineering",
    "score": 50
  },
  {
    "id": "IkFB4VM3zeg",
    "title": "Discover the Giant Roller Bearing Factory That Feeds Heavy Industry. Modern Production Documentary",
    "score": 50
  },
  {
    "id": "DtDw9qV_wmI",
    "title": "IMPOSSIBLE PLACES | The Most Unbelievable Megaprojects in the World | 4K Travel Documentary",
    "score": 50
  },
  {
    "id": "NvzxNm3Mxcs",
    "title": "World’s Most Extreme Railway | Megastructures | Free Documentary",
    "score": 50
  },
  {
    "id": "9GTjLYijZBg",
    "title": "World War 2 Explained | Best WW2 Documentary | Part 1",
    "score": 50
  },
  {
    "id": "9kON1isHtyA",
    "title": "Hell On Earth: The Complete, Uncensored History Of World War II",
    "score": 50
  },
  {
    "id": "mNVwzUW2FJM",
    "title": "The Full History of World War Two | On the Edge of the Abyss",
    "score": 50
  },
  {
    "id": "_jX6NdiDElM",
    "title": "The Complete History of the Second World War | World War II Documentary | Part 2",
    "score": 50
  },
  {
    "id": "Sg4GMVMdOPo",
    "title": "Python Full Course for Beginners",
    "score": 50
  },
  {
    "id": "NpmFbWO6HPU",
    "title": "How To Navigate These Projects",
    "score": 50
  },
  {
    "id": "yVl_G-F7m8c",
    "title": "Python for Data Science - Course for Beginners (Learn Python, Pandas, NumPy, Matplotlib)",
    "score": 50
  },
  {
    "id": "LHBE6Q9XlzI",
    "title": "Python Tutorials for Beginners - Learn Python Online",
    "score": 50
  },
  {
    "id": "CMEWVn1uZpQ",
    "title": "Intermediate Python Programming Course",
    "score": 50
  },
  {
    "id": "ygXn5nV5qFc",
    "title": "Introduction: Learn Python for AI",
    "score": 50
  },
  {
    "id": "ix9cRaBkVe0",
    "title": "1.python tutorial for beginners",
    "score": 50
  },
  {
    "id": "kqtD5dpn9C8",
    "title": "Learn Python - Full Course for Beginners [Tutorial]",
    "score": 50
  },
  {
    "id": "t8pPdKYpowI",
    "title": "Course Intro \\u0026 Course Overview",
    "score": 50
  },
  {
    "id": "nLRL_NcnK-4",
    "title": "Learn Python in Less than 10 Minutes for Beginners (Fast \\u0026 Easy)",
    "score": 50
  },
  {
    "id": "GwADruxCpWg",
    "title": "Learn 10 Advanced Bushcraft \\u0026 Survival Skills!",
    "score": 50
  },
  {
    "id": "qbETGQUOMZk",
    "title": "Learn 10 Beginner Bushcraft \\u0026 Survival Skills!",
    "score": 50
  },
  {
    "id": "8VrgeLeruFo",
    "title": "Building an Elevated Survival Shelter with Rope Ladder to Stay Safe from Ground Predators",
    "score": 50
  },
  {
    "id": "y2lgutQ0HLg",
    "title": "HOW TO DRAW A PERSON! (Beginner Friendly Step by Step)",
    "score": 50
  },
  {
    "id": "SDQEaJY291A",
    "title": "How to sketch anything intro",
    "score": 50
  },
  {
    "id": "7Qy_13MInxI",
    "title": "Draw a flower 🌸 Easy drawing lesson for beginners on how to draw a flower. #drawinglesson#howtodraw",
    "score": 50
  },
  {
    "id": "1v4QIHZKEl0",
    "title": "Coolest New Technologies of 2026",
    "score": 50
  },
  {
    "id": "1ZMCM3W5Veo",
    "title": "2060 Will Be Unrecognizable (15 Technologies)",
    "score": 50
  },
  {
    "id": "q4S19AZV99Y",
    "title": "2050: 20 Technologies That Sound Impossible",
    "score": 50
  },
  {
    "id": "9He9hoo3agk",
    "title": "15 CRAZY FUTURE TECHNOLOGY IDEAS YOU'LL SEE SOON",
    "score": 50
  },
  {
    "id": "Hb5sRAzY6Jc",
    "title": "Top 5 Future Technology Inventions | 2019 - 2050",
    "score": 50
  },
  {
    "id": "vbNHCn2gHQ4",
    "title": "Coolest New Technologies of 2025",
    "score": 50
  },
  {
    "id": "uUdDQSb5Jqo",
    "title": "Future Technology | 60 Minutes Marathon",
    "score": 50
  },
  {
    "id": "CbOmgCF8KCE",
    "title": "Future City 3000: The Age of Future Tech | Sci-fi AI Short Film (4K)",
    "score": 50
  },
  {
    "id": "jE8C0FHWuks",
    "title": "The World in 2050: Future Technology Will Leave You Speachless",
    "score": 50
  },
  {
    "id": "b0HfmY64eSE",
    "title": "TIMELAPSE OF FUTURE TECHNOLOGY: 2022 - 4000+",
    "score": 50
  },
  {
    "id": "dO8y-yWbkG8",
    "title": "Vector (Leon) \\u0026 Luis (Part 7) - Resident Evil 4 Remake Mod GFL2",
    "score": 50
  },
  {
    "id": "RskvZgc_s9g",
    "title": "Bhai Manjh Ji \\u0026 Guru Arjan Dev Ji || Info Saakhi Series Episode-6 || Sikh Itihaas (history)",
    "score": 50
  },
  {
    "id": "uAIaasx1cpQ",
    "title": "Bhai Nand Lal ji \\u0026 Guru Gobind Singh Ji || Info Saakhi Series Episode-5 || Sikh itihaas (History)",
    "score": 50
  },
  {
    "id": "aj7oF5jtWig",
    "title": "Sikhism introduction | World History | Khan Academy",
    "score": 50
  },
  {
    "id": "uWAUKbBqGoU",
    "title": "BHAI MANI SINGH JI | Info Saakhi Series Episode-8 (Part-1) | Sikh Animation | Sikh Itihaas(History)",
    "score": 50
  },
  {
    "id": "8WN0dYDy1c4",
    "title": "Guru Nanak Dev ji  (Part-2) | Info Saakhi series | Sikh History | Sikh Bedtime Stories",
    "score": 50
  },
  {
    "id": "jdYXVtKZz5k",
    "title": "Bhai Satta Bhai Balwand || Info Saakhi Series Episode 3 || Sikh Saakhiyan || Sikh itihas(history)",
    "score": 50
  },
  {
    "id": "RlKylyDn3d0",
    "title": "Saakhi- Baba Deep Singh Jee | New Series for kids | Sikh History | Anaahad Media | ਖਾਲਸੇ ਦਾ ਇਤਿਹਾਸ",
    "score": 50
  },
  {
    "id": "BnbVeEnEjZI",
    "title": "Sikh Warriors Explained - Nanak Dev, Nihangs, Faith \\u0026 Forgotten History | Guru Nidar Singh | TRS",
    "score": 50
  },
  {
    "id": "Bh1YxJO2rV8",
    "title": "Guru Nanak Dev ji and the Rogi || Learning Sikh History || Saakhi Videos || Bedtime Stories For kids",
    "score": 50
  },
  {
    "id": "__A3e5kop0c",
    "title": "Cheerleader FRIENDZONES Nice Guy!!!! He Teaches Her A Lesson She'll NEVER FORGET",
    "score": 50
  },
  {
    "id": "-MNnAPzBgn0",
    "title": "Stop Getting Friend Zoned - The Mistakes Nice Guys Make",
    "score": 50
  },
  {
    "id": "jPNofva1xEA",
    "title": "The Science of the Friend Zone",
    "score": 50
  },
  {
    "id": "e4w2nnPD6SQ",
    "title": "Dan distracts everyone to make his plans work | Home Sweetie Home Recap | February  29, 2020",
    "score": 50
  },
  {
    "id": "vg8lCKzocAc",
    "title": "Mafaad Parast Episode 61 - 1st February 2026 - Har Pal Geo - Mafad Parast Ep 61 Teaser Promo Review",
    "score": 50
  },
  {
    "id": "uMRfFhSsZ4Y",
    "title": "How to lace shoes | How to tie your shoelaces 024",
    "score": 50
  },
  {
    "id": "WGNM2U2jvX4",
    "title": "Fast Talk with Boy Abunda: Angelica Panganiban makes her showbiz comeback! (Full Episode 747)",
    "score": 50
  },
  {
    "id": "2KaRW-Nt4ZI",
    "title": "Beginner's Guide to Buying a BBQ Grill",
    "score": 50
  },
  {
    "id": "Am8DdAqEzBo",
    "title": "How To Choose The PERFECT Grill",
    "score": 50
  },
  {
    "id": "1-3MqPagoso",
    "title": "Melissa Makes Crab in Coconut Milk (Ginataang Alimasag) | From the Home Kitchen | Bon Appétit",
    "score": 50
  },
  {
    "id": "prLxLwcCunw",
    "title": "How to Cook Halabos na Alimasag",
    "score": 50
  },
  {
    "id": "YF_n4lgNnNk",
    "title": "Big Mud Crabs Catching - how to scan muddy for big mud crabs in rainy day #fishing #oyster #seafood",
    "score": 50
  },
  {
    "id": "ZAqIoDhornk",
    "title": "ALL OF PHYSICS explained in 14 Minutes",
    "score": 10
  },
  {
    "id": "9aTTC4DInDw",
    "title": "But What Actually Is a Particle? How Quantum Fields Shape Reality",
    "score": 10
  },
  {
    "id": "KLIS4lq1mBE",
    "title": "Intro",
    "score": 10
  },
  {
    "id": "mYcLuWHzfmE",
    "title": "Intro",
    "score": 10
  },
  {
    "id": "BHEhxPuMmQI",
    "title": "The subatomic world",
    "score": 10
  },
  {
    "id": "npYo7ee_fr0",
    "title": "The Biggest Misconception in Physics",
    "score": 10
  },
  {
    "id": "lcjdwSY2AzM",
    "title": "What is symmetry?",
    "score": 10
  },
  {
    "id": "b1t41Q3xRM8",
    "title": "Intro",
    "score": 10
  },
  {
    "id": "oKKSC9V2ETI",
    "title": "How Physicists Proved Everything is Quantum - Nobel Physics Prize 2025 Explained",
    "score": 10
  },
  {
    "id": "_mVBbdbqHmw",
    "title": "Nobel Prize 2025: Proving Size Doesn't Matter",
    "score": 10
  },
  {
    "id": "_TBNJyztai0",
    "title": "Radical simplicity in physics",
    "score": 10
  },
  {
    "id": "vjDvBP5IU-4",
    "title": "Energy Cannot Be Created or Destroyed. But Why?",
    "score": 10
  },
  {
    "id": "5DmLaNYBoWo",
    "title": "The One Principle That Explains All of Physics",
    "score": 10
  },
  {
    "id": "ax5Ne4liG6s",
    "title": "Level 1 to 100 Physics Concepts to Fall Asleep to",
    "score": 10
  },
  {
    "id": "ZffEvgEE-hc",
    "title": "The Most Misunderstood Concept in Physics",
    "score": 10
  },
  {
    "id": "DxL2HoqLbyA",
    "title": "Intro",
    "score": 10
  },
  {
    "id": "21XuHLJkEeg",
    "title": "What is the Schrödinger Equation? A basic introduction to Quantum Mechanics",
    "score": 10
  },
  {
    "id": "2WPA1L9uJqo",
    "title": "The Schrodinger Equation",
    "score": 10
  },
  {
    "id": "KdEZ-GOgZ3s",
    "title": "Search filters",
    "score": 10
  },
  {
    "id": "0lriA2ZoacE",
    "title": "Intro",
    "score": 10
  },
  {
    "id": "pVDqiYIxvdA",
    "title": "Instantly freeze water trick with HOT-ICE",
    "score": 10
  },
  {
    "id": "z-R3DShHbkA",
    "title": "Color changing walking water",
    "score": 10
  },
  {
    "id": "t8pcKyc3XbM",
    "title": "Superabsorbent polymer powder (SAP powder)",
    "score": 10
  },
  {
    "id": "NCjf6og4qHk",
    "title": "Corn flakes and magnet",
    "score": 10
  },
  {
    "id": "1Q_4HXewiS0",
    "title": "Intro",
    "score": 10
  },
  {
    "id": "NYQl9-5FpQM",
    "title": "Search filters",
    "score": 10
  },
  {
    "id": "Fsj8X712aOw",
    "title": "3 Hours Of Engineering Giants To Fall Asleep To",
    "score": 10
  },
  {
    "id": "AL9URlmQhVw",
    "title": "Boeing 747",
    "score": 10
  },
  {
    "id": "P7sOz55Ey1E",
    "title": "Eiffel Tower",
    "score": 10
  },
  {
    "id": "LmaPm5_pckU",
    "title": "Mega Dams \\u0026 Channels",
    "score": 10
  },
  {
    "id": "3yForRqB2fA",
    "title": "Bridges That Defined Modern Engineering | Mega Bridges | FD Engineering",
    "score": 10
  },
  {
    "id": "CF2YDfQgnVg",
    "title": "Massive Power Station Valve Replacement | Mega Maintenance | FD Engineering",
    "score": 10
  },
  {
    "id": "2k1wkMwtoPs",
    "title": "Steel Giants: Pushing the Limits of Bridge Design | Mega Bridges | FD Engineering",
    "score": 10
  },
  {
    "id": "HbCroBjFZEg",
    "title": "MSC Divina: Operating a Luxury City on the Ocean | FD Engineering",
    "score": 10
  },
  {
    "id": "0RVAGYCz4hY",
    "title": "Iron Bridges: Built to Last for Centuries | Mega Bridges | FD Engineering",
    "score": 10
  },
  {
    "id": "i8eIt0fVSVE",
    "title": "World’s Strongest Ship: The Titan That Redefines Heavy Lifting | FD Engineering",
    "score": 10
  },
  {
    "id": "zpse8p7cwRc",
    "title": "Bridges Before Steel: Pre-Industrial Marvels | Mega Bridges | FD Engineering",
    "score": 10
  },
  {
    "id": "43JWe87cetY",
    "title": "Aqueducts: Engineering the Water Systems of the Ancient World | FD Engineering",
    "score": 10
  },
  {
    "id": "1eoZ0AtHUjo",
    "title": "Massive Power Station Valve Replacement | Mega Maintenance | FD Engineering",
    "score": 10
  },
  {
    "id": "19AElybASFs",
    "title": "Three Gorges Dam",
    "score": 10
  },
  {
    "id": "EMAbsidMQnY",
    "title": "Tunnels",
    "score": 10
  },
  {
    "id": "i86Xia_PG44",
    "title": "North Sea Giant",
    "score": 10
  },
  {
    "id": "Unq1etYduBg",
    "title": "London's Super Sewer",
    "score": 10
  },
  {
    "id": "68PlPkeOwng",
    "title": "The Launchers",
    "score": 10
  },
  {
    "id": "bCm6tWIU89Q",
    "title": "Fast: World's Largest Radio Telescope",
    "score": 10
  },
  {
    "id": "PSV9ZjKtgIk",
    "title": "Fusion Power",
    "score": 10
  },
  {
    "id": "gxqPbGqYACw",
    "title": "The Rise and Fall of Julius Caesar",
    "score": 10
  },
  {
    "id": "utFGuXq3bkI",
    "title": "Impossible Engineering | Full Season 4 | Blueprint",
    "score": 10
  },
  {
    "id": "EdAM1pKy1Gg",
    "title": "Chernobyl's Toughest Fix",
    "score": 10
  },
  {
    "id": "pLtAwl7WSLM",
    "title": "Introduction",
    "score": 10
  },
  {
    "id": "6suaWHxaB6w",
    "title": "China’s Mega Machines Just Broke Every Rule of Physics — Experts Are Stunned",
    "score": 10
  },
  {
    "id": "KqLErMNg2uE",
    "title": "Welcome / What you’ll see in this factory mega-episode",
    "score": 10
  },
  {
    "id": "rBBAuJS1Ux0",
    "title": "Exploring Dworshak Dam: the biggest dam you've probably never heard of",
    "score": 10
  },
  {
    "id": "9sZne4R6q9s",
    "title": "WORLD MEGAPROJECTS | The Most Amazing Future Megastructures",
    "score": 10
  },
  {
    "id": "tEm_H280JLc",
    "title": "World’s Biggest Tent",
    "score": 10
  },
  {
    "id": "HVoifbegJ5E",
    "title": "Mega Bridges",
    "score": 10
  },
  {
    "id": "uTSpdD6MswA",
    "title": "Pasi Lautala Railway Engineer",
    "score": 10
  },
  {
    "id": "smg-vVPyw1s",
    "title": "The Craziest Treehouses of SEASON 5! | Treehouse Masters | Animal Planet",
    "score": 10
  },
  {
    "id": "00VeaL8a__k",
    "title": "How Is Worcestershire Sauce Made? | How Do They Do It?",
    "score": 10
  },
  {
    "id": "4WSiQAVzT1c",
    "title": "Intro",
    "score": 10
  },
  {
    "id": "6NtLzyfBO60",
    "title": "Introduction",
    "score": 10
  },
  {
    "id": "BI6bkwzPx5A",
    "title": "2 Hours Of Amazing Feats Of WW2 Engineering",
    "score": 10
  },
  {
    "id": "bntMGmeunS4",
    "title": "How World War One Caused World War Two | Price Of Empire",
    "score": 10
  },
  {
    "id": "oqY4QXwZ39s",
    "title": "The Palace of Versailles",
    "score": 10
  },
  {
    "id": "SjONVCcvOpA",
    "title": "Episode 1 - We Are At War",
    "score": 10
  },
  {
    "id": "vzTdGvYuNzo",
    "title": "Introduction",
    "score": 10
  },
  {
    "id": "YuScm1QMOjg",
    "title": "The invasion",
    "score": 10
  },
  {
    "id": "OO2QBAAMHAw",
    "title": "LUIS LISTENS TO RABIN \\u0026 ANGELA (Their heartfelt story of resilience and success) | Luis Manzano",
    "score": 10
  },
  {
    "id": "IqTd7LP_iJE",
    "title": "Toni is embarassed of what Alex did when Direk Paul visited their house | GGV",
    "score": 10
  },
  {
    "id": "wA_PBuOBiZI",
    "title": "Keyboard shortcuts",
    "score": 10
  },
  {
    "id": "eyhc6RFzhLI",
    "title": "Keyboard shortcuts",
    "score": 10
  },
  {
    "id": "_uQrJ0TkZlc",
    "title": "Introduction",
    "score": 10
  },
  {
    "id": "Onjs26YvfIQ",
    "title": "9 HOURS of Python Projects - From Beginner to Advanced",
    "score": 10
  },
  {
    "id": "yE9v9rt6ziw",
    "title": "What is Python?",
    "score": 10
  },
  {
    "id": "HGOBQPFzWKo",
    "title": "Intro",
    "score": 10
  },
  {
    "id": "3wkrYGmUqMk",
    "title": "Intro",
    "score": 10
  },
  {
    "id": "mDKM-JtUhhc",
    "title": "Intro",
    "score": 10
  },
  {
    "id": "8DvywoWv6fI",
    "title": "Computers want to be helpful...",
    "score": 10
  },
  {
    "id": "fH-_O9_SHqo",
    "title": "Intro",
    "score": 10
  },
  {
    "id": "rfscVS0vtbw",
    "title": "Introduction",
    "score": 10
  },
  {
    "id": "pKpZ7GOc5GY",
    "title": "Introduction to Python for Beginners",
    "score": 10
  },
  {
    "id": "wUSDVGivd-8",
    "title": "Welcome",
    "score": 10
  },
  {
    "id": "NA8Spo7Ixnw",
    "title": "25 Forgotten Survival Skills – The Ultimate Medieval Manual",
    "score": 10
  },
  {
    "id": "BE5_7YNrF3c",
    "title": "intro",
    "score": 10
  },
  {
    "id": "gvuMhD52Phg",
    "title": "Survival Skills: Kindling for Hiking and Wilderness Survival 🌳 #survival #camping #outdoors #forest",
    "score": 10
  },
  {
    "id": "HYx_KBoZ80I",
    "title": "15 Genius Medieval Survival Skills Modern Preppers Have Forgotten",
    "score": 10
  },
  {
    "id": "2xGrnfEsjoU",
    "title": "Intro",
    "score": 10
  },
  {
    "id": "xxVqXdCWL7c",
    "title": "50+ Survival and Bushcraft Tips!",
    "score": 10
  },
  {
    "id": "OClitn4zd_Q",
    "title": "Making Wooden Wedges",
    "score": 10
  },
  {
    "id": "KMO371fCkNM",
    "title": "75 days of using survival skills, trapping wild boars, wild chickens, wild fish, survival alone",
    "score": 10
  },
  {
    "id": "gopEqmFLXwM",
    "title": "Survival Skills: Amazing DIY heater for Extreme Conditions. #survival #camping #skills #lifehacks",
    "score": 10
  },
  {
    "id": "-bkiQCQ3W2Y",
    "title": "10 KILLER Survival Fails",
    "score": 10
  },
  {
    "id": "seLwyDN2wpQ",
    "title": "21 Genius Outdoor Survival Hacks You Wish You Knew Sooner! #camping #survival",
    "score": 10
  },
  {
    "id": "bS6WLN0FuRM",
    "title": "20+ Wilderness Survival Tips and Bushcraft Self Reliance Skills",
    "score": 10
  },
  {
    "id": "BFheNvvJGoQ",
    "title": "60+ Bushcraft Skills \\u0026 Survival Tips",
    "score": 10
  },
  {
    "id": "uAWp02IB-7U",
    "title": "Raising pigs use free range method, feeding them natural food - in 3 years he will be a billionaire",
    "score": 10
  },
  {
    "id": "iys_pmJSp9M",
    "title": "Search filters",
    "score": 10
  },
  {
    "id": "EUKZMqQtz2w",
    "title": "25 Essential Drawing Exercises: Unlock your Imagination",
    "score": 10
  },
  {
    "id": "BKiopm83L8c",
    "title": "Intro",
    "score": 10
  },
  {
    "id": "XAQ6K3DbEt4",
    "title": "Intro and Goals",
    "score": 10
  },
  {
    "id": "2nMeuaXo63E",
    "title": "20 FAST Tricks to Transform your Drawing Skills!",
    "score": 10
  },
  {
    "id": "Z6ZPq9Q4A0o",
    "title": "Introduction",
    "score": 10
  },
  {
    "id": "ao2IP7f23-8",
    "title": "drawing a curve right here in the middle of our paper",
    "score": 10
  },
  {
    "id": "XeIR7P82aPU",
    "title": "Intro",
    "score": 10
  },
  {
    "id": "2DVbargQCaY",
    "title": "Proportions",
    "score": 10
  },
  {
    "id": "j7CjkMtWJrw",
    "title": "Eye",
    "score": 10
  },
  {
    "id": "oeH2wOy_ris",
    "title": "Intro.",
    "score": 10
  },
  {
    "id": "PGNrnp-jLQg",
    "title": "The #1 Secret to Drawing",
    "score": 10
  },
  {
    "id": "zwKL5MScGXs",
    "title": "Search filters",
    "score": 10
  },
  {
    "id": "HqVJQxgVdU8",
    "title": "AI Just Made 15 Discoveries We Never Expected",
    "score": 10
  },
  {
    "id": "fuiJ-3CdU3Q",
    "title": "Introduction",
    "score": 10
  },
  {
    "id": "RM717Aj_VKQ",
    "title": "Why AI Will Never Stop Getting Smarter",
    "score": 10
  },
  {
    "id": "XyZ83EEjXxU",
    "title": "The AI Takeover Starts in 2026",
    "score": 10
  },
  {
    "id": "tMr5JSZP9cw",
    "title": "130 Ways AI Will Change Your Life",
    "score": 10
  },
  {
    "id": "gSBGNv9f8vU",
    "title": "AI In The Next 5 Years (2026 to 2030)",
    "score": 10
  },
  {
    "id": "o41gYSHXMKo",
    "title": "AI: The Next 10,000+ Years",
    "score": 10
  },
  {
    "id": "YqBl2h_1vWI",
    "title": "Type 7 Civilizations Are Terrifying",
    "score": 10
  },
  {
    "id": "8hJuF8EZmuM",
    "title": "The Kardashev Scale: Type 1 to Type 7 Civilizations",
    "score": 10
  },
  {
    "id": "L76f4cSjzS0",
    "title": "5 Years That Will Change AI Forever",
    "score": 10
  },
  {
    "id": "m-Wbn1htwdY",
    "title": "NEW INVENTIONS OF 2025 YOU SHOULD SEE",
    "score": 10
  },
  {
    "id": "T-F-vVNVQ50",
    "title": "Intro",
    "score": 10
  },
  {
    "id": "wrJsExM8D-o",
    "title": "Intro",
    "score": 10
  },
  {
    "id": "Oa9aWdcCC4o",
    "title": "Introduction",
    "score": 10
  },
  {
    "id": "wD6hyGXRcgk",
    "title": "Universal Translator",
    "score": 10
  },
  {
    "id": "PFVvCs9iQco",
    "title": "Intro",
    "score": 10
  },
  {
    "id": "SwkGVPh8jYs",
    "title": "20 Space Megastructures That Will Transform Our Future",
    "score": 10
  },
  {
    "id": "zfd1dn_h7wM",
    "title": "LUIS LISTENS TO MELAI CANTIVEROS (Babae pala ako. Ayokong mag-makaawa.) | Luis Manzano",
    "score": 10
  },
  {
    "id": "VwcyEbxRM8M",
    "title": "Totoo to, marami namatay sa gutom",
    "score": 10
  },
  {
    "id": "EPKDNGfsvD8",
    "title": "Transcript",
    "score": 10
  },
  {
    "id": "clUjSqf3md8",
    "title": "Keyboard shortcuts",
    "score": 10
  },
  {
    "id": "otYiGPcjTGI",
    "title": "Gandang Gabi Vice | Luis Manzano | Jeepney TV",
    "score": 10
  },
  {
    "id": "wrD-NlVdkq0",
    "title": "Maalaala Mo Kaya: Baul feat. Coney Reyes (Full Episode 243) | Jeepney TV",
    "score": 10
  },
  {
    "id": "w0tVImviX3Q",
    "title": "Filipino Jeepneys: The Craziest Public Transport",
    "score": 10
  },
  {
    "id": "Su2yBs8ur2o",
    "title": "Jeepney Gainz💪🏼🔥 #calisthenics #philippines #jeepney #gravity",
    "score": 10
  },
  {
    "id": "-x1isAo9gkE",
    "title": "The Ultimate Jeepney Chase! 🇵🇭 #Action #manila #jeepney",
    "score": 10
  },
  {
    "id": "P9GjEQYftCg",
    "title": "Jeepney Ride. Libertad to Marconi St. Feb. 5, 2026 #jeepney #pasay #makati",
    "score": 10
  },
  {
    "id": "0whlL5zLWu8",
    "title": "Gandang Gabi Vice | Luis Manzano, Toni Gonzaga | Jeepney TV",
    "score": 10
  },
  {
    "id": "P0m68YHWeo8",
    "title": "The last stop for Manila's jeepney artists",
    "score": 10
  },
  {
    "id": "hQXvhIwp194",
    "title": "Sweet JEEPNEY!❤️‍🔥🇵🇭 #Philippines #Jeep #Jeepney #Car #Truck #Vintage #Love #Classic #Rider #ASMR",
    "score": 10
  },
  {
    "id": "lzHYjDMQLC4",
    "title": "The Last Jeepney | 30 Years, One Route, One Last Trip (Full Film)",
    "score": 10
  },
  {
    "id": "x8eaVvUVwq8",
    "title": "PROUD PINOY JEEP #teampayamanin #viral",
    "score": 10
  },
  {
    "id": "Ao24rjda9jI",
    "title": "Si Lucky Manzano ba ang BET mo sa Top 10 Comedians of All Time?",
    "score": 10
  },
  {
    "id": "jrk6aAHubGg",
    "title": "mga modern jeepney na sirain hindi rin e renew ang prangkisa #viralvideo",
    "score": 10
  },
  {
    "id": "IQnH8sHKx0M",
    "title": "\\\"Guess Who\\\" with Bayani Agbayani and Long Mejia | Stars On Stars",
    "score": 10
  },
  {
    "id": "hy9gFS1s9bM",
    "title": "The Maricel Drama Special: Con Todo Mi Corazon feat. Edu Manzano [FULL EPISODE]",
    "score": 10
  },
  {
    "id": "l1Z2UCTKZHk",
    "title": "Jeepney karaoke is more fun being a foreigner in the Philippines",
    "score": 10
  },
  {
    "id": "3xUEq8vtM6c",
    "title": "Search filters",
    "score": 10
  },
  {
    "id": "ZUdOy252mmw",
    "title": "Keyboard shortcuts",
    "score": 10
  },
  {
    "id": "93nMBtXVAfM",
    "title": "We Need to Talk About Louis - Part 1",
    "score": 10
  },
  {
    "id": "OdbEeuml1gQ",
    "title": "Luis part",
    "score": 10
  },
  {
    "id": "KA93e8bd9ro",
    "title": "Portrait Art | Digital Art Process | Shading | Luis Part 2",
    "score": 10
  },
  {
    "id": "UCM0Vewvk3I",
    "title": "Paint With Me | Digital Art Portrait Process | Luis Part 3",
    "score": 10
  },
  {
    "id": "iKuXNm8xc_A",
    "title": "call of duty 4 louis vs luis part 2",
    "score": 10
  },
  {
    "id": "WaHmtNhCpKU",
    "title": "Louis CK: Sorry Not Sorry – He’s Back and Funnier Than Ever | Hilarious Stand-Up Comedy 2025",
    "score": 10
  },
  {
    "id": "g5Wn4arNe10",
    "title": "DELCY ENTREGA LAS FICHAS: CAEN GORRÍN Y SAAB, SE RESQUEBRAJA EL RÉGIMEN",
    "score": 10
  },
  {
    "id": "Zyp-1C3vd8c",
    "title": "Cómo opera la derecha. 4 de febrero de 2026 - Noroña",
    "score": 10
  },
  {
    "id": "okx7toLuICM",
    "title": "the Stranger Things finale sucked",
    "score": 10
  },
  {
    "id": "IRU8eihKf-Q",
    "title": "Mark 6:7-13 - Gospel of the day - Father Luis Zazano",
    "score": 10
  },
  {
    "id": "ix49lC6DLIs",
    "title": "Limericks with Louie | Ep 295 | Bad Friends",
    "score": 10
  },
  {
    "id": "Ot1iSfMxTGM",
    "title": "In the Wound",
    "score": 10
  },
  {
    "id": "uXuaI3amBm8",
    "title": "Trump Attacks CNN's Kaitlan Collins Over Epstein Q \\u0026 Renovates D.C. in His Image | The Daily Show",
    "score": 10
  },
  {
    "id": "BYHHJxzlUJE",
    "title": "Introduction",
    "score": 10
  },
  {
    "id": "yTVB_tg6J1E",
    "title": "This is how I experienced SHOT SHOW 2026 - Part 2",
    "score": 10
  },
  {
    "id": "QXl8hzosXro",
    "title": "Start Chapter 11",
    "score": 10
  },
  {
    "id": "03DUuoKzlrY",
    "title": "luis' part (my part) - water bowl sesh",
    "score": 10
  },
  {
    "id": "knfYx2U0zHY",
    "title": "Luis's part",
    "score": 10
  },
  {
    "id": "74JGWLoBaKc",
    "title": "GTA 4 TBOGT Voice Lines Luis Part 12",
    "score": 10
  },
  {
    "id": "Qh0Y0E4RS5w",
    "title": "Don Luis Parts One and Two",
    "score": 10
  },
  {
    "id": "gU9pQgjzQKk",
    "title": "PSYCHO Ex Girlfriend KIDNAPS YouTuber PART II",
    "score": 10
  },
  {
    "id": "KYe8izYfhtY",
    "title": "Search filters",
    "score": 10
  },
  {
    "id": "smGQm4mAfBM",
    "title": "LAADLIYAN | ਲਾਡਲੀਆਂ | EPISODE 21 | लाडलियां | لاڈلیاں | #mrmrsdevgan #punjabiwebseries #drama #mindo",
    "score": 10
  },
  {
    "id": "F_xlj5c9HYo",
    "title": "LAADLIYAN | ਲਾਡਲੀਆਂ | EPISODE 26 | लाडलियां | لاڈلیاں | #mrmrsdevgan #punjabiwebseries #drama #mindo",
    "score": 10
  },
  {
    "id": "8TxIEb55wmY",
    "title": "LAADLIYAN | ਲਾਡਲੀਆਂ | EPISODE 71 | लाडलियां | لاڈلیاں | #mrmrsdevgan #punjabiwebseries #drama #mindo",
    "score": 10
  },
  {
    "id": "J6moIjfLGN0",
    "title": "LAADLIYAN | ਲਾਡਲੀਆਂ | EPISODE 23 | लाडलियां | لاڈلیاں | #mrmrsdevgan #punjabiwebseries #drama #mindo",
    "score": 10
  },
  {
    "id": "qlkUNueAFpg",
    "title": "LAADLIYAN | ਲਾਡਲੀਆਂ | EPISODE 3 | लाडलियां | لاڈلیاں | #mrmrsdevgan #punjabiwebseries #drama #mindo",
    "score": 10
  },
  {
    "id": "nJSQ4buWTrg",
    "title": "LAADLIYAN | ਲਾਡਲੀਆਂ | EPISODE 23 | लाडलियां | لاڈلیاں | #mrmrsdevgan #punjabiwebseries #drama #mindo",
    "score": 10
  },
  {
    "id": "FiyoxZCglT8",
    "title": "LAADLIYAN | ਲਾਡਲੀਆਂ | EPISODE 30 | लाडलियां | لاڈلیاں | #mrmrsdevgan #punjabiwebseries #drama #mindo",
    "score": 10
  },
  {
    "id": "SwXZumgESjA",
    "title": "LAADLIYAN | ਲਾਡਲੀਆਂ | EPISODE 18 | लाडलियां | لاڈلیاں | #mrmrsdevgan #punjabiwebseries #drama #mindo",
    "score": 10
  },
  {
    "id": "xtRkPFoEwyk",
    "title": "LAADLIYAN | ਲਾਡਲੀਆਂ | EPISODE 27 | लाडलियां | لاڈلیاں | #mrmrsdevgan #punjabiwebseries #drama #mindo",
    "score": 10
  },
  {
    "id": "CxO5QMGeVeY",
    "title": "LAADLIYAN | ਲਾਡਲੀਆਂ | EPISODE 67 | लाडलियां | لاڈلیاں | #mrmrsdevgan #punjabiwebseries #drama #mindo",
    "score": 10
  },
  {
    "id": "N5FyhTMjUis",
    "title": "LAADLIYAN | ਲਾਡਲੀਆਂ | EPISODE 18 | लाडलियां | لاڈلیاں | #mrmrsdevgan #punjabiwebseries #drama #mindo",
    "score": 10
  },
  {
    "id": "FRsQYiBmmEY",
    "title": "ਸਾਂਝੇ ਟੱਬਰ ਦੇ ਪੁਆੜੇ | new punjabi movies2026|punjabi short videos@GHARPARIVARMANSA ",
    "score": 10
  },
  {
    "id": "caNGkXToBsY",
    "title": "Search filters",
    "score": 10
  },
  {
    "id": "-V-sywKOCwQ",
    "title": "Luis R Conriquez, Neton Vega - Si No Quieres No [Video Oficial]",
    "score": 10
  },
  {
    "id": "Tg3uqXpM6Zs",
    "title": "Me Metí En El Ruedo - Luis R Conriquez [En Vivo 2020]",
    "score": 10
  },
  {
    "id": "JDkPpdkIl7g",
    "title": "Luis R Conriquez, @NetonVega , @FUERZAREGIDA  - Chula Vente [Video Oficial]",
    "score": 10
  },
  {
    "id": "t8TBWnW90f8",
    "title": "Luis R Conriquez - Querido Ex Amor [En Vivo 2022]",
    "score": 10
  },
  {
    "id": "3TR00_yDtaU",
    "title": "Luis R Conriquez, @NetonVega , @FUERZAREGIDA  - Chula Vente [Video Oficial]",
    "score": 10
  },
  {
    "id": "E0KwLegXk8A",
    "title": "Cuando Te Acuerdes De Mi - Luis R Conriquez, Julian Mercado [En Vivo 2021]",
    "score": 10
  },
  {
    "id": "ygdtuSQKeyI",
    "title": "Lefty SM x Luis R Conriquez - Ahogándome En Alcohol",
    "score": 10
  },
  {
    "id": "8SzLgRtiGTo",
    "title": "Luis R Conriquez - Mexicano Soy [Video Oficial]",
    "score": 10
  },
  {
    "id": "pVVd1VZdE9Y",
    "title": "Luis R Conriquez, Neton Vega, Fuerza Regida - Chula Vente [Lyric Video]",
    "score": 10
  },
  {
    "id": "8Z5y92Tpe-A",
    "title": "Search filters",
    "score": 10
  },
  {
    "id": "XiQpUkLr5b4",
    "title": "¡ME QUITARON LA VISA!  - Tony Aguirre, El Chats \\u0026 Tito Torbellino Jr (Podcast)",
    "score": 10
  },
  {
    "id": "XR_u-DWaK-w",
    "title": "Neton Vega, Luis R Conriquez - El Plumas (Video Oficial)",
    "score": 10
  },
  {
    "id": "xGGv6VebNp0",
    "title": "MI PROPIO JEFE -  Luis R Conriquez, Edgardo Núñez, Raúl Beltrán (Video Musical)",
    "score": 10
  },
  {
    "id": "OiACtceKfbo",
    "title": "Luis R Conriquez, @AnuelAA - Relojito Cartier [Video Oficial]",
    "score": 10
  },
  {
    "id": "52Z4VVpGOa8",
    "title": "25. Luis R Conriquez, Panter Bélico - El Menos Visto [Visualizer]",
    "score": 10
  },
  {
    "id": "VrSfY3GDj3U",
    "title": "29. Luis R Conriquez, Panter Bélico - La 701 [Visualizer]",
    "score": 10
  },
  {
    "id": "xyLEu-cGmw0",
    "title": "Luis R Conriquez - Paz En Este Amor [En Vivo 2021]",
    "score": 10
  },
  {
    "id": "KzsfHAus9-E",
    "title": "Search filters",
    "score": 10
  },
  {
    "id": "L-1UAORcX4c",
    "title": "Sikhism Explained",
    "score": 10
  },
  {
    "id": "ENjJOF6pzxs",
    "title": "Confused Islamophobes Target American Sikhs: The Daily Show",
    "score": 10
  },
  {
    "id": "OyN0krWZxGs",
    "title": "Khalsa Raaj : EPISODE - 1 ( ORIGINS ) I New Punjabi Web Episode 2025",
    "score": 10
  },
  {
    "id": "925fZ4WKISo",
    "title": "Guru Nanak",
    "score": 10
  },
  {
    "id": "bFbYxgeqCGo",
    "title": "Bhai Joga Singh Ji \\u0026 Guru Gobind Singh Ji || Info Saakhi Series Episode 1 || Sikh Saakhiyan",
    "score": 10
  },
  {
    "id": "riaGzzvOYmI",
    "title": "Guru Ramdas Ji \\u0026 Bibi Bhani Ji | Info Saakhi Series Episode-9(Part-1) | Sikh Animation | Sikh Itihas",
    "score": 10
  },
  {
    "id": "xo1OLk8dpko",
    "title": "Start of the Podcast",
    "score": 10
  },
  {
    "id": "hvkFNEyH7xc",
    "title": "Search filters",
    "score": 10
  },
  {
    "id": "eEZyFgmIrZ8",
    "title": "ਚੰਨੋ ਵਣਜਾਰਨ | ਭਾਗ 2 | New punjabi short movie 2026 | Punjabi natak | @sanjhapariwarmansa ",
    "score": 10
  },
  {
    "id": "UJ8M4jHxe58",
    "title": "ਪਖੰਡਣ ਸੱਸ / New punjabi video 2025 / Punjabi short movies / Punjabi natak / @sanjhapariwarmansa",
    "score": 10
  },
  {
    "id": "I-sKK5eTpsk",
    "title": "ਮਾਂ ਦੀ ਕਰਤੂਤ || Ma Di Kartoot || New Punjabi short movie || Punjabi Natak ||@sanjhapariwarmansa",
    "score": 10
  },
  {
    "id": "HIjTjIqhHpU",
    "title": "ਸੱਸ ਮੇਰੀ ਨੰਬਰਦਾਰਨੀ || Punjabi short movie 2025 || Punjabi natak || Pendu virsa ||@sanjhapariwarmansa",
    "score": 10
  },
  {
    "id": "zUWWrgQDXp0",
    "title": "ਪ੍ਰੋਹਣੇ ਦੀ ਚਾਲ || New punjabi short movie || Pendu virsa || Punjabi natak ||@sanjhapariwarmansa",
    "score": 10
  },
  {
    "id": "mcHmNrAlQFc",
    "title": "ਗੁੱਸੇਖੋਰ ਸੱਸ | gussekhor sass | new punjabi short movie | punjabi natak 2025 | @sanjhapariwarmansa",
    "score": 10
  },
  {
    "id": "P2O9IgUDOYU",
    "title": "ਵਿਗੜੀ ਹੋਈ ਨਣਦ || Punjabi short movie 2025 || Pendu Virsa || Punjabi Natak ||@sanjhapariwarmansa",
    "score": 10
  },
  {
    "id": "_Q-JTiPxRxw",
    "title": "ਮਾਂ ਦੇ ਦੁੱਖ/New punjabi short movies/short punjabi movie 2025/punjabi natak/@sanjhapariwarmansa",
    "score": 10
  },
  {
    "id": "sNSdiiOf8Gk",
    "title": "ਰੌਲਾ ਮੈ ਦਾ / New punjabi short movie 2025 / Pendu virsa / Punjabi Natak /@sanjhapariwarmansa",
    "score": 10
  },
  {
    "id": "gES8JkPZlrg",
    "title": "ਘਰ ਦੇ ਜਿੰਦੇ || New punjabi short movies || Punjabi natak @sanjhapariwarmansa",
    "score": 10
  },
  {
    "id": "kEcLZozi8eU",
    "title": "ਮਾਂ ਦੀ ਅੜਵਾਈ || Punjabi short movie 2026 || Pendu virsa || Punjabi natak ||@sanjhapariwarmansa",
    "score": 10
  },
  {
    "id": "5IbZxhO6pv4",
    "title": "ਗੁੱਜਰਾ ਦਾ ਤਸ਼ੱਦਤ | New punjabi short movie 2026 | Punjabi natak |@sanjhapariwarmansa ",
    "score": 10
  },
  {
    "id": "mAMtf5aZl5w",
    "title": "ਕਮਲੀ ਸੱਸ || Kamli Sas || New punjabi short movie || Punjabi natak || Pendu virsa @sanjhapariwarmansa",
    "score": 10
  },
  {
    "id": "eguZS1V8ie4",
    "title": "@sanjhapariwarmansa #comedy #punjabicinema #funny #punjabifilm #sanjhapariwarmansa #punjabimovie",
    "score": 10
  },
  {
    "id": "Gre5KXAg9LE",
    "title": "New punjabi short movie 2026 | Punjabi natak | Sanjha pariwar mansa | Pendu virsa",
    "score": 10
  },
  {
    "id": "VxrvMcHNBZE",
    "title": "ਰੌਲਾ ਮੈ ਦਾ / Rola Mae Da / New punjabi short movie / Punjabi natak / Pendu Virsa/@sanjhapariwarmansa",
    "score": 10
  },
  {
    "id": "Vhv4qF4RhMo",
    "title": "Search filters",
    "score": 10
  },
  {
    "id": "kjyMbKsahzM",
    "title": "Friendzoned // Louis Lockwood (Original Song)",
    "score": 10
  },
  {
    "id": "vc68AidFdOk",
    "title": "friendzoned",
    "score": 10
  },
  {
    "id": "714_FMtQMJk",
    "title": "Clem Friendzone vs Kisses Louis Romance -All Choices- The Walking Dead The Final Season Episode 2",
    "score": 10
  },
  {
    "id": "n9f4Vj9vjeg",
    "title": "“FRIENDZONED”  | COMPLETE SEASON 1 With NEW Bonus Episode! |",
    "score": 10
  },
  {
    "id": "LhIB6pKsvFA",
    "title": "Friendzoned (feat. Mixie Moon) (Alaguan Remix)",
    "score": 10
  },
  {
    "id": "ui2aGmG15zI",
    "title": "All Dialogues With Friendzoned Louis - The Walking Dead Final Season 4 Episode 2 (Telltale Series)",
    "score": 10
  },
  {
    "id": "a2QrEcbJZmM",
    "title": "Friend Zone",
    "score": 10
  },
  {
    "id": "Kgf250lkMwY",
    "title": "The Walking Dead Season 4 Episode 3 - No Date - Friendzoned Louis",
    "score": 10
  },
  {
    "id": "M7-zOCRe7HI",
    "title": "No Tongue Louis FLIRTING With Clem -ROMANCE VS FRIENDZONE- The Walking Dead Final Season Ep4",
    "score": 10
  },
  {
    "id": "Xmc4kRRXSS4",
    "title": "Madara Dusal - FriendZone (Audio Official)",
    "score": 10
  },
  {
    "id": "TLc-Irr-XIY",
    "title": "When The Girl Who Friendzoned You, Finds Out You Moved On",
    "score": 10
  },
  {
    "id": "VVvVSAn_g2E",
    "title": "Friend Zone (English Version)",
    "score": 10
  },
  {
    "id": "dEzMib8cBsc",
    "title": "The Walking Dead Season 4 Episode 4 - Clem and Friendzoned Louis Dialogue + Don't Shoot Minnie",
    "score": 10
  },
  {
    "id": "_MOc78Spqlc",
    "title": "[Louis \\u0026 Clem] Differences between Friendzone \\u0026 Romance in Episode 3 | TWD Season 4",
    "score": 10
  },
  {
    "id": "ZPCXdSM4Tz8",
    "title": "Louis doesn't hold Clem's hand (Louis friendzoned)",
    "score": 10
  },
  {
    "id": "IGK2KprU-To",
    "title": "Search filters",
    "score": 10
  },
  {
    "id": "e4F7AZjnscE",
    "title": "MASSIVE UPSET | No. 6 Gonzaga vs. Portland | Pilots STUN The Zags 87-80 | FULL GAME HIGHLIGHTS",
    "score": 10
  },
  {
    "id": "p52ubvyt7gc",
    "title": "ALEX GONZAGA'S CONDO TOUR (PAGOD EDITION) | Luis Manzano",
    "score": 10
  },
  {
    "id": "Vu08x9XF-gQ",
    "title": "WIFEY vs BESTIE: WHO KNOWS ME BETTER? | Luis Manzano",
    "score": 10
  },
  {
    "id": "wn76ZJXQeEs",
    "title": "ZUMBABA MEETS SMALL LAUDE | Luis Manzano",
    "score": 10
  },
  {
    "id": "CIcNishaLLs",
    "title": "A DAY IN THE LIFE + KULITAN WITH ALEX GONZAGA | Luis Manzano",
    "score": 10
  },
  {
    "id": "6ruJ1a8HuMI",
    "title": "Daddy Lie Detector Test By Alex Gonzaga",
    "score": 10
  },
  {
    "id": "YemIY9fo8YI",
    "title": "Gonzaga’s Graham Ike post Portland ",
    "score": 10
  },
  {
    "id": "rLKCxv6jpD8",
    "title": "My Condo Warming with family by Alex Gonzaga",
    "score": 10
  },
  {
    "id": "KMe5wEUGZcs",
    "title": "EMBARRASSING: Gonzaga suffers SHOCKING loss to Portland, Mark Few OUTCOACHED! | March implications??",
    "score": 10
  },
  {
    "id": "tVrpfkSUMkI",
    "title": "Best Bohemian Rhapsody Cover by Alex Gonzaga",
    "score": 10
  },
  {
    "id": "YN3kLCxLSW4",
    "title": "Palawan Wedding by Alex Gonzaga",
    "score": 10
  },
  {
    "id": "uJiRYR70QkM",
    "title": "LUIS LISTENS TO PAPA JACKSON (It's always a privilege to listen to people's stories) | Luis Manzano",
    "score": 10
  },
  {
    "id": "pIBiC_lSmZU",
    "title": "Search filters",
    "score": 10
  },
  {
    "id": "_UAPw6WaOPQ",
    "title": "Angeline and Yeng’s powerful duet | ASAP Natin To",
    "score": 10
  },
  {
    "id": "Kx1u2HqNw6c",
    "title": "Angeline Quinto, Yeng Constantino, KZ Tandingan, Kyla Songs 💝 OPM Tagalog Love Songs playlist 2020",
    "score": 10
  },
  {
    "id": "QQaoqijF1zw",
    "title": "Yeng Constantino BINURAOT ang MAMAHALING SAPATOS ni Angeline Quinto",
    "score": 10
  },
  {
    "id": "zK_kt5f9q_w",
    "title": "Yeng Constantino, Angeline Quinto, Moira Dela Torre, Morissette🙌Bagong OPM Wish 107.5 Playlist 2024💝",
    "score": 10
  },
  {
    "id": "JtV2-zs9EIY",
    "title": "The Best of Yeng Constantino, KZ Tandingan, Juris, \\u0026 Jona | Non-Stop",
    "score": 10
  },
  {
    "id": "V2Bo_1fQBzA",
    "title": "KZ, Kyla, Yeng \\u0026 Angeline sing their favorite songs | GGV",
    "score": 10
  },
  {
    "id": "TBgrP4-wKsc",
    "title": "Klarisse, Angeline, Yeng's rendition of \\\"Ako Na Lang Muna\\\" | ASAP",
    "score": 10
  },
  {
    "id": "mKjyQzWZkl8",
    "title": "WATCH: Angeline and Yeng's jamming with Imago | ASAP",
    "score": 10
  },
  {
    "id": "i7QyTYkV5F4",
    "title": "YENG CONSTANTINO, KZ TANDINGAN, KYLA , ANGELINE QUINTO hiTS PlayLISt 2019  \\\\ TAGALOG love SOnGs HITS",
    "score": 10
  },
  {
    "id": "L4he3xBfBuA",
    "title": "Napahiya si Angeline Quinto sa eroplano?! May tampo nga ba kay Yeng Constantino? | Chad Kinis Show",
    "score": 10
  },
  {
    "id": "Zn1vRW9i33c",
    "title": "UNTV: C-NEWS | February 5, 2026",
    "score": 10
  },
  {
    "id": "vqdmOV0UgEg",
    "title": "HONG KONG DISNEYLAND FOR SYLVIO'S BIRTHDAY! | Love Angeline Quinto",
    "score": 10
  },
  {
    "id": "HpHQqz3J48c",
    "title": "CELEBRATING AZENA SYLVIA! | Love Angeline Quinto",
    "score": 10
  },
  {
    "id": "Acq6gksmQVg",
    "title": "Eugene Domingo: Fun chikahan with Angeline Quinto",
    "score": 10
  },
  {
    "id": "vAd_3h-SM-8",
    "title": "Sa Ganang Mamamayan - February 5, 2026",
    "score": 10
  },
  {
    "id": "FqgMZSR24wQ",
    "title": "Hear It Like Never Before: Yeng, Angeline, Erik sing each other's hits | ASAP",
    "score": 10
  },
  {
    "id": "KeIHLpX3QaY",
    "title": "Angeline, KZ, Yeng, \\u0026 Kyla sing each other's hit songs | GGV",
    "score": 10
  },
  {
    "id": "b-WemNXjT1c",
    "title": "Vice cries over Angeline's \\\"joke\\\" | GGV",
    "score": 10
  },
  {
    "id": "QJi3-iGWz6k",
    "title": "[ARTIST LAB] ON BENDED KNEES - KYLA, KZ, YENG \\u0026 ANGELINE",
    "score": 10
  },
  {
    "id": "CPaPU8Ql21A",
    "title": "OPM Tagalog Love Songs playlist 2020   Angeline Quinto, Yeng Constantino, KZ Tandingan, Kyla Song",
    "score": 10
  },
  {
    "id": "hW1HY1OsQ3g",
    "title": "Lipad Ng Pangarap - Angeline, Jona, Klarisse, and Yeng | iWant ASAP Highlights",
    "score": 10
  },
  {
    "id": "dk2G4gWlrr0",
    "title": "Search filters",
    "score": 10
  },
  {
    "id": "BJnMTb4CHts",
    "title": "Billy and Vhong's past arguments | Magandang Buhay",
    "score": 10
  },
  {
    "id": "VoasaC6wLO4",
    "title": "Pip discovers Ferdie's letter for Julie | HSH Extra Sweet",
    "score": 10
  },
  {
    "id": "o91f9LKi6h4",
    "title": "Barako Boys find a way to earn money | HSH Extra Sweet",
    "score": 10
  },
  {
    "id": "icne3xqSqvs",
    "title": "Vhong remembers the humble beginnings of It's Showtime | It's Showtime Sampu-Sample",
    "score": 10
  },
  {
    "id": "EKDqjfZrUYA",
    "title": "Kanto Boys reunite on ASAP 20th Anniversary",
    "score": 10
  },
  {
    "id": "FNUv17NB4C8",
    "title": "SARAP TIRIK ANG AKING MATA",
    "score": 10
  },
  {
    "id": "Yq4PX0D5pis",
    "title": "Minute To Win It: Vhong Navarro, wish na magkasama sila ni Luis sa isang pelikula",
    "score": 10
  },
  {
    "id": "EX16A3hjV10",
    "title": "Luis, kinuha ang number ni Toni kay Vhong noon | GGV",
    "score": 10
  },
  {
    "id": "uOBZY0q-yYU",
    "title": "It's Showtime: Lucas Andalio at Vhong, nag-sample ng award-winning na pag-arte! (Laro, Laro, Pick)",
    "score": 10
  },
  {
    "id": "zgYjBJpjp3A",
    "title": "“Nilalangaw eh!” Vice Ganda, pinayuhan si Lassy  na ‘wag magsuot ng brown | It’s Showtime",
    "score": 10
  },
  {
    "id": "SzBjcO-dnZs",
    "title": "Ungkatan ng past: Ganti ni Vice Ganda sa pang-aasar nina Vhong at Jhong | ABS-CBN News",
    "score": 10
  },
  {
    "id": "_hEFYcutrOY",
    "title": "ANAK ni Jhong Hilario di Nahiya sa Stage GINAYA ang AMA nasi Jhong sa Pag-SAMPLE sa Harap ng MADLA!",
    "score": 10
  },
  {
    "id": "mgg9qOcsYI4",
    "title": "Gandang Gabi Vice | Bayani Agbayani, Vhong Navarro",
    "score": 10
  },
  {
    "id": "omR7D9qjOwg",
    "title": "EAT BULAGA | Paolo, nagulat kay Whetney Love!",
    "score": 10
  },
  {
    "id": "3dwZdcayoug",
    "title": "Vhong and Jhong put Vice Ganda in the hot seat | Tawag ng Tanghalan",
    "score": 10
  },
  {
    "id": "GVN2IkTFWP4",
    "title": "Director Bobet enters the studio because of Vice, Jhong and Vhong | It's Showtime Mr. Q and A",
    "score": 10
  },
  {
    "id": "qEcJ1v-Mtho",
    "title": "Vhong at Billy, nagsama para sa birthday ni Luis | I Can See Your Voice",
    "score": 10
  },
  {
    "id": "Qd09IZlkOmg",
    "title": "Billy, Vhong and Luis look back on their Kanto Boys days | Magandang Buhay",
    "score": 10
  },
  {
    "id": "_4bvTZ2dDB4",
    "title": "Billy has a birthday message for his friend Vhong | It’s Showtime",
    "score": 10
  },
  {
    "id": "VtPlZ7e1uUU",
    "title": "Ferdie helps with Julie's school work | HSH Extra Sweet",
    "score": 10
  },
  {
    "id": "ophvx72rjbk",
    "title": "Between LUIS at VHONG, mas muntik daw maging dyowa ni TONI si VHONG",
    "score": 10
  },
  {
    "id": "Qa6r2WrMnHM",
    "title": "Vhong Navarro Jhong Hilario Billy Crawford in MiniMe showdown HD",
    "score": 10
  },
  {
    "id": "AVT6zkn7Q44",
    "title": "Ferdie and Edwin find a new car mechanic | HSH Extra Sweet",
    "score": 10
  },
  {
    "id": "RLq9OTS_sio",
    "title": "Sarah's BACKSTREET BOYS Medley with Luis, Billy, and Vhong",
    "score": 10
  },
  {
    "id": "Qopjq9GnRys",
    "title": "Luis, Vhong, and Billy's Unli25 Bloopers",
    "score": 10
  },
  {
    "id": "k5ljnXp4r8c",
    "title": "Search filters",
    "score": 10
  },
  {
    "id": "KFptQTSs2f4",
    "title": "Dheeyan: Rajvir Jawanda | Harashjot Kaur | G Guri | Stalinveer | Singhjeet | New Punjabi Song 2023",
    "score": 10
  },
  {
    "id": "I13QisWfLKQ",
    "title": "ਧੀਆਂ ਦੇ ਦੁਸ਼ਮਣ -2 / Dheeyan De Dushman -2  | New Web Series 2026",
    "score": 10
  },
  {
    "id": "bLxtqSe9sT8",
    "title": "ਧੀਆਂ ਦੇ ਦੁਸ਼ਮਣ -1 / Dheeyan De Dushman -1  | New Web Series 2026",
    "score": 10
  },
  {
    "id": "ry13nkSWcJo",
    "title": "Menka ने ढाबे ते पहोचने तों रोकेया tempo नु | Dheeyan Meriyan | Full Episode 1 | Zee Punjabi",
    "score": 10
  },
  {
    "id": "ccZA0ksW6dk",
    "title": "ਧੀਆਂ ਦੇ ਦਲਾਲ LAST EPISODE  / DHEEYAN DE DALAAL / NEW PUNJABI WEB SERIES @Sheronwale",
    "score": 10
  },
  {
    "id": "f5KSrzGnHwE",
    "title": "LAADLIYAN | ਲਾਡਲੀਆਂ | EPISODE 71 | लाडलियां | لاڈلیاں | #mrmrsdevgan #punjabiwebseries #drama #mindo",
    "score": 10
  },
  {
    "id": "M8WoaftSazY",
    "title": "Who destroyed Asha's Dhaba? | Dheeyan Meriyan | Full Episode 6 | Zee Punjabi",
    "score": 10
  },
  {
    "id": "5ph7Q5TjD4w",
    "title": "Dheeyan Meriyan | 21 - 25 November, 2022 - Punjabi TV Show - Highlights - Zee Punjabi",
    "score": 10
  },
  {
    "id": "mTxTMDFq4no",
    "title": "Dheeyan Meriyan | 25 - 29 July, 2022 - Punjabi TV Show - Highlights - Zee Punjabi",
    "score": 10
  },
  {
    "id": "wMc3HRne6sA",
    "title": "ਲਾਵਾਂ ਫ਼ੇਰੇ - 8 | Lavaan Fere - 8 | Punjabi Web Series  | Tajinder Sandeep  | Being Sikh",
    "score": 10
  },
  {
    "id": "RRChCq4ZjrY",
    "title": "Sargun wants degree Milan Da Jashan | Dheeyan Meriyan | Full Episode 3 | Zee Punjabi",
    "score": 10
  },
  {
    "id": "_HXGGgXyqDo",
    "title": "LAADLIYAN | ਲਾਡਲੀਆਂ | EPISODE 70 | लाडलियां | لاڈلیاں | #mrmrsdevgan #punjabiwebseries #drama #mindo",
    "score": 10
  },
  {
    "id": "XbmGAQ9oaC4",
    "title": "Search filters",
    "score": 10
  },
  {
    "id": "Wl23DnOaW88",
    "title": "Mafaad Parast Episode 62 - [Eng Sub] - Nazish Jahangir Khan - Osama Tahir - 3rd February 2026",
    "score": 10
  },
  {
    "id": "g7AxF4iiaVs",
    "title": "Mafaad Parast Episode 61 - [Eng Sub] - Nazish Jahangir Khan - Osama Tahir - 2nd February 2026",
    "score": 10
  },
  {
    "id": "TPKCe-pcYjE",
    "title": "Mafaad Parast 2nd Last Episode 64Teaser  | Mafaad Parast Ep 64 Promo | Mafaad Parast Episode  63",
    "score": 10
  },
  {
    "id": "O0SpoKGPi6g",
    "title": "Recap Mafaad Parast Episode 62 - 4th February 2026 - HAR PAL GEO",
    "score": 10
  },
  {
    "id": "T_EgGADGhCg",
    "title": "Mafaad Parast Episode 62 Teaser - 2nd February 2026 - HAR PAL GEO",
    "score": 10
  },
  {
    "id": "4c5lFzrxoxg",
    "title": "Mafaad Parast Episode 60 - [Eng Sub] - Nazish Jahangir Khan - Osama Tahir - 1st February 2026",
    "score": 10
  },
  {
    "id": "VOm68OnlULg",
    "title": "Mafaad Parast Episode 63 Teaser - 3rd February 2026 - HAR PAL GEO",
    "score": 10
  },
  {
    "id": "qGZkGhlRSmg",
    "title": "Mafaad Parast Episode 63 Teaser  | Mafaad Parast Ep 63 Promo | Mafaad Parast Episode  62",
    "score": 10
  },
  {
    "id": "KxFbC2LUAxw",
    "title": "Mafaad Parast Episode 61 Teaser  | Mafaad Parast Ep 61 Promo | Mafaad Parast Episode  60",
    "score": 10
  },
  {
    "id": "0lT23PDUN5Y",
    "title": "Mafaad Parast Episode 61 Teaser - 1st February 2026 - HAR PAL GEO",
    "score": 10
  },
  {
    "id": "UWphd9jCz3I",
    "title": "Mafaad Parast Episode 62 Teaser  | Mafaad Parast Ep 62 Promo | Mafaad Parast Episode  61",
    "score": 10
  },
  {
    "id": "H2g-EKrGMyE",
    "title": "Recap Mafaad Parast Episode 60 - 2nd February 2026 - HAR PAL GEO",
    "score": 10
  },
  {
    "id": "i6ndPqUFWFM",
    "title": "Recap Mafaad Parast Episode 61 - 3rd February 2026 - HAR PAL GEO",
    "score": 10
  },
  {
    "id": "DxBO76zVmGU",
    "title": "Recap Mafaad Parast Episode 59 - 1st February 2026 - HAR PAL GEO",
    "score": 10
  },
  {
    "id": "Cl_yGkt3WiY",
    "title": "Mafaad Parast Episode 63 Teaser - HAR PAL GEO",
    "score": 10
  },
  {
    "id": "1ZCvQArgYlk",
    "title": "\\\"Mafaad Parast Episode 63 Teaser | 4rd February 2026 | Drama Latest Scene\\\"",
    "score": 10
  },
  {
    "id": "uSt_uQFkY_I",
    "title": "Search filters",
    "score": 10
  },
  {
    "id": "knWakWutHWw",
    "title": "Moh",
    "score": 10
  },
  {
    "id": "WBxbee-yxQo",
    "title": "Jatts In Golmaal",
    "score": 10
  },
  {
    "id": "uBDZZ--86lU",
    "title": "Shareek",
    "score": 10
  },
  {
    "id": "905EOUu4mGc",
    "title": "25 Kille",
    "score": 10
  },
  {
    "id": "-rCyo4i98zM",
    "title": "Sat Shri Akaal England",
    "score": 10
  },
  {
    "id": "sVe1F-HV_RQ",
    "title": "Rangeelay",
    "score": 10
  },
  {
    "id": "pnFh0_k2QYc",
    "title": "Motor Mitraan Di",
    "score": 10
  },
  {
    "id": "jAwgpDemm_I",
    "title": "Haani",
    "score": 10
  },
  {
    "id": "tXyUd_YMssg",
    "title": "Double Di Trouble",
    "score": 10
  },
  {
    "id": "1qrAUbNV-DQ",
    "title": "Mukhtiar Chadha",
    "score": 10
  },
  {
    "id": "pelmHNOA3nc",
    "title": "Son of Manjeet Singh",
    "score": 10
  },
  {
    "id": "XCv-uzUBbx4",
    "title": "Faraar",
    "score": 10
  },
  {
    "id": "p_yXae3j4HA",
    "title": "Parahuna",
    "score": 10
  },
  {
    "id": "BXmlIIKqiCs",
    "title": "Soorma",
    "score": 10
  },
  {
    "id": "FP8dmBOUHVU",
    "title": "Tanu Weds Manu",
    "score": 10
  },
  {
    "id": "QVKMJLmNnkc",
    "title": "Naughty Jatts",
    "score": 10
  },
  {
    "id": "oh36_UTIYfY",
    "title": "Khido Khundi",
    "score": 10
  },
  {
    "id": "tAMEJ_Ujtug",
    "title": "Loins of Punjab Presents",
    "score": 10
  },
  {
    "id": "z54sXLuRYSc",
    "title": "Needhi Singh",
    "score": 10
  },
  {
    "id": "cEJun8AJ8yg",
    "title": "Qissa Panjab",
    "score": 10
  },
  {
    "id": "LFrjBHdd-Bo",
    "title": "Bathinda Express",
    "score": 10
  },
  {
    "id": "Ob3gyd8ib_o",
    "title": "Judge Singh LLB",
    "score": 10
  },
  {
    "id": "uDD941PR_08",
    "title": "Dil Vil Pyaar Vyaar",
    "score": 10
  },
  {
    "id": "xT6xkOkk9Gw",
    "title": "Hashar A Love Story",
    "score": 10
  },
  {
    "id": "U81zH7SQpeA",
    "title": "Gadaar: The Traitor",
    "score": 10
  },
  {
    "id": "lUrMbJjwvrI",
    "title": "Bhagat Dhanna Jatt",
    "score": 10
  },
  {
    "id": "CMnz6zotbNw",
    "title": "What The Jatt",
    "score": 10
  },
  {
    "id": "G4Q--fkVdHA",
    "title": "Dharti",
    "score": 10
  },
  {
    "id": "BWSq-sosLGM",
    "title": "Pooja… Kiven Aa..???",
    "score": 10
  },
  {
    "id": "yK-H96FNhOU",
    "title": "Mundeyan Ton Bachke Rahin",
    "score": 10
  },
  {
    "id": "67KLP5f7FPY",
    "title": "Saadey CM Saab",
    "score": 10
  },
  {
    "id": "KXxgqm1_trE",
    "title": "Dushman",
    "score": 10
  },
  {
    "id": "XQuRSKNlYtE",
    "title": "Chidiya A Love Story l | Ammy Virk | Neeru Bajwa | Tania | Latest Punjabi Movie 2025 | New",
    "score": 10
  },
  {
    "id": "A_W2z1c7gmg",
    "title": "CHAL MERA PUTT 4 | NEW PUNJABI MOVIE 2025 | FULL MOVIE IN HD ",
    "score": 10
  },
  {
    "id": "azeUJhH3y0s",
    "title": "FURLOW (Full Movie) Gurpreet Ghuggi | Love Gill | Honey Mattu | Latest Punjabi Comedy Movie 2026",
    "score": 10
  },
  {
    "id": "0UjdhV3LKWc",
    "title": "Carry On Jatta (Full Movie) | Gippy Grewal | Binnu Dhillon | Gurpreet Ghuggi | Punjabi Movie 2025",
    "score": 10
  },
  {
    "id": "A7uwqEXipU8",
    "title": "New punjabi /ਚੌਕੀਦਾਰ ਹੀ ਚੋਰ ਹੈ । Punjabi full move/hd movie/mkv./comdy move ",
    "score": 10
  },
  {
    "id": "nrnNLlBq5dg",
    "title": "Hit Punjabi Movie | New Punjabi Movie 2025 | Full Punjabi Movie | Latest Punjabi Movie 2025",
    "score": 10
  },
  {
    "id": "rhRZLdvtNTw",
    "title": "Babe Bhangra Paunde Ne (2022) | Full Punjabi Movie | Ammy Virk, Sonam Bajwa | Comedy Drama Movie",
    "score": 10
  },
  {
    "id": "aez9STaJh6Y",
    "title": "Ghar Vapsi | Punjabi Movie 2026 Ammy Virk | Sonam Bajwa | New Punjabi Movies 2026",
    "score": 10
  },
  {
    "id": "SnZA-pO3JRI",
    "title": "ਮਾਲਦਾਰ ਛੜਾ 222 MALDAR SHADA baghu shada latest SHORT MOVIE 2026 PUNJABI FILM JATT BEAT RECORD",
    "score": 10
  },
  {
    "id": "Q-Ep-fCeZI0",
    "title": "Kuriyan Jawan Bapu Preshaan 2 (Full Movie) Karamjit Anmol | Full Comedy | Latest Punjabi Movie 2025",
    "score": 10
  },
  {
    "id": "If9sqwj8iCg",
    "title": "\\\"New Punjabi Movie 2026 Full HD | \\\"Superhit Punjabi Movie | Family Comedy Movie 2026",
    "score": 10
  },
  {
    "id": "8W_-Rxb4H4I",
    "title": "New Punjabi Full Movies 2026 | MANGANI - FULL MOVIE | Latest Punjabi Movies 2025",
    "score": 10
  },
  {
    "id": "GR7zJcW4NvE",
    "title": "Madhaniyan (Full Movie) Starring Dev Kharoud, Neeru Bajwa, Nav Bajwa, Gurpreet Ghuggi",
    "score": 10
  },
  {
    "id": "N5-w48i99yk",
    "title": "Godday Godday Chaa Full Movie HD | Sonam Bajwa, Tania | New Punjabi Movie | Punjabi Comedy Film",
    "score": 10
  },
  {
    "id": "OgrMM4SKmKk",
    "title": "Sarbala Ji Full Punjabi Movie 2025 | Gippy Grewal | Ammy Virk | Sargun Mehta | Punjabi Movies 2025",
    "score": 10
  },
  {
    "id": "cqi63X0ndeU",
    "title": "Jaatni | Kudi Haryane Val Di | Ammy Virk \\u0026 Sonam Bajwa | New Movie Punjabi Movies 2026",
    "score": 10
  },
  {
    "id": "JM0RSbLczKs",
    "title": "Viah 70 KM (Full Movie) | Harish Verma | Jaswinder Bhalla | Geeta Zaildar | Punjabi Movies 2026",
    "score": 10
  },
  {
    "id": "v48UIbLZIL8",
    "title": "Gippy Grewal - New Full Punjabi Movie 2026 | Latest Punjabi Movie | Super Hit Punjabi Movie",
    "score": 10
  },
  {
    "id": "tzrAnGFnRII",
    "title": "Search filters",
    "score": 10
  },
  {
    "id": "X897ml02vM0",
    "title": "Luis R Conriquez, Joel De La P, El Alfa, Chimbala  - Meneo [Video Oficial]",
    "score": 10
  },
  {
    "id": "MwUFWknkYgE",
    "title": "Luis R Conriquez, Neton Vega, Fuerza Regida - Chula Vente [Visualizer]",
    "score": 10
  },
  {
    "id": "P1kWdoo2y58",
    "title": "Me Metí En El Ruedo - Luis R Conriquez [En Vivo 2020]",
    "score": 10
  },
  {
    "id": "lBKMQG_t1GI",
    "title": "Luis R Conriquez, Joel De La P, Chimbala - Que Se Cuide [Video Oficial]",
    "score": 10
  },
  {
    "id": "CMAD1xtrmg0",
    "title": "Luis R Conriquez - El Buho (En Vivo 2019)",
    "score": 10
  },
  {
    "id": "0yKJeBW16rw",
    "title": "Esau Ortíz, Luis R Conriquez, Oscar Maydon, Alemán feat. Victor Mendivil - Triple Lavada (Remix)",
    "score": 10
  },
  {
    "id": "nt1Q4vJBCWc",
    "title": "MI PROPIO JEFE -  Luis R Conriquez, Edgardo Núñez, Raúl Beltrán (Video Musical)",
    "score": 10
  },
  {
    "id": "wJm8dZvnT0U",
    "title": "Fuerza Regida X Luis R Conriquez - CHOLO 7 (VIDEO OFICIAL)",
    "score": 10
  },
  {
    "id": "6CvT_1tOrlY",
    "title": "Me Meti En El Ruedo - Luis R Conriquez [Video Oficial]",
    "score": 10
  },
  {
    "id": "Q-5INx6yPPo",
    "title": "Luis R Conriquez - Martes 13 [Video Oficial]",
    "score": 10
  },
  {
    "id": "ysQ5wYleCRE",
    "title": "FUERZA REGIDA - MARLBORO ROJO (VIDEO OFICIAL)",
    "score": 10
  },
  {
    "id": "ddkbVYutRXA",
    "title": "Frecuencia - Dareyes de la Sierra (Video Oficial)",
    "score": 10
  },
  {
    "id": "ebXEaHEYYng",
    "title": "Lefty SM x Luis R Conriquez - Ahogándome En Alcohol",
    "score": 10
  },
  {
    "id": "HTf0x9Jq8E8",
    "title": "Luis R Conriquez, Neton Vega, Fuerza Regida - Chula Vente [Lyric Video]",
    "score": 10
  },
  {
    "id": "c3yEjD_oijw",
    "title": "Tame Impala - Nangs (Audio)",
    "score": 10
  },
  {
    "id": "tOJ3nmte_NM",
    "title": "Aira Bermudez, pataas nang pataas ang bahay noon sa Tondo dahil sa kinikita sa SexBomb | i-Listen",
    "score": 10
  },
  {
    "id": "8tW-E21Y0aQ",
    "title": "Dating PDL na 20 beses nakulong, isa nang pastor ngayon! (Full Episode) | i-Listen",
    "score": 10
  },
  {
    "id": "fjFduB3erBA",
    "title": "Listen, Listen",
    "score": 10
  },
  {
    "id": "rDDcnJVlH_o",
    "title": "Listen",
    "score": 10
  },
  {
    "id": "TBgX4rQUeT0",
    "title": "i yap u listen",
    "score": 10
  },
  {
    "id": "-hcCesPJ8UY",
    "title": "I Left USA for Vietnam! Tour My $500 House in Da Nang",
    "score": 10
  },
  {
    "id": "BETDEZanhUI",
    "title": "Try Listening For 2 Minutes - Explore The Depths Of Your Mind - Relaxing Music",
    "score": 10
  },
  {
    "id": "AclJEg7psPw",
    "title": "Nang Liger feat Panhatry \\u0026 Yorn Ha (LISTEN FOR ME - ស្តាប់ខ្ញុំ) [OFFiCIAL AUDIO]",
    "score": 10
  },
  {
    "id": "iP-5ISlZZks",
    "title": "Mackin Hangin Video - Na'Listen Ft. JiT",
    "score": 10
  },
  {
    "id": "AqH6tzoRDlw",
    "title": "Nang iwan #listen #subscribe #music #chillmusic",
    "score": 10
  },
  {
    "id": "BYg87aZWZ6g",
    "title": "PANHA- LISTEN FOR ME Ft NANG LIGER x YORN HA (OFFICIAL AUDIO)",
    "score": 10
  },
  {
    "id": "XmCw-hsyHHs",
    "title": "(Reading Practice (Improve your pronunciation in English",
    "score": 10
  },
  {
    "id": "EL6gw96u1-U",
    "title": "Snow begins to fall in November",
    "score": 10
  },
  {
    "id": "Kc2B25xX9eQ",
    "title": "Tình Yêu Trên Cầu Rồng | Da Nang Vietnam Song you must listen to!",
    "score": 10
  },
  {
    "id": "O4_WN5z0Rfc",
    "title": "Listen - Cover by Edel Q of Tawag nang tanghalan",
    "score": 10
  },
  {
    "id": "8N-V01N_g_8",
    "title": "Brown Cat English Reading Practice #english  #englishpractice",
    "score": 10
  },
  {
    "id": "tjYd7T2xrp4",
    "title": "Las Vegas Casino Heist: Armed Robbers on the Run",
    "score": 10
  },
  {
    "id": "yD5SBu-LtbQ",
    "title": "Dangerous Gamble",
    "score": 10
  },
  {
    "id": "asuZzvWbX1o",
    "title": "Search filters",
    "score": 10
  },
  {
    "id": "2Q9fufhFI4E",
    "title": "BABAL DA VEHRA ALL EPISODE FULL STORY | MR MRS DEVGAN | DEV MINDO  | NEW PUNJABI WEB SERIES 2024",
    "score": 10
  },
  {
    "id": "WHCNxbS4x7g",
    "title": "Vehra | ਵੇਹੜਾ  | Heart Touching Punjabi Short Film | Xpose Prime Originals",
    "score": 10
  },
  {
    "id": "nzxPYysBhfY",
    "title": "ਵਿਆਹ ਤੋਂ ਬਾਅਦ ਪਹਿਲੀ ਗਲਤੀ 😮 l VEHRA SHAGNA DA PUNJABI FILM 2024 l FULL PUNJABI MOVIE l  GANDHUAN GTV",
    "score": 10
  },
  {
    "id": "eTfIHS8L8zw",
    "title": "Sanjha Vehda Punjabi New Movie ! Lovepreet Ghuman ! Harmeet Jassi ! Jaggie Tv ! Mangu Films !",
    "score": 10
  },
  {
    "id": "J1ErG8k5rjk",
    "title": "Vehra | ਵੇਹੜਾ  | Punjabi Short Film | Teaser | Xpose Prime | Tauqeer Paul | Malaika Riaz",
    "score": 10
  },
  {
    "id": "AjehuY9kwUs",
    "title": "BABAL DA VEHRA EP1 | MR MRS DEVGAN | HARMINDER MINDO | NEW PUNJABI WEB SERIES | #punjabiwebseries",
    "score": 10
  },
  {
    "id": "HB7ud2ALKG8",
    "title": "Vehra | ਵੇਹੜਾ  | Best Scene | Heart Touching Punjabi Short Film | Xpose Prime Originals",
    "score": 10
  },
  {
    "id": "ReShzsP2Y54",
    "title": "LAADLIYAN | ਲਾਡਲੀਆਂ | EPISODE 68 | लाडलियां | لاڈلیاں | #mrmrsdevgan #punjabiwebseries #drama #mindo",
    "score": 10
  },
  {
    "id": "cTqchylnVz8",
    "title": "BABAL DA VEHRA EP 100 | MR MRS DEVGAN | DEV MINDO  | NEW PUNJABI WEB SERIES | #punjabiwebseries",
    "score": 10
  },
  {
    "id": "910qY_VGl2A",
    "title": "BABAL DA VEHRA EP18 | MR MRS DEVGAN | HARMINDER MINDO | NEW PUNJABI WEB SERIES | #punjabiwebseries",
    "score": 10
  },
  {
    "id": "6C6Gmgss3w0",
    "title": "Choti Nuh ਛੋਟੀ ਨੂੰਹ | Full Season 1 | New Punjabi Webseries | Latest Punjabi Webseries 2025",
    "score": 10
  },
  {
    "id": "Bw8a9O-cmi0",
    "title": "Search filters",
    "score": 10
  },
  {
    "id": "hjHeq_FmYRw",
    "title": "IV of Spades reveals the changes after Unique left | TWBA",
    "score": 10
  },
  {
    "id": "23bFigYYK6w",
    "title": "TWBA: Tito Boy asks Toni why she didn't end up with Luis",
    "score": 10
  },
  {
    "id": "eltS3O7lAeM",
    "title": "TWBA: Robin thinks Sharon didn't like their kissing scene",
    "score": 10
  },
  {
    "id": "8R9cJAY93Ns",
    "title": "TWBA: Sharon Cuneta admits they did not receive inheritance from her parents",
    "score": 10
  },
  {
    "id": "C8FT2QCwlkc",
    "title": "TWBA: Karla admits that she didn't like to talk about her love life",
    "score": 10
  },
  {
    "id": "2XKI75tChTY",
    "title": "TWBA: Candy says she didn't get support from her child's father",
    "score": 10
  },
  {
    "id": "_rmbrrAox5s",
    "title": "TWBA: Nanette shares why she didn't want to marry",
    "score": 10
  },
  {
    "id": "FnJxpWVuXCA",
    "title": "TWBA: Paulo says that he didn't want to be famous",
    "score": 10
  },
  {
    "id": "e-letgdQPxo",
    "title": "Intro",
    "score": 10
  },
  {
    "id": "B9ikJeunTSo",
    "title": "TWBA: Unique reveals why he decided to leave IV of Spades",
    "score": 10
  },
  {
    "id": "3WBUM_uaDi0",
    "title": "Vice Ganda gets annoyed with Bea and Angelica | GGV",
    "score": 10
  },
  {
    "id": "PCZhqNSjdmY",
    "title": "Di Na Natuto (Sorry na, Pwede Ba?) FULL MOVIE HD | Robin Padilla, Sharon Cuneta",
    "score": 10
  },
  {
    "id": "WRmi6OUUIhE",
    "title": "Why Piolo Considered Quitting Showbiz While Filming Starting Over Again | Toni Talks",
    "score": 10
  },
  {
    "id": "R_0A7ljGMGU",
    "title": "Toni at Piolo, may ni-reveal tungkol sa kanilang past | GGV",
    "score": 10
  },
  {
    "id": "qAkKIAT3xk4",
    "title": "They Didn’t Know What They’d Created",
    "score": 10
  },
  {
    "id": "LWqCCAB8yVU",
    "title": "ANGELICA PANGANIBAN’s Road To Healing \\u0026 Finding Happiness! | Karen Davila Ep234",
    "score": 10
  },
  {
    "id": "xVVWW8AqMd4",
    "title": "Magandang Buhay: Jaya expresses her gratefulness to Pilita",
    "score": 10
  },
  {
    "id": "f-prLhEePPw",
    "title": "TWBA: Regine Velasquez spills who the leading man she refused to work with was",
    "score": 10
  },
  {
    "id": "hZlHnMo7Mpg",
    "title": "TWBA: Fast Talk with Kris Aquino and Bimby Yap",
    "score": 10
  },
  {
    "id": "xwbgFsNSEOo",
    "title": "TWBA: Kim and Gerald on having closure",
    "score": 10
  },
  {
    "id": "kfFBFEkZMAw",
    "title": "Daniel Padilla shares how he avoids temptation | TWBA",
    "score": 10
  },
  {
    "id": "coygyJUmme8",
    "title": "TWBA: Iza reveals the real reason why she didn't throw the bouquet",
    "score": 10
  },
  {
    "id": "w6Fb3sUbbeI",
    "title": "TWBA Uncut Interview: IV of Spades",
    "score": 10
  },
  {
    "id": "ZDDwJxhYmxo",
    "title": "TWBA: Ebe Dancel shares the story behind the song \\\"Wag Ka Nang Umiyak\\\"",
    "score": 10
  },
  {
    "id": "xg2sQCQEESU",
    "title": "Edward proudly states that he didn't look at other girls | TWBA",
    "score": 10
  },
  {
    "id": "z2uNE5TI6uA",
    "title": "Search filters",
    "score": 10
  },
  {
    "id": "chi7ayNbjps",
    "title": "BOL MITTI DEYA BAWEYA | EPI 8 | ਬੋਲ ਮਿੱਟੀ ਦਿਆ ਬਾਵਿਆ #mrmrsdevgan #amardevgan  #punjabiwebseries",
    "score": 10
  },
  {
    "id": "N9HGJjz2-PA",
    "title": "BOL MITTI DEYA BAWEYA | EPI 9 | ਬੋਲ ਮਿੱਟੀ ਦਿਆ ਬਾਵਿਆ #mrmrsdevgan #amardevgan  #punjabiwebseries",
    "score": 10
  },
  {
    "id": "acgZZyMF4lU",
    "title": "ਮੇਰਾ ਕੀ ਕਸੂਰ | EPISODE 47 | MERA KI KASOOR | मेरा क्या कसूर | PUNJABI WEB SERIES | SHELLYRAJFILMS",
    "score": 10
  },
  {
    "id": "PcKk00Mp-LY",
    "title": "ਮਾਲਦਾਰ ਛੜਾ 222 MALDAR SHADA baghu shada latest SHORT MOVIE 2026 PUNJABI FILM JATT BEAT RECORD",
    "score": 10
  },
  {
    "id": "FOZplNjrS4s",
    "title": "ਸਾਂਝੇ ਟੱਬਰ ਦੇ ਪੁਆੜੇ | new punjabi movies2026|punjabi short videos@GHARPARIVARMANSA ",
    "score": 10
  },
  {
    "id": "AOsY7uXSE6c",
    "title": "35 ਲੱਖ ਵਾਲੀ ਨੂੰਹ | New punjabi short movie 2026 | Punjabi natak | Pendu virsa |@sanjhapariwarmansa",
    "score": 10
  },
  {
    "id": "P5pDOMkoQeA",
    "title": "ਲੱਗ ਗਿਆ ਵੀਜ਼ਾ !! Lagg gya visa !! New punjabi short film 2026 @lovepreetghumaan6 ",
    "score": 10
  },
  {
    "id": "yG4BoyJqgYs",
    "title": "ਆਖ਼ਰੀ ਉਡੀਕ part:20 (season-2) akhri udeek( new video)#thepunjab #sadapunjab #pannutvv",
    "score": 10
  },
  {
    "id": "O0hb0NZJXoI",
    "title": "LAADLIYAN | ਲਾਡਲੀਆਂ | EPISODE 28 | लाडलियां | لاڈلیاں | #mrmrsdevgan #punjabiwebseries #drama #mindo",
    "score": 10
  },
  {
    "id": "nAgT9i04Ia4",
    "title": "HANKAR TE PYAR EP-41 || ਹੰਕਾਰ ਤੇ ਪਿਆਰ ਭਾਗ-41 #kabbinooh #priyasinghpreet #viralvideos #punjabidrama ",
    "score": 10
  },
  {
    "id": "cq5AyESBiqU",
    "title": "LAADLIYAN | ਲਾਡਲੀਆਂ | EPISODE 67 | लाडलियां | لاڈلیاں | #mrmrsdevgan #punjabiwebseries #drama #mindo",
    "score": 10
  },
  {
    "id": "--gxNK3cETE",
    "title": "LAADLIYAN | ਲਾਡਲੀਆਂ | EPISODE 29 | लाडलियां | لاڈلیاں | #mrmrsdevgan #punjabiwebseries #drama #mindo",
    "score": 10
  },
  {
    "id": "7eDpzrtVegc",
    "title": "LAADLIYAN | ਲਾਡਲੀਆਂ | EPISODE 29 | लाडलियां | لاڈلیاں | #mrmrsdevgan #punjabiwebseries #drama #mindo",
    "score": 10
  },
  {
    "id": "sEbsOK7k-WE",
    "title": "Intro",
    "score": 10
  },
  {
    "id": "84xzZmQitIA",
    "title": "Pk Grills vs Weber (PK300 vs Weber Kettle Compared)",
    "score": 10
  },
  {
    "id": "Cg0zEditNz4",
    "title": "Intro",
    "score": 10
  },
  {
    "id": "1xbDElMO1hU",
    "title": "Intro",
    "score": 10
  },
  {
    "id": "d8obaDVsbKU",
    "title": "Bakit - Tagahari cover at Tribu Grill",
    "score": 10
  },
  {
    "id": "QQdkn7ijt6I",
    "title": "All Things Grills with Basco \\u0026 Blaze",
    "score": 10
  },
  {
    "id": "zgnNFqrDzoc",
    "title": "Rick Bayless: Grilling 101",
    "score": 10
  },
  {
    "id": "yPAeRiKa0h8",
    "title": "Grill Grates Are Important",
    "score": 10
  },
  {
    "id": "hBKy3u3mIFI",
    "title": "WEBER BABY Q:THINGS YOU SHOULDNT DO WITH WEBER Q",
    "score": 10
  },
  {
    "id": "tQXdBIrcESc",
    "title": "Bakit nasa loob ang aming window grills. #windowgrill #windowgrills",
    "score": 10
  },
  {
    "id": "hpGbAsbpWfM",
    "title": "BBQ Life Hack: #DawnPowerwash will be your BFF this grilling season! Link in comments! #DawnPartner",
    "score": 10
  },
  {
    "id": "bamcAMHdroA",
    "title": "Best BBQ Grills 2025 - Top BBQ Grills Everyone Needs To Have!",
    "score": 10
  },
  {
    "id": "JjODmNkfEUI",
    "title": "Gas Grill Burner Flames Blowing Out Or Looking Yellow and Wavy?",
    "score": 10
  },
  {
    "id": "1v1daqdFcZ8",
    "title": "Thaan Charcoal Grill #bbqgrills",
    "score": 10
  },
  {
    "id": "-XtoVpjM4kI",
    "title": "Search filters",
    "score": 10
  },
  {
    "id": "VwRfwcCNwvM",
    "title": "LUIS LISTENS TO AGA MUHLACH (At the end of the day lahat naman naghahanap ng trabaho) | Luis Manzano",
    "score": 10
  },
  {
    "id": "Ehs5xMYuqOo",
    "title": "LUIS LISTENS TO AIKO MELENDEZ (Magagaling kasama mo, so bawal ang t*nga sa acting) | Luis Manzano",
    "score": 10
  },
  {
    "id": "8aIjwzCqscM",
    "title": "LUIS LISTENS TO BOY ABUNDA (This pain is the only thing that connects me to my mother)| Luis Manzano",
    "score": 10
  },
  {
    "id": "oGCyB_H7h8Q",
    "title": "LUIS LISTENS TO JANICE, GELLI \\u0026 CANDY (Ang galing niya magkwento ng mga chismis) | Luis Manzano",
    "score": 10
  },
  {
    "id": "vKwfGwYnZfE",
    "title": "LUIS LISTENS TO KAILA ESTRADA (When I started taping, doon ko na-realize na mahirap) | Luis Manzano",
    "score": 10
  },
  {
    "id": "v8cumxD0HVo",
    "title": "10 Pinaka MAYAMAN na Senador sa Pilipinas | Richest SENATORS",
    "score": 10
  },
  {
    "id": "dwR9cUyE0ps",
    "title": "CRISTY FERMINUTE | FEBRUARY 5, 2026",
    "score": 10
  },
  {
    "id": "x93qPJwt6kc",
    "title": "Balitanghali: February 5, 2026 (Part 1)",
    "score": 10
  },
  {
    "id": "jLwzPvKFJRo",
    "title": "“Pumapalakpak” ang China kay Sen. Marcoleta! Bwisit ang Kaniyang mga Kasamahan!",
    "score": 10
  },
  {
    "id": "J2QHrxxKCy0",
    "title": "LUIS LISTENS TO POKWANG (May nakikita na akong mga red flags, pinabayaan ko lang) | Luis Manzano",
    "score": 10
  },
  {
    "id": "r2D0UIjqs9g",
    "title": "LUIS LISTENS TO EULEEN CASTRO A.K.A PAMBANSANG YOBAB (Natanggap ko na sa sarili ko) | Luis Manzano",
    "score": 10
  },
  {
    "id": "vy_XG6JVn1A",
    "title": "LUIS LISTENS TO JENNICA GARCIA (Nakakaiyak na naka-aircon po ako, tapos sila hindi) | Luis Manzano",
    "score": 10
  },
  {
    "id": "bUDfK_V7f7w",
    "title": "LUIS LISTENS TO ALDEN RICHARDS \\u0026 JULIA MONTES + FILIPINO FOOD MUKBANG | Luis Manzano",
    "score": 10
  },
  {
    "id": "mxSMdns4gSY",
    "title": "LUIS LISTENS TO CLAUDINE BARRETTO (Your Mom, Vilma Santos saved my life.) | Luis Manzano",
    "score": 10
  },
  {
    "id": "1ZGGe3x8K80",
    "title": "LUIS LISTENS TO MATTEO GUIDICELLI (Marriage is not easy) | Luis Manzano",
    "score": 10
  },
  {
    "id": "FODH00ZRLGQ",
    "title": "LUIS LISTENS TO MOMSKI'S REVELATIONS | Luis Manzano",
    "score": 10
  },
  {
    "id": "CrFZqdwDL3c",
    "title": "LUIS LISTENS TO BELA PADILLA (Nilagnat ako to the point na I wanted to quit showbiz.) | Luis Manzano",
    "score": 10
  },
  {
    "id": "hI8FZ7iYs1s",
    "title": "Search filters",
    "score": 10
  },
  {
    "id": "bwM5yjjtO0A",
    "title": "LUIS LISTENS TO ELIZA BORROMEO (Second attempt ko po; sobrang pangarap ko po ang PBB) | Luis Manzano",
    "score": 10
  },
  {
    "id": "1s4rxSFfIAI",
    "title": "LUIS LISTENS TO RICA PERALEJO (Buong buhay ang ibinigay mo…One day, I don’t want it.) | Luis Manzano",
    "score": 10
  },
  {
    "id": "YNO69BMHTLo",
    "title": "BAKASYON SA BANGKOK + BIRTHDAY NI MOMSKI | Luis Manzano",
    "score": 10
  },
  {
    "id": "umLIL93rX6U",
    "title": "Elevated tyson push ups - weighted tip toe squat jumps - high muay in and out knees 👍👍👍",
    "score": 10
  },
  {
    "id": "8XzK3QZvoUw",
    "title": "FIGHTER MODE ON with MARK \\\"MUGEN\\\" STRIEGL | Luis Manzano",
    "score": 10
  },
  {
    "id": "f5ulJOdWw3A",
    "title": "LUIS LISTENS TO RICA PERALEJO (Buong buhay ang ibinigay mo…One day, I don’t want it.) | Luis Manzano",
    "score": 10
  },
  {
    "id": "WdmSDECk3aY",
    "title": "BAYANI AGBAYANI'S P.A. FOR A DAY | Luis Manzano",
    "score": 10
  },
  {
    "id": "LQzRukZdDzc",
    "title": "MOMSKI vs WIFEY: WHO KNOWS ME BETTER? | Luis Manzano",
    "score": 10
  },
  {
    "id": "p3HcHWwneBM",
    "title": "LUIS LISTENS TO BERNADETTE SEMBRANO (Passion, Purpose \\u0026 Inevitable Goodbyes) | Luis Manzano",
    "score": 10
  },
  {
    "id": "RYQnQkhIWO0",
    "title": "LUIS LISTENS TO MOMSKI'S REVELATIONS | Luis Manzano",
    "score": 10
  },
  {
    "id": "Xlh6N3e-g54",
    "title": "HEART-TO-HEART TALK WITH MOMSKI | Luis Manzano",
    "score": 10
  },
  {
    "id": "ZQZkG81YfNg",
    "title": "LUIS LISTENS TO EMPOY MARQUEZ (Masaya ako na may napuntahan yun mga pinaghirapan ko) | Luis Manzano",
    "score": 10
  },
  {
    "id": "J_22djIkgik",
    "title": "LUIS LISTENS TO NEGI \\u0026 PETITE (Yung mga hindi ko ginagawa, pinapagawa niya sa akin) | Luis Manzano",
    "score": 10
  },
  {
    "id": "XB4G_EUCRdI",
    "title": "NAAGRABYADO SI MOMSKI! (Huling Kulitan muna with the Family) | Luis Manzano",
    "score": 10
  },
  {
    "id": "pQxWlr3GNsQ",
    "title": "THE CONVERSATION I NEVER HAD with DADDY YOW | Luis Manzano",
    "score": 10
  },
  {
    "id": "W8F1WaOY1to",
    "title": "Search filters",
    "score": 10
  },
  {
    "id": "u6uwDbCOphs",
    "title": "BOL MITTI DEYA BAWEYA | EPI 58 | ਬੋਲ ਮਿੱਟੀ ਦਿਆ ਬਾਵਿਆ #mrmrsdevgan #amardevgan  #punjabiwebseries",
    "score": 10
  },
  {
    "id": "_KF_2zkWPU8",
    "title": "BOL MITTI DEYA BAWEYA | EPI 11 | ਬੋਲ ਮਿੱਟੀ ਦਿਆ ਬਾਵਿਆ #mrmrsdevgan #amardevgan  #punjabiwebseries",
    "score": 10
  },
  {
    "id": "jcr6v3YnYZ8",
    "title": "BOL MITTI DEYA BAWEYA | EPI 37 | ਬੋਲ ਮਿੱਟੀ ਦਿਆ ਬਾਵਿਆ #mrmrsdevgan #amardevgan  #punjabiwebseries",
    "score": 10
  },
  {
    "id": "aUqkwsQkXIA",
    "title": "BOL MITTI DEYA BAWEYA | EPI 23 | ਬੋਲ ਮਿੱਟੀ ਦਿਆ ਬਾਵਿਆ #mrmrsdevgan #amardevgan  #punjabiwebseries",
    "score": 10
  },
  {
    "id": "gMHumK_xEpE",
    "title": "ਮੇਰਾ ਕੀ ਕਸੂਰ | EPISODE 47 | MERA KI KASOOR | मेरा क्या कसूर | PUNJABI WEB SERIES | SHELLYRAJFILMS",
    "score": 10
  },
  {
    "id": "8XKb--fRWfY",
    "title": "ਵਿਧਵਾਂ ਦੀ ਜ਼ਿੰਦਗੀ (ਭਾਗ -24) widwa di zindagi ( part-24)#maanpurtv ",
    "score": 10
  },
  {
    "id": "Ra6CbqabdW0",
    "title": "35 ਲੱਖ ਵਾਲੀ ਨੂੰਹ | New punjabi short movie 2026 | Punjabi natak | Pendu virsa |@sanjhapariwarmansa",
    "score": 10
  },
  {
    "id": "VlpNHvgI1R0",
    "title": "BOL MITTI DEYA BAWEYA | EPI 22 | ਬੋਲ ਮਿੱਟੀ ਦਿਆ ਬਾਵਿਆ #mrmrsdevgan #amardevgan  #punjabiwebseries",
    "score": 10
  },
  {
    "id": "iq6D9Oczoys",
    "title": "BOL MITTI DEYA BAWEYA | EPI 14 | ਬੋਲ ਮਿੱਟੀ ਦਿਆ ਬਾਵਿਆ #mrmrsdevgan #amardevgan  #punjabiwebseries",
    "score": 10
  },
  {
    "id": "16kgDqN0SWs",
    "title": "LAADLIYAN | ਲਾਡਲੀਆਂ | EPISODE 69 | लाडलियां | لاڈلیاں | #mrmrsdevgan #punjabiwebseries #drama #mindo",
    "score": 10
  },
  {
    "id": "DMFkmTpFc90",
    "title": "BOL MITTI DEYA BAWEYA | EPI 33 | ਬੋਲ ਮਿੱਟੀ ਦਿਆ ਬਾਵਿਆ #mrmrsdevgan #amardevgan  #punjabiwebseries",
    "score": 10
  },
  {
    "id": "cZ_4hr9hqVQ",
    "title": "LAADLIYAN | ਲਾਡਲੀਆਂ | EPISODE 66 | लाडलियां | لاڈلیاں | #mrmrsdevgan #punjabiwebseries #drama #mindo",
    "score": 10
  },
  {
    "id": "9ZzEn3K9zD0",
    "title": "BOL MITTI DEYA BAWEYA | EPI 42 | ਬੋਲ ਮਿੱਟੀ ਦਿਆ ਬਾਵਿਆ #mrmrsdevgan #amardevgan  #punjabiwebseries",
    "score": 10
  },
  {
    "id": "otzFPvl_wdA",
    "title": "BOL MITTI DEYA BAWEYA | EPI 40 | ਬੋਲ ਮਿੱਟੀ ਦਿਆ ਬਾਵਿਆ #mrmrsdevgan #amardevgan  #punjabiwebseries",
    "score": 10
  },
  {
    "id": "CbxCcr7FfpY",
    "title": "Sokhe Wele Sare Aukhe Wele ? - Mr Mrs Devgan - Mindo Devgan",
    "score": 10
  },
  {
    "id": "fNoQvEvFHhM",
    "title": "Search filters",
    "score": 10
  },
  {
    "id": "VepO625T-_8",
    "title": "LAADLIYAN | ਲਾਡਲੀਆਂ | EPISODE 18 | लाडलियां | لاڈلیاں | #mrmrsdevgan #punjabiwebseries #drama #mindo",
    "score": 10
  },
  {
    "id": "dmsqn1ItLIs",
    "title": "Search filters",
    "score": 10
  },
  {
    "id": "Fg9vUn4VpF4",
    "title": "Ginataang  Alimasag Recipe! Crab In Coconut Milk",
    "score": 10
  },
  {
    "id": "XMHfpgm4El4",
    "title": "Catching Lambay, Alimasag, or Blue Crabs using \\\"Sapyaw\\\" [Catch \\u0026 Cook] Garlic Crabs Recipe",
    "score": 10
  },
  {
    "id": "HEaWhBRQPuM",
    "title": "Tortang Alimasag (Crab Omelet)",
    "score": 10
  },
  {
    "id": "wepaJHc_suQ",
    "title": "GANITO PALA ANG MASARAP NA LUTO SA ALIMASAG! KAKAIBA ANG SARAP AT LINAMNAM NITO!",
    "score": 10
  },
  {
    "id": "ziqev4OI7FU",
    "title": "NAPAKAAMO NILA ALIMASAG ADVENTURE",
    "score": 10
  },
  {
    "id": "4RUORK565b4",
    "title": "Rellenong Alimasag Recipe",
    "score": 10
  },
  {
    "id": "rJWY7EOfZkI",
    "title": "2 tbsp white onion, chopped",
    "score": 10
  },
  {
    "id": "zdUFixG0RPo",
    "title": "Rellenong Alimasag",
    "score": 10
  },
  {
    "id": "5gDNKIiiBEk",
    "title": "DUNGENESS CRAB",
    "score": 10
  },
  {
    "id": "zxTbJyDrgrg",
    "title": "GIANT MUDCRAB barehanded catch for ISLAND SURVIVAL",
    "score": 10
  },
  {
    "id": "qyPqCNPFmhU",
    "title": "Ginataang Alimasag | Blue Crab with String Beans and Squash",
    "score": 10
  },
  {
    "id": "OxtIR65xa68",
    "title": "🦀 Crab Farmer Drains Pond to Reveal Hidden Crabs Behind Concrete Blocks! 👀",
    "score": 10
  },
  {
    "id": "BquO389SkRA",
    "title": "GAWIN MO ITO MAPAPANGITI KA SA SARAP- RELLENONG ALIMASAG",
    "score": 10
  },
  {
    "id": "1huO35q5E4g",
    "title": "How Crab Trap Works Underwater! (📷:fishhunterkh)",
    "score": 10
  },
  {
    "id": "PJiSwh-IZuo",
    "title": "Halabos na Alimasag",
    "score": 10
  },
  {
    "id": "TLaOq9TayVQ",
    "title": "COOKING FRESH CRABS/ AYAW NILA SA ALIMASAG AT ALLERGIC SILA😅",
    "score": 10
  },
  {
    "id": "oVM3AkelxEE",
    "title": "Sarap Ang ulam nila alimasag(4)",
    "score": 10
  },
  {
    "id": "6bf4-fOJNO8",
    "title": "Sabi nila baka daw Ako ma allergy sa alimasag ,,,,,, no no no it’s so yummy",
    "score": 10
  },
  {
    "id": "bN2CtKQbr9A",
    "title": "Catching Giant Mud Crab Nabulabog Ang Lungga Nila😲",
    "score": 10
  },
  {
    "id": "B8qwily9x5g",
    "title": "Search filters",
    "score": 10
  },
  {
    "id": "vUs31S42oxk",
    "title": "Latest Punjabi Web Series | Shikaari Episode 1 | Guggu Gill | Chaupal | Punjabi Web Series",
    "score": 10
  },
  {
    "id": "naIb5Y7SoSg",
    "title": "LAADLIYAN | ਲਾਡਲੀਆਂ | EPISODE 8 | लाडलियां | لاڈلیاں | #mrmrsdevgan #punjabiwebseries #drama #mindo",
    "score": 10
  },
  {
    "id": "7XMjlAE7ix0",
    "title": "ਮੇਰਾ ਕੀ ਕਸੂਰ | EPISODE 47 | MERA KI KASOOR | मेरा क्या कसूर | PUNJABI WEB SERIES | SHELLYRAJFILMS",
    "score": 10
  },
  {
    "id": "dKdpQTvxbI0",
    "title": "ਧੀਆਂ ਦੇ ਦੁਸ਼ਮਣ -2 / Dheeyan De Dushman -2  | New Web Series 2026",
    "score": 10
  },
  {
    "id": "e7o56JnSGD0",
    "title": "ਆਖ਼ਰੀ ਉਡੀਕ part:20 (season-2) akhri udeek( new video)#thepunjab #sadapunjab #pannutvv",
    "score": 10
  },
  {
    "id": "n8Bby1fFuUE",
    "title": "Inquiry | Punjabi WebSeries | Ep 01| Latest Punjabi Movie Series | Hasrat Records 2025",
    "score": 10
  },
  {
    "id": "9DBksBKh7-Q",
    "title": "Introduction | Inquiry Web Series ਸ਼ੁਰੂ",
    "score": 10
  },
  {
    "id": "jeyJo26FIYY",
    "title": "LAADLIYAN | ਲਾਡਲੀਆਂ | EPISODE 66 | लाडलियां | لاڈلیاں | #mrmrsdevgan #punjabiwebseries #drama #mindo",
    "score": 10
  },
  {
    "id": "kthwQwi8Fc4",
    "title": "LAADLIYAN | ਲਾਡਲੀਆਂ | EPISODE 24 | लाडलियां | لاڈلیاں | #mrmrsdevgan #punjabiwebseries #drama #mindo",
    "score": 10
  }
]